Workbook
Name nproducto: [1]NPRODUCTOS!$J$9:$U$7009

Sheet Detalle1
A1: Detalles para Suma de FRECUENCIA ANUAL DE MANTENIMIENTO - CRÍTICO/ RELEVANTE / IM≥12 / NO APLICA: CRÍTICO, AÑO INGRESO A PLAN DE MANTENIMIENTO (2023 / 2024 / 2025 / 2026): 2023
A3: SERVICIO CLÍNICO | B3: RECINTO | C3: CLASE | D3: SUBCLASE | E3: NOMBRE EQUIPO | F3: MARCA | G3: MODELO | H3: SERIE | I3: N° INVENTARIO | J3: AÑO DE ADQUISICIÓN | K3: VIDA ÚTIL | L3: VIDA ÚTIL RESIDUAL | M3: PROPIO / ARRIENDO / COMODATO | N3: ESTADO (BUENO / REGULAR / MALO / BAJA) | O3: CRÍTICO/ RELEVANTE / IM≥12 / NO APLICA | P3: EN GARANTÍA (SI / NO) | Q3: AÑO VENCIMIENTO GARANTÍA | R3: BAJO PLAN DE MANTENIMIENTO (SI / NO) | S3: AÑO INGRESO A PLAN DE MANTENIMIENTO (2023 / 2024 / 2025 / 2026) | T3: MANTENIMIENTO INTERNO O MANTENIMIENTO EXTERNO O CONTRATO | U3: NOMBRE DE PROVEEDOR O MANTENIMIENTO INTERNO | V3: ID CONVENIO DE MANTENIMIENTO / ID DE REFERENCIA / COTIZACIÓN DE REFERENCIA | W3: COSTO ANUAL DE MANTENIMIENTO SEGÚN CONVENIO / PRECIO DE REFERENCIA MANTENIMIENTO ANUAL | X3: FRECUENCIA ANUAL DE MANTENIMIENTO
A4: UTI - 9D | B4: Hospital Penco Lirquen | C4: Apoyo Terapéutico | D4: Alto Costo | E4: Ventilador mecánico no Invasivo | F4: Philips | G4: Trilogy 202 | H4: TV016091214 | I4: HPL24850 | J4: 2016 | K4: 8 | L4: 1 | M4: Propio | N4: Bueno | O4: CRÍTICO | P4: NO | R4: SI | S4: 2023 | T4: EXTERNO | U4: TDM | V4: 1057540-65-LE21 | W4: 270000 | X4: 2
A5: Ambulancia | B5: Hospital Penco Lirquen | C5: Otros | D5: Alto Costo | E5: Ambulancia | F5: Mercedes - Benz | G5: Sprinter 315 | H5: FFRG-92 | I5: HPL29456 | J5: 2019 | K5: 8 | L5: 4 | M5: Propio | N5: Bueno | O5: CRÍTICO | P5: NO | R5: SI | S5: 2023 | T5: EXTERNO | U5: N/A | X5: 2
A6: Ambulancia | B6: Hospital Penco Lirquen | C6: Otros | D6: Alto Costo | E6: Ambulancia | F6: Mercedes - Benz | G6: Sprinter 315 | H6: FFRG-94 | I6: HPL29457 | J6: 2019 | K6: 8 | L6: 4 | M6: Propio | N6: Bueno | O6: CRÍTICO | P6: NO | R6: SI | S6: 2023 | T6: EXTERNO | U6: N/A | X6: 2
A7: Ambulancia | B7: Hospital Penco Lirquen | C7: Otros | D7: Alto Costo | E7: Ambulancia | F7: Mercedes - Benz | G7: Sprinter 314 | H7: PGHF-57 | I7: HPL29451 | J7: 2020 | K7: 8 | L7: 5 | M7: Propio | N7: Bueno | O7: CRÍTICO | P7: NO | R7: SI | S7: 2023 | T7: EXTERNO | U7: N/A | X7: 2
A8: Ambulancia - 6B | B8: Hospital Penco Lirquen | C8: Monitoreo | D8: Mediano Costo | E8: Desfibrilador externo automático (DEA) | F8: Mindray | G8: BeneHeart C2 | H8: AE7-01001130 | I8: HPL30209 | J8: 2020 | K8: 8 | L8: 5 | M8: Propio | N8: Bueno | O8: CRÍTICO | P8: NO | R8: SI | S8: 2023 | T8: INTERNO | U8: TECNICO EQM HPL | X8: 2
A9: Ambulancia - 7B | B9: Hospital Penco Lirquen | C9: Monitoreo | D9: Mediano Costo | E9: Monitor ECG Baja Complejidad | F9: Nihon Kohden | G9: SVM-7260 | H9: 00292 | I9: HPL30123 | J9: 2020 | K9: 8 | L9: 5 | M9: Propio | N9: Bueno | O9: CRÍTICO | P9: NO | R9: SI | S9: 2023 | T9: INTERNO | U9: TECNICO EQM HPL | X9: 2
A10: Ambulancia - 7B | B10: Hospital Penco Lirquen | C10: Monitoreo | D10: Mediano Costo | E10: Monitor de signos vitales | F10: Mindray | G10: DPM3 | H10: DQ-18000401 | I10: HPL30239 | J10: 2015 | K10: 8 | L10: 0 | M10: Propio | N10: Bueno | O10: CRÍTICO | P10: NO | R10: SI | S10: 2023 | T10: INTERNO | U10: TECNICO EQM HPL | X10: 2
A11: Ambulancia - 7B | B11: Hospital Penco Lirquen | C11: Monitoreo | D11: Mediano Costo | E11: Monitor ECG Baja Complejidad | F11: Mindray | G11: uMEC10 | H11: KN-03065493 | I11: HPL30261 | J11: 2020 | K11: 8 | L11: 5 | M11: Propio | N11: Bueno | O11: CRÍTICO | P11: NO | R11: SI | S11: 2023 | T11: INTERNO | U11: TECNICO EQM HPL | X11: 2
A12: Ambulancia -11 | B12: Hospital Penco Lirquen | C12: Monitoreo | D12: Mediano Costo | E12: Desfibrilador externo automático (DEA) | F12: Philips | G12: Heart Start | H12: A19K-06543 | I12: HPL30200 | J12: 2020 | K12: 8 | L12: 5 | M12: Propio | N12: Bueno | O12: CRÍTICO | P12: NO | R12: SI | S12: 2023 | T12: INTERNO | U12: TECNICO EQM HPL | X12: 2
A13: UTI - 9D | B13: Hospital Penco Lirquen | C13: Apoyo Terapéutico | D13: Alto Costo | E13: Ventilador mecánico no Invasivo | F13: Philips | G13: Trilogy 202 | H13: TV016091211 | I13: HPL24776 | J13: 2016 | K13: 8 | L13: 1 | M13: Propio | N13: Bueno | O13: CRÍTICO | P13: NO | R13: SI | S13: 2023 | T13: EXTERNO | U13: TDM | V13: 1057540-65-LE21 | W13: 270000 | X13: 2
A14: UTI - 1B | B14: Hospital Penco Lirquen | C14: Apoyo Terapéutico | D14: Alto Costo | E14: Ventilador mecánico Invasivo | F14: Aeonmed | G14: VG70 | H14: XZZT14086 | I14: HPL30403 | J14: 2020 | K14: 8 | L14: 5 | M14: Préstamo | N14: Bueno | O14: CRÍTICO | P14: NO | R14: SI | S14: 2023 | T14: EXTERNO | U14: TDM | V14: 1057540-65-LE21 | W14: 407911 | X14: 2
A15: UTI - 1B | B15: Hospital Penco Lirquen | C15: Apoyo Terapéutico | D15: Alto Costo | E15: Ventilador mecánico Invasivo | F15: Aeonmed | G15: VG70 | H15: XZZT13533 | I15: .- | J15: 2021 | K15: 8 | L15: 6 | M15: Préstamo | N15: Bueno | O15: CRÍTICO | R15: SI | S15: 2023 | X15: 2
A16: BODEGA DE EQUIPOS MÉDICOS | B16: Hospital Penco Lirquen | C16: Apoyo Terapéutico | D16: Alto Costo | E16: Ventilador mecánico Invasivo | F16: Aeonmed | G16: VG70 | H16: XZZT17062 | I16: HPL30404 | J16: 2020 | K16: 8 | L16: 5 | M16: Préstamo | N16: Bueno | O16: CRÍTICO | P16: NO | R16: SI | S16: 2023 | T16: EXTERNO | V16: LIC 5 | W16: 407911 | X16: 2
A17: BODEGA DE EQUIPOS MÉDICOS - 1B | B17: Hospital Penco Lirquen | C17: Apoyo Terapéutico | D17: Alto Costo | E17: Ventilador mecánico Invasivo | F17: MECKics | G17: MV2000-EVO 5 | H17: MV2000UA1C0315 | I17: HPL30269 | J17: 2021 | K17: 8 | L17: 6 | M17: Préstamo | N17: Bueno | O17: CRÍTICO | P17: SI | R17: SI | S17: 2023 | T17: EXTERNO | V17: LIC 5 | W17: 407911 | X17: 2
A18: BODEGA DE EQUIPOS MÉDICOS - 1B | B18: Hospital Penco Lirquen | C18: Apoyo Terapéutico | D18: Alto Costo | E18: Ventilador mecánico Invasivo | F18: MECKics | G18: MV2000-EVO 5 | H18: MV2000UA1C0316 | I18: HPL30270 | J18: 2021 | K18: 8 | L18: 6 | M18: Préstamo | N18: Bueno | O18: CRÍTICO | P18: SI | R18: SI | S18: 2023 | T18: EXTERNO | V18: LIC 5 | W18: 407911 | X18: 2
A19: BODEGA DE EQUIPOS MÉDICOS - 1B | B19: Hospital Penco Lirquen | C19: Apoyo Terapéutico | D19: Alto Costo | E19: Ventilador mecánico Invasivo | F19: MECKics | G19: MV2000-EVO 5 | H19: MV2000UA1C0317 | I19: HPL30271 | J19: 2021 | K19: 8 | L19: 6 | M19: Préstamo | N19: Bueno | O19: CRÍTICO | P19: SI | R19: SI | S19: 2023 | T19: EXTERNO | V19: LIC 5 | W19: 407911 | X19: 2
A20: BODEGA DE EQUIPOS MÉDICOS - 1B | B20: Hospital Penco Lirquen | C20: Apoyo Terapéutico | D20: Alto Costo | E20: Ventilador mecánico Invasivo | F20: MECKics | G20: MV2000-EVO 5 | H20: MV2000UA1C0549 | I20: HPL30272 | J20: 2021 | K20: 8 | L20: 6 | M20: Préstamo | N20: Bueno | O20: CRÍTICO | P20: SI | R20: SI | S20: 2023 | T20: EXTERNO | V20: LIC 5 | W20: 407911 | X20: 2
A21: Bodega de Equipos Médicos - 6B | B21: Hospital Penco Lirquen | C21: Monitoreo | D21: Mediano Costo | E21: Desfibrilador externo automático (DEA) | F21: Philips | G21: Heart Start | H21: A15G-08197 | I21: HPL30196 | J21: 2015 | K21: 8 | L21: 0 | M21: Propio | N21: Bueno | O21: CRÍTICO | P21: NO | R21: SI | S21: 2023 | T21: INTERNO | U21: TECNICO EQM HPL | X21: 2
A22: UTI - 1B | B22: Hospital Penco Lirquen | C22: Apoyo Terapéutico | D22: Alto Costo | E22: Ventilador mecánico Invasivo | F22: Aeonmed | G22: VG70 | H22: XZZT11901 | I22: HPL30402 | J22: 2020 | K22: 8 | L22: 5 | M22: Préstamo | N22: Bueno | O22: CRÍTICO | P22: NO | R22: SI | S22: 2023 | T22: EXTERNO | U22: TDM | V22: LIC 5 | W22: 407911 | X22: 2
A23: UTI - 1B | B23: Hospital Penco Lirquen | C23: Apoyo Terapéutico | D23: Alto Costo | E23: Ventilador mecánico Invasivo | F23: Aeonmed | G23: VG70 | H23: XZZS27794 | I23: .- | J23: 2021 | K23: 8 | L23: 6 | M23: Préstamo | N23: Bueno | O23: CRÍTICO | R23: SI | S23: 2023 | T23: EXTERNO | X23: 2
A24: UTI - 1B | B24: Hospital Penco Lirquen | C24: Apoyo Terapéutico | D24: Alto Costo | E24: Ventilador mecánico Invasivo | F24: Philips | G24: Trilogy 100 | H24: TV11909271B | I24: HPL30385 | J24: 2020 | K24: 8 | L24: 5 | M24: Préstamo | N24: Bueno | O24: CRÍTICO | P24: NO | R24: SI | S24: 2023 | T24: EXTERNO | U24: TDM | V24: 1057540-65-LE21 | W24: 270000 | X24: 2
A25: UTI - 1B | B25: Hospital Penco Lirquen | C25: Apoyo Terapéutico | D25: Alto Costo | E25: Ventilador mecánico Invasivo | F25: MECKics | G25: MV2000-EVO 5 | H25: MV2000UA1C0551 | I25: HPL30273 | J25: 2021 | K25: 8 | L25: 6 | M25: Préstamo | N25: Bueno | O25: CRÍTICO | P25: NO | R25: SI | S25: 2023 | T25: EXTERNO | V25: LIC 5 | W25: 407911 | X25: 2
A26: UTI - 1B | B26: Hospital Penco Lirquen | C26: Monitoreo | D26: Mediano Costo | E26: Monitor desfibrilador con carro de paro | F26: Zoll | G26: Serie R ALS | H26: AF20F118297 | I26: HPL30215 | J26: 2020 | K26: 8 | L26: 5 | M26: Propio | N26: Bueno | O26: CRÍTICO | P26: NO | R26: SI | S26: 2023 | T26: INTERNO | U26: TECNICO EQM HPL | X26: 2
A27: UTI - 1B | B27: Hospital Penco Lirquen | C27: Apoyo Terapéutico | D27: Alto Costo | E27: Ventilador mecánico no Invasivo | F27: Covidien | G27: Puritan Bennet 560 | H27: 40966N0858 | I27: HPL30188 | J27: 2020 | K27: 8 | L27: 5 | M27: Préstamo | N27: Bueno | O27: CRÍTICO | P27: NO | R27: SI | S27: 2023 | T27: EXTERNO | V27: LIC 5 | W27: 1039250 | X27: 2
A28: Bodega equipos médicos - 1A | B28: Hospital Penco Lirquen | C28: Monitoreo | D28: Alto Costo | E28: Monitor ECG mediana complejidad | F28: Nihon Kohden | G28: BSM-6301K | H28: 8352 | I28: HPL29882 | J28: 2017 | K28: 8 | L28: 2 | M28: Propio | N28: Bueno | O28: CRÍTICO | P28: NO | R28: SI | S28: 2023 | T28: INTERNO | U28: TECNICO EQM HPL | X28: 2
A29: Bodega equipos médicos - 1A | B29: Hospital Penco Lirquen | C29: Monitoreo | D29: Alto Costo | E29: Monitor ECG mediana complejidad | F29: Nihon Kohden | G29: BSM-6301K | H29: 8353 | I29: HPL25047 | J29: 2017 | K29: 8 | L29: 2 | M29: Propio | N29: Bueno | O29: CRÍTICO | P29: NO | R29: SI | S29: 2023 | T29: INTERNO | U29: TECNICO EQM HPL | X29: 2
A30: Bodega equipos médicos - 1A | B30: Hospital Penco Lirquen | C30: Monitoreo | D30: Alto Costo | E30: Monitor ECG mediana complejidad | F30: Nihon Kohden | G30: BSM-6301K | H30: 8357 | I30: HPL29885 | J30: 2017 | K30: 8 | L30: 2 | M30: Propio | N30: Bueno | O30: CRÍTICO | P30: NO | R30: SI | S30: 2023 | T30: INTERNO | U30: TECNICO EQM HPL | X30: 2
A31: UTI - 1B | B31: Hospital Penco Lirquen | C31: Apoyo Terapéutico | D31: Alto Costo | E31: Ventilador mecánico no Invasivo | F31: Covidien | G31: Puritan Bennet 560 | H31: 40966N0851 | I31: HPL30187 | J31: 2020 | K31: 8 | L31: 5 | M31: Préstamo | N31: Bueno | O31: CRÍTICO | P31: NO | R31: SI | S31: 2023 | T31: EXTERNO | V31: LIC 5 | W31: 1039250 | X31: 2
A32: UTI - 1A | B32: Hospital Penco Lirquen | C32: Monitoreo | D32: Alto Costo | E32: Monitor ECG mediana complejidad (pequeño adosado a 03726 ) | F32: Nihon Kohden | G32: BSM-1763K | H32: 8528 | J32: 2023 | K32: 8 | L32: 8 | M32: Préstamo | N32: Bueno | O32: CRÍTICO | P32: NO | R32: SI | S32: 2023 | T32: INTERNO | U32: TECNICO EQM HPL | X32: 2
A33: UTI - 1A | B33: Hospital Penco Lirquen | C33: Monitoreo | D33: Alto Costo | E33: Monitor ECG mediana complejidad (pequeño adosado a 03726 ) | F33: Nihon Kohden | G33: BSM-1763K | H33: 08701 | I33: HPL30135 | J33: 2021 | K33: 8 | L33: 6 | M33: Propio | N33: Bueno | O33: CRÍTICO | P33: NO | R33: SI | S33: 2023 | T33: INTERNO | U33: TECNICO EQM HPL | X33: 2
A34: Bodega equipos médicos - 9C | B34: Hospital Penco Lirquen | C34: Monitoreo | D34: Mediano Costo | E34: Monitor desfibrilador con carro de paro | F34: Schiller | G34: Defigard 4000 | H34: 108994104698 | I34: HPL30092 | J34: 2015 | K34: 8 | L34: 0 | M34: Propio | N34: Bueno | O34: CRÍTICO | P34: NO | R34: SI | S34: 2023 | T34: INTERNO | U34: TECNICO EQM HPL | X34: 2
A35: UTI - 1A | B35: Hospital Penco Lirquen | C35: Monitoreo | D35: Alto Costo | E35: Monitor ECG mediana complejidad (pequeño adosado a 03714) | F35: Nihon Kohden | G35: BSM-1763K | H35: 08699 | I35: HPL30134 | J35: 2021 | K35: 8 | L35: 6 | M35: Propio | N35: Bueno | O35: CRÍTICO | P35: NO | R35: SI | S35: 2023 | T35: INTERNO | U35: TECNICO EQM HPL | X35: 2
A36: UTI - 1A | B36: Hospital Penco Lirquen | C36: Monitoreo | D36: Alto Costo | E36: Monitor ECG mediana complejidad (pequeño adosado a 03717) | F36: Nihon Kohden | G36: BSM-1763K | H36: 08697 | I36: HPL30133 | J36: 2021 | K36: 8 | L36: 6 | M36: Propio | N36: Bueno | O36: CRÍTICO | P36: NO | R36: SI | S36: 2023 | T36: INTERNO | U36: TECNICO EQM HPL | X36: 2
A37: UTI - 1A | B37: Hospital Penco Lirquen | C37: Monitoreo | D37: Alto Costo | E37: Monitor ECG mediana complejidad (pequeño adosado a 03740) | F37: Nihon Kohden | G37: BSM-1763K | H37: 08694 | I37: HPL30132 | J37: 2021 | K37: 8 | L37: 6 | M37: Propio | N37: Bueno | O37: CRÍTICO | P37: NO | R37: SI | S37: 2023 | T37: INTERNO | U37: TECNICO EQM HPL | X37: 2
A38: UTI - 1A | B38: Hospital Penco Lirquen | C38: Monitoreo | D38: Alto Costo | E38: Monitor ECG mediana complejidad | F38: Nihon Kohden | G38: CSM-1502 | H38: 03740 | I38: HPL30129 | J38: 2021 | K38: 8 | L38: 6 | M38: Propio | N38: Bueno | O38: CRÍTICO | P38: NO | R38: SI | S38: 2023 | T38: INTERNO | U38: TECNICO EQM HPL | X38: 2
A39: UTI - 1A | B39: Hospital Penco Lirquen | C39: Monitoreo | D39: Alto Costo | E39: Monitor ECG mediana complejidad | F39: Nihon Kohden | G39: CSM-1502 | H39: 03739 | I39: HPL30128 | J39: 2021 | K39: 8 | L39: 6 | M39: Propio | N39: Bueno | O39: CRÍTICO | P39: NO | R39: SI | S39: 2023 | T39: INTERNO | U39: TECNICO EQM HPL | X39: 2
A40: UTI - 1A | B40: Hospital Penco Lirquen | C40: Monitoreo | D40: Alto Costo | E40: Monitor ECG mediana complejidad | F40: Nihon Kohden | G40: CSM-1502 | H40: 03726 | I40: HPL30127 | J40: 2021 | K40: 8 | L40: 6 | M40: Propio | N40: Bueno | O40: CRÍTICO | P40: NO | R40: SI | S40: 2023 | T40: INTERNO | U40: TECNICO EQM HPL | X40: 2
A41: UTI - 1A | B41: Hospital Penco Lirquen | C41: Monitoreo | D41: Alto Costo | E41: Monitor ECG mediana complejidad | F41: Nihon Kohden | G41: CSM-1502 | H41: 03723 | I41: HPL30126 | J41: 2021 | K41: 8 | L41: 6 | M41: Propio | N41: Bueno | O41: CRÍTICO | P41: NO | R41: SI | S41: 2023 | T41: INTERNO | U41: TECNICO EQM HPL | X41: 2
A42: UTI - 1A | B42: Hospital Penco Lirquen | C42: Monitoreo | D42: Alto Costo | E42: Monitor ECG mediana complejidad | F42: Nihon Kohden | G42: CSM-1502 | H42: 03717 | I42: HPL30125 | J42: 2021 | K42: 8 | L42: 6 | M42: Propio | N42: Bueno | O42: CRÍTICO | P42: NO | R42: SI | S42: 2023 | T42: INTERNO | U42: TECNICO EQM HPL | X42: 2
A43: UTI - 1A | B43: Hospital Penco Lirquen | C43: Monitoreo | D43: Alto Costo | E43: Monitor ECG mediana complejidad | F43: Nihon Kohden | G43: CSM-1502 | H43: 03714 | I43: HPL30124 | J43: 2021 | K43: 8 | L43: 6 | M43: Propio | N43: Bueno | O43: CRÍTICO | P43: NO | R43: SI | S43: 2023 | T43: INTERNO | U43: TECNICO EQM HPL | X43: 2
A44: UTI - 1A | B44: Hospital Penco Lirquen | C44: Monitoreo | D44: Alto Costo | E44: Monitor multiparametros transporte | F44: Nihon Kohden | G44: BSM - 1763K | H44: 6678 | I44: HPL29879 | J44: 2020 | K44: 8 | L44: 5 | M44: Propio | N44: Bueno | O44: CRÍTICO | P44: NO | R44: SI | S44: 2023 | T44: INTERNO | U44: TECNICO EQM HPL | X44: 2
A45: Urgencia - 7B | B45: Hospital Penco Lirquen | C45: Monitoreo | D45: Mediano Costo | E45: Monitor ECG Baja Complejidad | F45: General Electric | G45: B20 | H45: SGF15151303WA | I45: HPL30370 | J45: 2016 | K45: 8 | L45: 1 | M45: Propio | N45: Bueno | O45: CRÍTICO | P45: NO | R45: SI | S45: 2023 | T45: INTERNO | U45: TECNICO EQM HPL | X45: 2
A46: Urgencia - 7B | B46: Hospital Penco Lirquen | C46: Monitoreo | D46: Mediano Costo | E46: Monitor ECG Baja Complejidad | F46: General Electric | G46: B20 | H46: SGF15131190WA | I46: HPL30369 | J46: 2015 | K46: 8 | L46: 0 | M46: Propio | N46: Bueno | O46: CRÍTICO | P46: NO | R46: SI | S46: 2023 | T46: INTERNO | U46: TECNICO EQM HPL | X46: 2
A47: Urgencia - 7B | B47: Hospital Penco Lirquen | C47: Monitoreo | D47: Mediano Costo | E47: Monitor ECG Baja Complejidad | F47: Fukuda Denshi | G47: Dinascope DSL-8001 | H47: 50200469 | I47: HPL30044 | J47: 2016 | K47: 8 | L47: 1 | M47: Propio | N47: Bueno | O47: CRÍTICO | P47: NO | R47: SI | S47: 2023 | T47: INTERNO | U47: TECNICO EQM HPL | X47: 2
A48: Urgencia - 7B | B48: Hospital Penco Lirquen | C48: Monitoreo | D48: Mediano Costo | E48: Monitor ECG Baja Complejidad | F48: Fukuda Denshi | G48: Dinascope DSL-8001 | H48: 50200457 | I48: HPL30039 | J48: 2016 | K48: 8 | L48: 1 | M48: Propio | N48: Bueno | O48: CRÍTICO | P48: NO | R48: SI | S48: 2023 | T48: INTERNO | U48: TECNICO EQM HPL | X48: 2
A49: Urgencia - 7A | B49: Hospital Penco Lirquen | C49: Monitoreo | D49: Mediano Costo | E49: Monitor ECG Baja Complejidad | F49: Fukuda Denshi | G49: Dinascope DSL-8001 | H49: 50200455 | I49: HPL30037 | J49: 2016 | K49: 8 | L49: 1 | M49: Propio | N49: Bueno | O49: CRÍTICO | P49: NO | R49: SI | S49: 2023 | T49: INTERNO | U49: TECNICO EQM HPL | X49: 2
A50: Urgencia - 7A | B50: Hospital Penco Lirquen | C50: Monitoreo | D50: Mediano Costo | E50: Monitor ECG Baja Complejidad | F50: Fukuda Denshi | G50: Dinascope DSL-8001 | H50: 50200452 | I50: HPL30035 | J50: 2016 | K50: 8 | L50: 1 | M50: Propio | N50: Bueno | O50: CRÍTICO | P50: NO | R50: SI | S50: 2023 | T50: INTERNO | U50: TECNICO EQM HPL | X50: 2
A51: Urgencia - 7A | B51: Hospital Penco Lirquen | C51: Monitoreo | D51: Mediano Costo | E51: Monitor ECG Baja Complejidad | F51: Fukuda Denshi | G51: Dinascope DSL-8001 | H51: 50200451 | I51: HPL30034 | J51: 2016 | K51: 8 | L51: 1 | M51: Propio | N51: Bueno | O51: CRÍTICO | P51: NO | R51: SI | S51: 2023 | T51: INTERNO | U51: TECNICO EQM HPL | X51: 2
A52: Urgencia - 7A | B52: Hospital Penco Lirquen | C52: Monitoreo | D52: Mediano Costo | E52: Monitor ECG Baja Complejidad | F52: Fukuda Denshi | G52: Dinascope DSL-8001 | H52: 50200448 | I52: HPL30033 | J52: 2016 | K52: 8 | L52: 1 | M52: Propio | N52: Bueno | O52: CRÍTICO | P52: NO | R52: SI | S52: 2023 | T52: INTERNO | U52: TECNICO EQM HPL | X52: 2
A53: Corta Estadia - 4 | B53: Hospital Penco Lirquen | C53: Monitoreo | D53: Mediano Costo | E53: Monitor ECG Baja Complejidad | F53: Fukuda Denshi | G53: Dinascope DSL-8001 | H53: 50200450 | I53: HPL25510 | J53: 2016 | K53: 8 | L53: 1 | M53: Propio | N53: Bueno | O53: CRÍTICO | P53: NO | R53: SI | S53: 2023 | T53: INTERNO | U53: TECNICO EQM HPL | X53: 2
A54: Corta Estadia - 4 | B54: Hospital Penco Lirquen | C54: Monitoreo | D54: Mediano Costo | E54: Monitor ECG Baja Complejidad | F54: Fukuda Denshi | G54: Dinascope DSL-8001 | H54: 50200468 | I54: HPL21701 | J54: 2016 | K54: 8 | L54: 1 | M54: Propio | N54: Bueno | O54: CRÍTICO | P54: NO | R54: SI | S54: 2023 | T54: INTERNO | U54: TECNICO EQM HPL | X54: 2
A55: Urgencia - 7A | B55: Hospital Penco Lirquen | C55: Monitoreo | D55: Mediano Costo | E55: Monitor ECG Baja Complejidad | F55: Fukuda Denshi | G55: Dinascope DSL-8001 | H55: 50200444 | I55: HPL30030 | J55: 2016 | K55: 8 | L55: 1 | M55: Propio | N55: Bueno | O55: CRÍTICO | P55: NO | R55: SI | S55: 2023 | T55: INTERNO | U55: TECNICO EQM HPL | X55: 2
A56: Urgencia - 7A | B56: Hospital Penco Lirquen | C56: Monitoreo | D56: Mediano Costo | E56: Monitor ECG Baja Complejidad | F56: Fukuda Denshi | G56: Dinascope DSL-8001 | H56: 50200436 | I56: HPL30029 | J56: 2016 | K56: 8 | L56: 1 | M56: Propio | N56: Bueno | O56: CRÍTICO | P56: NO | R56: SI | S56: 2023 | T56: INTERNO | U56: TECNICO EQM HPL | X56: 2
A57: Corta Estadia - 4 | B57: Hospital Penco Lirquen | C57: Monitoreo | D57: Mediano Costo | E57: Desfibrilador externo automático (DEA) | F57: Philips | G57: Heart Start | H57: A19K-06055 | I57: HPL30198 | J57: 2020 | K57: 8 | L57: 5 | M57: Propio | N57: Bueno | O57: CRÍTICO | P57: NO | R57: SI | S57: 2023 | T57: INTERNO | U57: TECNICO EQM HPL | X57: 2
A58: Urgencia - 7A | B58: Hospital Penco Lirquen | C58: Monitoreo | D58: Mediano Costo | E58: Monitor ECG Baja Complejidad | F58: Nihon Kohden | G58: PVM-2701 | H58: 115438 | I58: HPL29917 | J58: 2016 | K58: 8 | L58: 1 | M58: Propio | N58: Bueno | O58: CRÍTICO | P58: NO | R58: SI | S58: 2023 | T58: INTERNO | U58: TECNICO EQM HPL | X58: 2
A59: Urgencia - 7A | B59: Hospital Penco Lirquen | C59: Monitoreo | D59: Mediano Costo | E59: Monitor ECG Baja Complejidad | F59: Nihon Kohden | G59: PVM-2701 | H59: 115409 | I59: HPL29913 | J59: 2016 | K59: 8 | L59: 1 | M59: Propio | N59: Bueno | O59: CRÍTICO | P59: NO | R59: SI | S59: 2023 | T59: INTERNO | U59: TECNICO EQM HPL | X59: 2
A60: Urgencia - 7A | B60: Hospital Penco Lirquen | C60: Monitoreo | D60: Mediano Costo | E60: Monitor ECG Baja Complejidad | F60: Nihon Kohden | G60: PVM-2701 | H60: 115373 | I60: HPL29911 | J60: 2016 | K60: 8 | L60: 1 | M60: Propio | N60: Bueno | O60: CRÍTICO | P60: NO | R60: SI | S60: 2023 | T60: INTERNO | U60: TECNICO EQM HPL | X60: 2
A61: Urgencia - 6B | B61: Hospital Penco Lirquen | C61: Monitoreo | D61: Mediano Costo | E61: Monitor desfibrilador con carro de paro | F61: Zoll medical | G61: Serie R ALS | H61: AF15D045654 | I61: HPL30211 | J61: 2016 | K61: 8 | L61: 1 | M61: Propio | N61: Bueno | O61: CRÍTICO | P61: NO | R61: SI | S61: 2023 | T61: INTERNO | U61: TECNICO EQM HPL | X61: 2
A62: Urgencia - 6B | B62: Hospital Penco Lirquen | C62: Monitoreo | D62: Mediano Costo | E62: Monitor desfibrilador con carro de paro | F62: Zoll medical | G62: Serie R ALS | H62: AF15D045649 | I62: HPL30210 | J62: 2016 | K62: 8 | L62: 1 | M62: Propio | N62: Bueno | O62: CRÍTICO | P62: NO | R62: SI | S62: 2023 | T62: INTERNO | U62: TECNICO EQM HPL | X62: 2
A63: Urgencia - 6B | B63: Hospital Penco Lirquen | C63: Monitoreo | D63: Mediano Costo | E63: Desfibrilador externo automático (DEA) | F63: Philips | G63: Heart Start | H63: A19K-06534 | I63: HPL30199 | J63: 2020 | K63: 8 | L63: 5 | M63: Propio | N63: Bueno | O63: CRÍTICO | P63: NO | R63: SI | S63: 2023 | T63: INTERNO | U63: TECNICO EQM HPL | X63: 2
A64: Urgencia - 6B | B64: Hospital Penco Lirquen | C64: Monitoreo | D64: Mediano Costo | E64: Desfibrilador externo automático (DEA) | F64: Zoll | G64: AED plus | H64: (21) X16K874144 | I64: HPL30119 | J64: 2017 | K64: 8 | L64: 2 | M64: Propio | N64: Bueno | O64: CRÍTICO | P64: NO | R64: SI | S64: 2023 | T64: INTERNO | U64: TECNICO EQM HPL | X64: 2
A65: Urgencia - 1B | B65: Hospital Penco Lirquen | C65: Apoyo Terapéutico | D65: Alto Costo | E65: Ventilador mecánico invasivo de transporte | F65: Drager | G65: Oxylog 3000 plus | H65: ASNH-0102 | I65: HPL30220 | J65: 2020 | K65: 8 | L65: 5 | M65: Propio | N65: Bueno | O65: CRÍTICO | P65: NO | R65: SI | S65: 2023 | T65: EXTERNO | V65: LIC 5 | W65: 1039250 | X65: 2
A66: URGENCIA | B66: Hospital Penco Lirquen | C66: Apoyo Terapéutico | D66: Alto Costo | E66: Ventilador mecánico Invasivo | F66: Aeonmed | G66: VG70 | H66: XZZT19761 | I66: HPL30405 | J66: 2020 | K66: 8 | L66: 5 | M66: Préstamo | N66: Bueno | O66: CRÍTICO | P66: NO | R66: SI | S66: 2023 | T66: EXTERNO | V66: 1057540-65-LE21 | W66: 407911 | X66: 2
A67: Salud del personal - 5 | B67: Hospital Penco Lirquen | C67: Monitoreo | D67: Mediano Costo | E67: Monitor de signos vitales | F67: Edan | G67: M3A | H67: 302019-M14505610013 | I67: HPL11939 | J67: 2017 | K67: 8 | L67: 2 | M67: Propio | N67: Bueno | O67: CRÍTICO | P67: NO | R67: SI | S67: 2023 | T67: INTERNO | U67: TECNICO EQM HPL | X67: 2
A68: Rehabilitacion Integral - 10 | B68: Hospital Penco Lirquen | C68: Monitoreo | D68: Mediano Costo | E68: Monitor ECG Baja Complejidad | F68: Fukuda Denshi | G68: Dinascope DSL-8001 | H68: 50200458 | I68: HPL30040 | J68: 2016 | K68: 8 | L68: 1 | M68: Propio | N68: Bueno | O68: CRÍTICO | P68: NO | R68: SI | S68: 2023 | T68: INTERNO | U68: TECNICO EQM HPL | X68: 2
A69: Parto Integral - 2 | B69: Hospital Penco Lirquen | C69: Monitoreo | D69: Mediano Costo | E69: Monitor de signos vitales | F69: Creative medical | G69: PC-900 | H69: J0100JL01720 | I69: HPL30259 | J69: 2014 | K69: 8 | L69: -1 | M69: Propio | N69: Bueno | O69: CRÍTICO | P69: NO | R69: SI | S69: 2023 | T69: INTERNO | U69: TECNICO EQM HPL | X69: 2
A70: Parto Integral - 2 | B70: Hospital Penco Lirquen | C70: Apoyo Terapéutico | D70: Alto Costo | E70: Incubadora de transporte | F70: Drager | G70: TI 500 | H70: EF10863 | I70: HPL30240 | J70: 2016 | K70: 8 | L70: 1 | M70: Propio | N70: Bueno | O70: CRÍTICO | P70: NO | R70: SI | S70: 2023 | T70: EXTERNO | U70: TDM | V70: 1057540-65-LE21 | W70: 195000 | X70: 2
A71: Parto Integral - 2 | B71: Hospital Penco Lirquen | C71: Monitoreo | D71: Mediano Costo | E71: Monitor desfibrilador | F71: Zoll medical | G71: Serie R ALS | H71: AF15D045660 | I71: HPL30213 | J71: 2016 | K71: 8 | L71: 1 | M71: Propio | N71: Bueno | O71: CRÍTICO | P71: NO | R71: SI | S71: 2023 | T71: INTERNO | U71: TECNICO EQM HPL | X71: 2
A72: Parto Integral - 2 | B72: Hospital Penco Lirquen | C72: Monitoreo | D72: Mediano Costo | E72: Monitor ECG Baja Complejidad | F72: Fukuda Denshi | G72: Dinascope DSL-8001 | H72: 50200461 | I72: HPL30042 | J72: 2016 | K72: 8 | L72: 1 | M72: Propio | N72: Bueno | O72: CRÍTICO | P72: NO | R72: SI | S72: 2023 | T72: INTERNO | U72: TECNICO EQM HPL | X72: 2
A73: Pabellón - 3C | B73: Hospital Penco Lirquen | C73: Monitoreo | D73: Mediano Costo | E73: Monitor ECG Baja Complejidad | F73: General Electric | G73: B20 | H73: SGF15131188WA | I73: HPL30368 | J73: 2015 | K73: 8 | L73: 0 | M73: Propio | N73: Bueno | O73: CRÍTICO | P73: NO | R73: SI | S73: 2023 | T73: INTERNO | U73: TECNICO EQM HPL | X73: 2
A74: Pabellón - 3C | B74: Hospital Penco Lirquen | C74: Monitoreo | D74: Mediano Costo | E74: Monitor ECG Baja Complejidad | F74: Fukuda Denshi | G74: Dinascope DSL-8001 | H74: 50200447 | I74: HPL30032 | J74: 2016 | K74: 8 | L74: 1 | M74: Propio | N74: Bueno | O74: CRÍTICO | P74: NO | R74: SI | S74: 2023 | T74: INTERNO | U74: TECNICO EQM HPL | X74: 2
A75: Pabellón - 3C | B75: Hospital Penco Lirquen | C75: Monitoreo | D75: Mediano Costo | E75: Monitor de signos vitales | F75: Indura | G75: Lifecare 740 | H75: 1022045 | I75: HPL29945 | J75: 2015 | K75: 8 | L75: 0 | M75: Propio | N75: Bueno | O75: CRÍTICO | P75: NO | R75: SI | S75: 2023 | T75: INTERNO | U75: TECNICO EQM HPL | X75: 2
A76: Pabellón - 3C | B76: Hospital Penco Lirquen | C76: Monitoreo | D76: Mediano Costo | E76: Monitor ECG Baja Complejidad | F76: Nihon Kohden | G76: PVM-2701 | H76: 115467 | I76: HPL29918 | J76: 2016 | K76: 8 | L76: 1 | M76: Propio | N76: Bueno | O76: CRÍTICO | P76: NO | R76: SI | S76: 2023 | T76: INTERNO | U76: TECNICO EQM HPL | X76: 2
A77: Pabellón - 3C | B77: Hospital Penco Lirquen | C77: Monitoreo | D77: Mediano Costo | E77: Monitor ECG Baja Complejidad | F77: Nihon Kohden | G77: PVM-2701 | H77: 115432 | I77: HPL29916 | J77: 2016 | K77: 8 | L77: 1 | M77: Propio | N77: Bueno | O77: CRÍTICO | P77: NO | R77: SI | S77: 2023 | T77: INTERNO | U77: TECNICO EQM HPL | X77: 2
A78: Pabellón - 3C | B78: Hospital Penco Lirquen | C78: Monitoreo | D78: Mediano Costo | E78: Monitor ECG Baja Complejidad | F78: Nihon Kohden | G78: PVM-2701 | H78: 115426 | I78: HPL29915 | J78: 2016 | K78: 8 | L78: 1 | M78: Propio | N78: Bueno | O78: CRÍTICO | P78: NO | R78: SI | S78: 2023 | T78: INTERNO | U78: TECNICO EQM HPL | X78: 2
A79: Pabellón - 3C | B79: Hospital Penco Lirquen | C79: Monitoreo | D79: Mediano Costo | E79: Monitor ECG Baja Complejidad | F79: Nihon Kohden | G79: PVM-2701 | H79: 115425 | I79: HPL29914 | J79: 2016 | K79: 8 | L79: 1 | M79: Propio | N79: Bueno | O79: CRÍTICO | P79: NO | R79: SI | S79: 2023 | T79: INTERNO | U79: TECNICO EQM HPL | X79: 2
A80: Endoscopia y PCM - 13B | B80: Hospital Penco Lirquen | C80: Monitoreo | D80: Mediano Costo | E80: Monitor ECG Baja Complejidad | F80: Fukuda Denshi | G80: Dinascope DSL-8001 | H80: 50200459 | I80: HPL30041 | J80: 2016 | K80: 8 | L80: 1 | M80: Propio | N80: Bueno | O80: CRÍTICO | P80: NO | R80: SI | S80: 2023 | T80: INTERNO | U80: TECNICO EQM HPL | X80: 2
A81: Endoscopia y PCM - 13B | B81: Hospital Penco Lirquen | C81: Monitoreo | D81: Mediano Costo | E81: Monitor desfibrilador | F81: Instramed | G81: Cardiomax | H81: 10608CM2833 | I81: HPL30137 | J81: 2014 | K81: 8 | L81: -1 | M81: Propio | N81: Bueno | O81: CRÍTICO | P81: NO | R81: SI | S81: 2023 | T81: INTERNO | U81: TECNICO EQM HPL | X81: 2
A82: Endoscopia y PCM - 13B | B82: Hospital Penco Lirquen | C82: Monitoreo | D82: Alto Costo | E82: Monitor ECG mediana complejidad | F82: Progetti | G82: TGS50 | H82: Q068E034129 | I82: HPL30277 | J82: 2021 | K82: 8 | L82: 6 | M82: Préstamo | N82: Bueno | O82: CRÍTICO | P82: NO | R82: SI | S82: 2023 | T82: INTERNO | U82: TECNICO EQM HPL | X82: 2
A83: Pabellón - 3C | B83: Hospital Penco Lirquen | C83: Monitoreo | D83: Mediano Costo | E83: Monitor ECG Baja Complejidad | F83: Nihon Kohden | G83: PVM-2701 | H83: 115405 | I83: HPL29912 | J83: 2016 | K83: 8 | L83: 1 | M83: Propio | N83: Bueno | O83: CRÍTICO | P83: NO | R83: SI | S83: 2023 | T83: INTERNO | U83: TECNICO EQM HPL | X83: 2
A84: Endoscopia y PCM (urgencia) - 13B | B84: Hospital Penco Lirquen | C84: Monitoreo | D84: Mediano Costo | E84: Monitor de signos vitales | F84: Mindray | G84: DPM3 | H84: DQ-18000395 | I84: HPL30238 | J84: 2015 | K84: 8 | L84: 0 | M84: Propio | N84: Bueno | O84: CRÍTICO | P84: NO | R84: SI | S84: 2023 | T84: INTERNO | U84: TECNICO EQM HPL | X84: 2
A85: Pabellón - 3B | B85: Hospital Penco Lirquen | C85: Apoyo Quirúrgico | D85: Alto Costo | E85: Máquina de Anestesia | F85: Drager | G85: Fabius GS Premium 8607000 | H85: ASHJ-0206 | I85: HPL30219 | J85: 2016 | K85: 8 | L85: 1 | M85: Propio | N85: Bueno | O85: CRÍTICO | P85: NO | R85: SI | S85: 2023 | T85: EXTERNO | U85: Drager | V85: 1057540-40-LP20 | W85: 10222948 | X85: 2
A86: Pabellón - 3B | B86: Hospital Penco Lirquen | C86: Apoyo Quirúrgico | D86: Alto Costo | E86: Máquina de Anestesia | F86: Drager | G86: Fabius GS Premium 8607000 | H86: ASHJ-0205 | I86: HPL30218 | J86: 2016 | K86: 8 | L86: 1 | M86: Propio | N86: Bueno | O86: CRÍTICO | P86: NO | R86: SI | S86: 2023 | T86: EXTERNO | U86: Drager | V86: 1057540-40-LP20 | W86: 10222948 | X86: 2
A87: Pabellón - 3B | B87: Hospital Penco Lirquen | C87: Apoyo Quirúrgico | D87: Alto Costo | E87: Máquina de Anestesia | F87: Drager | G87: Fabius GS Premium 8607000 | H87: ASFN-0031 | I87: HPL30217 | J87: 2015 | K87: 8 | L87: 0 | M87: Propio | N87: Bueno | O87: CRÍTICO | P87: NO | R87: SI | S87: 2023 | T87: EXTERNO | U87: Drager | V87: 1057540-40-LP20 | W87: 10222948 | X87: 2
A88: Pabellón - 3B | B88: Hospital Penco Lirquen | C88: Monitoreo | D88: Mediano Costo | E88: Monitor desfibrilador con carro de paro | F88: Zoll medical | G88: Serie R ALS | H88: AF15D045672 | I88: HPL30214 | J88: 2016 | K88: 8 | L88: 1 | M88: Propio | N88: Bueno | O88: CRÍTICO | P88: NO | R88: SI | S88: 2023 | T88: INTERNO | U88: TECNICO EQM HPL | X88: 2
A89: Pabellón - 3B | B89: Hospital Penco Lirquen | C89: Monitoreo | D89: Mediano Costo | E89: Monitor desfibrilador con carro de paro | F89: Zoll medical | G89: Serie R ALS | H89: AF15D045656 | I89: HPL30212 | J89: 2016 | K89: 8 | L89: 1 | M89: Propio | N89: Bueno | O89: CRÍTICO | P89: NO | R89: SI | S89: 2023 | T89: INTERNO | U89: TECNICO EQM HPL | X89: 2
A90: Pabellón - 3A | B90: Hospital Penco Lirquen | C90: Apoyo Terapéutico | D90: Mediano Costo | E90: Incubadora | F90: Medix | G90: TR200 | H90: 1078 | I90: HPL29859 | J90: 2015 | K90: 8 | M90: Propio | N90: Bueno | O90: CRÍTICO | P90: NO | R90: SI | S90: 2023 | T90: EXTERNO | U90: TDM | V90: 1057540-65-LE21 | W90: 195000 | X90: 2
A91: Laboratorio - 14A | B91: Hospital Penco Lirquen | C91: Monitoreo | D91: Mediano Costo | E91: Monitor de signos vitales | F91: Criticare | G91: 506DN | H91: 122010786 | I91: HPL30046 | J91: 2022 | K91: 8 | L91: 7 | M91: Propio | N91: Bueno | O91: CRÍTICO | P91: NO | R91: SI | S91: 2023 | T91: INTERNO | U91: TECNICO EQM HPL | X91: 2
A92: Imagenologia - 8 | B92: Hospital Penco Lirquen | C92: Monitoreo | D92: Mediano Costo | E92: Monitor desfibrilador con carro de paro | F92: Zoll | G92: Serie R ALS | H92: AF20G120257 | I92: HPL30216 | J92: 2021 | K92: 8 | L92: 6 | M92: Propio | N92: Bueno | O92: CRÍTICO | P92: NO | R92: SI | S92: 2023 | T92: INTERNO | U92: TECNICO EQM HPL | X92: 2
A93: Imagenologia - 8 | B93: Hospital Penco Lirquen | C93: Monitoreo | D93: Mediano Costo | E93: Monitor ECG Baja Complejidad | F93: Fukuda Denshi | G93: Dinascope DSL-8001 | H93: 50200456 | I93: HPL30038 | J93: 2016 | K93: 8 | L93: 1 | M93: Propio | N93: Bueno | O93: CRÍTICO | P93: NO | R93: SI | S93: 2023 | T93: INTERNO | U93: TECNICO EQM HPL | X93: 2
A94: Hospitalizados - 9E | B94: Hospital Penco Lirquen | C94: Monitoreo | D94: Alto Costo | E94: Monitor ECG mediana complejidad | F94: Mindray | G94: uMEC12 | H94: KQ-04039751 | I94: HPL30267 | J94: 2020 | K94: 8 | L94: 5 | M94: Propio | N94: Bueno | O94: CRÍTICO | P94: NO | R94: SI | S94: 2023 | T94: INTERNO | U94: TECNICO EQM HPL | X94: 2
A95: Hospitalizados - 9E | B95: Hospital Penco Lirquen | C95: Monitoreo | D95: Alto Costo | E95: Monitor ECG mediana complejidad | F95: Mindray | G95: uMEC12 | H95: KQ-04039657 | I95: HPL30266 | J95: 2020 | K95: 8 | L95: 5 | M95: Propio | N95: Bueno | O95: CRÍTICO | P95: NO | R95: SI | S95: 2023 | T95: INTERNO | U95: TECNICO EQM HPL | X95: 2
A96: Especialidades cuidados paliativos - 15B | B96: Hospital Penco Lirquen | C96: Monitoreo | D96: Mediano Costo | E96: Monitor de signos vitales | F96: General Electric | G96: V100 | H96: SH617070056SA | I96: HPL5044 | J96: 2017 | K96: 8 | L96: 2 | M96: Propio | N96: Bueno | O96: CRÍTICO | P96: NO | R96: SI | S96: 2023 | T96: INTERNO | U96: TECNICO EQM HPL | X96: 2
A97: Hospitalizados - 9E | B97: Hospital Penco Lirquen | C97: Monitoreo | D97: Alto Costo | E97: Monitor ECG mediana complejidad | F97: Mindray | G97: uMEC12 | H97: KQ-04039627 | I97: HPL30265 | J97: 2020 | K97: 8 | L97: 5 | M97: Propio | N97: Bueno | O97: CRÍTICO | P97: NO | R97: SI | S97: 2023 | T97: INTERNO | U97: TECNICO EQM HPL | X97: 2
A98: Hospitalizados - 9E | B98: Hospital Penco Lirquen | C98: Monitoreo | D98: Alto Costo | E98: Monitor ECG mediana complejidad | F98: Mindray | G98: uMEC12 | H98: KQ-04039590 | I98: HPL30264 | J98: 2020 | K98: 8 | L98: 5 | M98: Propio | N98: Bueno | O98: CRÍTICO | P98: NO | R98: SI | S98: 2023 | T98: INTERNO | U98: TECNICO EQM HPL | X98: 2
A99: Especialidades cuidados paliativos - 15B | B99: Hospital Penco Lirquen | C99: Monitoreo | D99: Mediano Costo | E99: Monitor de signos vitales | F99: General Electric | G99: V100 | H99: SH617070057SA | I99: HPL5046 | J99: 2017 | K99: 8 | L99: 2 | M99: Propio | N99: Bueno | O99: CRÍTICO | P99: NO | R99: SI | S99: 2023 | T99: INTERNO | U99: TECNICO EQM HPL | X99: 2
A100: Hospitalizados - 9E | B100: Hospital Penco Lirquen | C100: Monitoreo | D100: Alto Costo | E100: Monitor ECG mediana complejidad | F100: Mindray | G100: uMEC12 | H100: KQ-04039029 | I100: HPL30263 | J100: 2020 | K100: 8 | L100: 5 | M100: Propio | N100: Bueno | O100: CRÍTICO | P100: NO | R100: SI | S100: 2023 | T100: INTERNO | U100: TECNICO EQM HPL | X100: 2
A101: Hospitalizados - 9E | B101: Hospital Penco Lirquen | C101: Monitoreo | D101: Alto Costo | E101: Monitor ECG mediana complejidad | F101: Mindray | G101: uMEC12 | H101: KQ-04039010 | I101: HPL30262 | J101: 2020 | K101: 8 | L101: 5 | M101: Propio | N101: Bueno | O101: CRÍTICO | P101: NO | R101: SI | S101: 2023 | T101: INTERNO | U101: TECNICO EQM HPL | X101: 2
...

Sheet CATASTRO Y PLANIFICACIÓN MP
A3: SERVICIO DE SALUD | B3: AYSEN
A5: NOMBRE ESTABLECIMIENTO | B5: HOSPITAL DR. LEOPOLDO ORTEGA RODRIGUEZ
A7: RESPONSABLE TÉCNICO | B7: RODRIGO RAMÍREZ PÉREZ | X7: MONITOREO MENSUAL DEL PLAN
X8: % EJECUCIÓN MP TOTAL MENSUAL | Y8: =+'TABLA CÁLCULO'!B24 | Z8: =+'TABLA CÁLCULO'!C24 | AA8: =+'TABLA CÁLCULO'!D24 | AB8: =+'TABLA CÁLCULO'!E24 | AC8: =+'TABLA CÁLCULO'!F24 | AD8: =+'TABLA CÁLCULO'!G24 | AE8: =+'TABLA CÁLCULO'!H24 | AF8: =+'TABLA CÁLCULO'!I24 | ... AJ8: =+'TABLA CÁLCULO'!M24
A9: AÑO DE LEVANTAMIENTO | B9: 2026 | X9: % EJECUCIÓN MP EQC MENSUAL | Y9: =+'TABLA CÁLCULO'!B25 | Z9: =+'TABLA CÁLCULO'!C25 | AA9: =+'TABLA CÁLCULO'!D25 | AB9: =+'TABLA CÁLCULO'!E25 | AC9: =+'TABLA CÁLCULO'!F25 | AD9: =+'TABLA CÁLCULO'!G25 | AE9: =+'TABLA CÁLCULO'!H25 | AF9: =+'TABLA CÁLCULO'!I25 | ... AJ9: =+'TABLA CÁLCULO'!M25
X10: % EJECUCIÓN MP EQR MENSUAL | Y10: =+'TABLA CÁLCULO'!B26 | Z10: =+'TABLA CÁLCULO'!C26 | AA10: =+'TABLA CÁLCULO'!D26 | AB10: =+'TABLA CÁLCULO'!E26 | AC10: =+'TABLA CÁLCULO'!F26 | AD10: =+'TABLA CÁLCULO'!G26 | AE10: =+'TABLA CÁLCULO'!H26 | AF10: =+'TABLA CÁLCULO'!I26 | ... AJ10: =+'TABLA CÁLCULO'!M26
A11: GASTO PROGRAMADO MP | B11: =SUM('SEGUIMIENTO GASTO'!I8:I13) -> 0 | D11: EJECUCIÓN GASTO MP | E11: =+SUM('SEGUIMIENTO GASTO'!AI8:AI13) -> 0 | X11: % EJECUCIÓN MP IM≥12 MENSUAL | Y11: =+'TABLA CÁLCULO'!B27 | Z11: =+'TABLA CÁLCULO'!C27 | AA11: =+'TABLA CÁLCULO'!D27 | AB11: =+'TABLA CÁLCULO'!E27 | AC11: =+'TABLA CÁLCULO'!F27 | AD11: =+'TABLA CÁLCULO'!G27 | AE11: =+'TABLA CÁLCULO'!H27 | AF11: =+'TABLA CÁLCULO'!I27 | ... AJ11: =+'TABLA CÁLCULO'!M27
A13: GASTO PROGRAMADO MC | B13: =SUM('SEGUIMIENTO GASTO'!G21:G26) -> 0 | D13: EJECUCIÓN GASTO MC | E13: =+SUM('SEGUIMIENTO GASTO'!AG21:AG26) -> 0 | Q13: % EJECUCIÓN GASTO MP | T13: % EJECUCIÓN GASTO MC
Y14: CUMPLIMIENTO MANTENIMIENTO PREVENTIVO
A15: SERVICIO CLÍNICO | B15: RECINTO | C15: CLASE | D15: SUBCLASE | E15: NOMBRE EQUIPO | F15: MARCA | G15: MODELO | H15: SERIE | I15: N° INVENTARIO | J15: AÑO DE ADQUISICIÓN | K15: VIDA ÚTIL | L15: VIDA ÚTIL RESIDUAL | M15: PROPIO / ARRIENDO / COMODATO | N15: ESTADO (BUENO / REGULAR / MALO / BAJA) | O15: CRÍTICO/ RELEVANTE / IM≥12 / NO APLICA | P15: EN GARANTÍA (SI / NO) | Q15: AÑO VENCIMIENTO GARANTÍA | R15: BAJO PLAN DE MANTENIMIENTO (SI / NO) | S15: AÑO INGRESO A PLAN DE MANTENIMIENTO (2025 / 2026 / 2027 / 2028) | T15: MANTENIMIENTO INTERNO O MANTENIMIENTO EXTERNO O CONTRATO | U15: NOMBRE DE PROVEEDOR O MANTENIMIENTO INTERNO | V15: ID CONVENIO DE MANTENIMIENTO / ID DE REFERENCIA / COTIZACIÓN DE REFERENCIA | W15: COSTO ANUAL DE MANTENIMIENTO SEGÚN CONVENIO / PRECIO DE REFERENCIA MANTENIMIENTO ANUAL | X15: FRECUENCIA ANUAL DE MANTENIMIENTO | Y15: ENERO | Z15: FEBRERO | AA15: MARZO | AB15: ABRIL | AC15: MAYO | AD15: JUNIO | AE15: JULIO | AF15: AGOSTO | AG15: SEPTIEMBRE | AH15: OCTUBRE | AI15: NOVIEMBRE | AJ15: DICIEMBRE
A16: Laboratorio | B16: Hematología Química Clínica | C16: Laboratorio/Farmacia | D16: Bajo Costo | E16: Agitador de muestras (tipo vortex) | F16: DLAB | G16: MX-S | H16: VB232AS0008474 | I16: 75188 | J16: 2025 | K16: 10 | L16: =K16-($B$9-J16) -> 9 | M16: PROPIO | N16: BUENO | O16: RELEVANTE | P16: SI | Q16: 2026 | R16: SI | S16: 2026 | T16: Mantenimiento Externo | U16: Arquimed | X16: 1 | AD16: X
A17: Laboratorio | B17: Bacteriología y Orina | C17: Laboratorio/Farmacia | D17: Bajo Costo | E17: Agitador Magnetico (RPR) | F17: DIGISYSTEM | G17: DS-DSR2100D | H17: S/S | I17: 75067 | J17: 2025 | K17: 10 | L17: =K17-($B$9-J17) -> 9 | M17: PROPIO | N17: BUENO | O17: RELEVANTE | P17: NO | Q17: 2025 | R17: SI | S17: 2026 | T17: Mantenimiento Externo | U17: Farmalatina | X17: 1 | AA17: ꓣ
A18: Laboratorio | B18: Hematología Química Clínica | C18: Laboratorio/Farmacia | D18: Alto Costo | E18: Analizador Hematologico Digital (Células Sanguíneas) | F18: DIGISYSTEM | G18: DBC-9D-M | H18: S/S | I18: 75066 | J18: 2025 | K18: 10 | L18: =K18-($B$9-J18) -> 9 | M18: PROPIO | N18: BUENO | O18: RELEVANTE | P18: NO | Q18: 2025 | R18: SI | S18: 2026 | T18: Mantenimiento Externo | U18: Farmalatina | X18: 1 | AA18: ꓣ
A19: Atención Abierta | B19: Laboratorio Dental | C19: Odontología | D19: Bajo Costo | E19: Arenadora con cajón | F19: ESSENCE | G19: EVOLUT | H19: TJ0124 | I19: 76577 | J19: 2025 | K19: 10 | L19: =K19-($B$9-J19) -> 9 | M19: PROPIO | N19: BUENO | O19: NO APLICA | P19: SI | Q19: 2026 | R19: SI | S19: 2027 | T19: Mantenimiento Interno | U19: Dental Laval | X19: 1 | AD19: X
A20: Hospital Antiguo | B20: Bodega EQM | C20: Esterilización | D20: Alto Costo | E20: AUTOCLAVE | F20: MINGTAI | G20: SUN45-III | H20: SA2211296 | I20: 74052 | J20: 2015 | K20: 10 | L20: 0 | M20: PROPIO | N20: BUENO | O20: RELEVANTE | P20: NO | Q20: NO APLICA | R20: SI | S20: 2025 | T20: Mantenimiento Externo | U20: ITALO BRAVO | W20: 816550 | X20: 1 | AC20: X
A21: Esterilización | B21: Material Esteril (Autoclave) | C21: Esterilización | D21: Alto Costo | E21: Autoclave 100 Litros (2 STU) | F21: MATACHANA | G21: SC500E-1 | H21: E-35162 | I21: 75041 | J21: 2025 | K21: 10 | L21: =K21-($B$9-J21) -> 9 | M21: PROPIO | N21: BUENO | O21: RELEVANTE | P21: SI | Q21: 2026 | R21: SI | S21: 2025 | T21: Mantenimiento Externo | U21: IClinics | X21: 2 | AC21: X | AI21: X
A22: Sedile | B22: Sedile | C22: Esterilización | D22: Alto Costo | E22: Autoclave 21 Litros | F22: MATACHANA | G22: M20-B | H22: 34122 | I22: 75039 | J22: 2025 | K22: 10 | L22: =K22-($B$9-J22) -> 9 | M22: PROPIO | N22: BUENO | O22: RELEVANTE | P22: SI | Q22: 2026 | R22: SI | S22: 2025 | T22: Mantenimiento Externo | U22: IClinics | X22: 2 | AC22: X | AI22: X
A23: Laboratorio | B23: Descontaminacion y Lavado | C23: Esterilización | D23: Alto Costo | E23: Autoclave 50Lt vertical | F23: RAYPA | G23: AE-50-DRY | H23: 443333 | I23: 75038 | J23: 2025 | K23: 10 | L23: =K23-($B$9-J23) -> 9 | M23: PROPIO | N23: BUENO | O23: RELEVANTE | P23: SI | Q23: 2026 | R23: SI | S23: 2025 | T23: Mantenimiento Externo | U23: IClinics | X23: 2 | AC23: X | AI23: X
A24: Unidad Urgencias | B24: Closet EQM | C24: Apoyo Diagnóstico | D24: Alto Costo | E24: Autorefractómetro | F24: NIDEK | G24: Ark-1 | H24: S/N | I24: 75071 | J24: 2025 | K24: 10 | L24: =K24-($B$9-J24) -> 9 | M24: PROPIO | N24: BUENO | O24: IM ≥ 12 | P24: SI | Q24: 2027 | R24: SI | S24: 2026 | T24: Mantenimiento Externo | U24: Alta Tecnologia Medica | X24: 1 | AD24: X
A25: Laboratorio | B25: Entrega de Sangre (Unidad Medicina Transfusional) | C25: Laboratorio/Farmacia | D25: Mediano Costo | E25: Balanza de presición | F25: BIOLOGIX | G25: 01-BD304N4 | H25: YS05202410006 | I25: 75302 | J25: 2025 | K25: 10 | L25: =K25-($B$9-J25) -> 9 | M25: PROPIO | N25: BUENO | O25: RELEVANTE | P25: NO | Q25: 2025 | R25: SI | S25: 2026 | T25: Mantenimiento Externo | U25: Microx Chile | X25: 1 | AA25: ꓣ | AD25: X
A26: Laboratorio | B26: Hematología Química Clínica | C26: Laboratorio/Farmacia | D26: Bajo Costo | E26: Baño Termoregulado | F26: LAUDA | G26: HYDRO H8 | H26: S230014557 | I26: 75187 | J26: 2025 | K26: 10 | L26: =K26-($B$9-J26) -> 9 | M26: PROPIO | N26: BUENO | O26: RELEVANTE | P26: SI | Q26: 2026 | R26: SI | S26: 2027 | T26: Mantenimiento Externo | U26: Arquimed | X26: 1 | AD26: X
A27: Hospital Antiguo | B27: Bodega EQM | C27: Med. Física y Rehabilitación | D27: Alto Costo | E27: BAÑO TURBIÓN EXTREMIDAD INFERIOR | F27: S/M | G27: S/M | H27: S/N | I27: 74177 | J27: 2015 | K27: 10 | L27: 0 | M27: PROPIO | N27: BUENO | O27: IM ≥ 12 | P27: NO | Q27: NO APLICA | R27: SI | S27: 2026 | T27: Mantenimiento Interno | X27: 1 | AJ27: X
A28: Medicina Fisica y Rehabilitación | B28: Area de Gimnasio infantil y adulto (actividades terapeuticas) | C28: Med. Física y Rehabilitación | D28: Mediano Costo | E28: Bicicleta Ergonométrica | F28: DYACO | G28: 7.0 | H28: 20-24080029 | I28: 75299 | J28: 2025 | K28: 10 | L28: =K28-($B$9-J28) -> 9 | M28: PROPIO | N28: BUENO | O28: IM ≥ 12 | P28: SI | Q28: 2027 | R28: SI | S28: 2026 | T28: Mantenimiento Externo | U28: Quimicolor | X28: 1 | AC28: X
A29: Medicina Fisica y Rehabilitación | B29: Area de Gimnasio infantil y adulto (actividades terapeuticas) | C29: Med. Física y Rehabilitación | D29: Mediano Costo | E29: Bicicleta Ergonométrica | F29: DYACO | G29: 7.0 | H29: 30-24080019 | I29: 75300 | J29: 2025 | K29: 10 | L29: =K29-($B$9-J29) -> 9 | M29: PROPIO | N29: BUENO | O29: IM ≥ 12 | P29: SI | Q29: 2027 | R29: SI | S29: 2026 | T29: Mantenimiento Externo | U29: Quimicolor | X29: 1 | AC29: X
A30: Atención Cerrada Hospitalización | B30: Bodega de Equipos | C30: Apoyo Terapéutico | D30: Bajo Costo | E30: Bomba Alimentación Enteral | F30: FEEGIND PUMP | G30: FP300 | H30: 8014223 | I30: 75134 | J30: 2025 | K30: 10 | L30: =K30-($B$9-J30) -> 9 | M30: PROPIO | N30: BUENO | O30: NO APLICA | P30: SI | Q30: 2026 | R30: SI | S30: 2026 | T30: Mantenimiento Externo | U30: Skill Training | X30: 2 | AA30: ꓣ | AB30: X | AH30: X
A31: Unidad Urgencia Pabellón Quirúrgico | B31: Pabellón Quirúrgico Multiproposito | C31: Apoyo Quirúrgico | D31: Bajo Costo | E31: Bomba Aspiración Quirúrgica | F31: CAMI | G31: NEW HOSPIVAC 350 | H31: 41017 | I31: 75072 | J31: 2025 | K31: 10 | L31: =K31-($B$9-J31) -> 9 | M31: PROPIO | N31: BUENO | O31: IM ≥ 12 | P31: SI | Q31: 2026 | R31: SI | S31: 2026 | T31: Mantenimiento Externo | U31: Bioscom | X31: 1 | AH31: X
A32: Unidad Urgencia Pabellón Quirúrgico | B32: Sala de Parto Integral | C32: Apoyo Quirúrgico | D32: Bajo Costo | E32: Bomba Aspiración Quirúrgica | F32: CAMI | G32: NEW HOSPIVAC 350 | H32: 41013 | I32: 75073 | J32: 2025 | K32: 10 | L32: =(J32+K32)-$B$9 -> 9 | M32: PROPIO | N32: BUENO | O32: IM ≥ 12 | P32: SI | Q32: 2026 | R32: SI | S32: 2026 | T32: Mantenimiento Externo | U32: Bioscom | X32: 1 | AH32: X
A33: Hospital Antiguo | B33: Bodega EQM | C33: Apoyo Quirúrgico | D33: Bajo Costo | E33: Bomba de Aspiración | F33: CA-MI | G33: 230-12BR | H33: 2470 | I33: 74184 | J33: 2015 | K33: 10 | L33: 0 | M33: PROPIO | N33: BUENO | O33: IM ≥ 12 | P33: NO | Q33: NO APLICA | R33: SI | S33: 2025 | T33: Mantenimiento Externo | U33: MEDICAL SYSTEM | W33: 246971.63 | X33: 1 | AJ33: X
A34: Hospital Antiguo | B34: Bodega EQM | C34: Apoyo Quirúrgico | D34: Bajo Costo | E34: Bomba de Aspiración | F34: DEVILBISS | G34: 7314P-D | H34: 4PD061810 | I34: 74191 | J34: 2015 | K34: 10 | L34: 0 | M34: PROPIO | N34: BUENO | O34: IM ≥ 12 | P34: NO | Q34: NO APLICA | R34: SI | S34: 2025 | T34: Mantenimiento Externo | U34: MEDICAL SYSTEM | W34: 246971.63 | X34: 1 | AJ34: X
A35: Hospital Antiguo | B35: Bodega EQM | C35: Apoyo Quirúrgico | D35: Bajo Costo | E35: Bomba de Aspiración | F35: EACHMAN | G35: VP35 | H35: V3AB-90-1141 | I35: 74210 | J35: 2015 | K35: 10 | L35: 0 | M35: PROPIO | N35: BUENO | O35: IM ≥ 12 | P35: NO | Q35: NO APLICA | R35: SI | S35: 2025 | T35: Mantenimiento Externo | U35: MEDICAL SYSTEM | W35: 246971.63 | X35: 1 | AJ35: X
A36: Hospital Antiguo | B36: Bodega EQM | C36: Apoyo Quirúrgico | D36: Bajo Costo | E36: Bomba de Aspiración | F36: MEDI AIR | G36: SUBOI SERIES | H36: SU12K00846 | I36: 74194 | J36: 2015 | K36: 10 | L36: 0 | M36: PROPIO | N36: BUENO | O36: IM ≥ 12 | P36: NO | Q36: NO APLICA | R36: SI | S36: 2025 | T36: Mantenimiento Externo | U36: MEDICAL SYSTEM | W36: 246971.63 | X36: 1 | AJ36: X
A37: Hospital Antiguo | B37: Bodega EQM | C37: Apoyo Quirúrgico | D37: Bajo Costo | E37: Bomba de Aspiración | F37: NEW ASKIR | G37: 230-12BR | H37: 19979 | I37: 74187 | J37: 2015 | K37: 10 | L37: 0 | M37: PROPIO | N37: BUENO | O37: IM ≥ 12 | P37: NO | Q37: NO APLICA | R37: SI | S37: 2025 | T37: Mantenimiento Externo | U37: MEDICAL SYSTEM | W37: 246971.63 | X37: 1 | AJ37: X
A38: Hospital Antiguo | B38: Bodega EQM | C38: Apoyo Quirúrgico | D38: Bajo Costo | E38: Bomba de Aspiración | F38: THOMAS | G38: 1636 | H38: 16900002248 | J38: 2015 | K38: 10 | L38: 0 | M38: PROPIO | N38: BUENO | O38: IM ≥ 12 | P38: NO | Q38: NO APLICA | R38: SI | S38: 2025 | T38: Mantenimiento Externo | U38: MEDICAL SYSTEM | W38: 246971.63 | X38: 1 | AJ38: X
A39: Hospital Antiguo | B39: Bodega EQM | C39: Apoyo Quirúrgico | D39: Bajo Costo | E39: Bomba de Aspiración | F39: APEX MEDICAL | G39: VAC PLUS | H39: 077B-04591 | J39: 2024 | K39: 10 | L39: 9 | M39: PROPIO | N39: REGULAR | O39: IM ≥ 12 | P39: NO | Q39: NO APLICA | R39: NO | T39: Mantenimiento Externo | X39: 1 | AJ39: X
A40: Atención Cerrada Hospitalización | B40: Bodega de Equipos | C40: Apoyo Quirúrgico | D40: Bajo Costo | E40: Bomba de Aspiración | F40: FLAEM | G40: ASPIRA PLUS | H40: 23AK260037 | I40: 76591 | J40: 2025 | K40: 10 | L40: =(J40+K40)-$B$9 -> 9 | M40: PROPIO | N40: BUENO | O40: IM ≥ 12 | P40: SI | Q40: 2026 | R40: SI | S40: 2025 | T40: Mantenimiento Externo | U40: Mediplex | X40: 1 | AD40: X
A41: Atención Abierta | B41: Box Tratamiento Respiratorio (IRA) | C41: Apoyo Quirúrgico | D41: Bajo Costo | E41: Bomba de Aspiración | F41: FLAEM | G41: ASPIRA PLUS | H41: 23AK260048 | I41: 75108 | J41: 2025 | K41: 10 | L41: =K41-($B$9-J41) -> 9 | M41: PROPIO | N41: BUENO | O41: IM ≥ 12 | P41: SI | Q41: 2026 | R41: SI | S41: 2025 | T41: Mantenimiento Externo | U41: Mediplex | X41: 1 | AD41: X
A42: Atención Cerrada Hospitalización | B42: Estación Enfermería | C42: Apoyo Quirúrgico | D42: Bajo Costo | E42: Bomba de Aspiración | F42: FLAEM | G42: ASPIRA PLUS | H42: 23AK260047 | I42: 75110 | J42: 2025 | K42: 10 | L42: =K42-($B$9-J42) -> 9 | M42: PROPIO | N42: BUENO | O42: IM ≥ 12 | P42: SI | Q42: 2026 | R42: SI | S42: 2025 | T42: Mantenimiento Externo | U42: Mediplex | X42: 1 | AD42: X
A43: Unidad Urgencias | B43: Estación Enfermería | C43: Apoyo Quirúrgico | D43: Bajo Costo | E43: Bomba de Aspiración | F43: FLAEM | G43: ASPIRA PLUS | H43: 23AK260031 | I43: 75113 | J43: 2025 | K43: 10 | L43: =K43-($B$9-J43) -> 9 | M43: PROPIO | N43: BUENO | O43: IM ≥ 12 | P43: SI | Q43: 2026 | R43: SI | S43: 2025 | T43: Mantenimiento Externo | U43: Mediplex | X43: 1 | AD43: X
A44: Unidad Urgencias | B44: Sala Reanimación | C44: Apoyo Quirúrgico | D44: Bajo Costo | E44: Bomba de Aspiración | F44: FLAEM | G44: ASPIRA PLUS | H44: 23AK260032 | I44: 75114 | J44: 2025 | K44: 10 | L44: =K44-($B$9-J44) -> 9 | M44: PROPIO | N44: BUENO | O44: IM ≥ 12 | P44: SI | Q44: 2026 | R44: SI | S44: 2025 | T44: Mantenimiento Externo | U44: Mediplex | X44: 1 | AD44: X
A45: Unidad Urgencias | B45: Box Atención 2 | C45: Apoyo Quirúrgico | D45: Bajo Costo | E45: Bomba de Aspiración | F45: FLAEM | G45: ASPIRA PLUS | H45: 23AK260038 | I45: 75115 | J45: 2025 | K45: 10 | L45: =K45-($B$9-J45) -> 9 | M45: PROPIO | N45: BUENO | O45: IM ≥ 12 | P45: SI | Q45: 2026 | R45: SI | S45: 2025 | T45: Mantenimiento Externo | U45: Mediplex | X45: 1 | AD45: X
A46: Unidad Urgencia Pabellón Quirúrgico | B46: Estación Enfermería (Área Limpia) | C46: Apoyo Terapéutico | D46: Mediano Costo | E46: Bomba Infusión Jeringa | F46: BRAUN | G46: B/BRAUN | H46: 644181 | I46: 75275 | J46: 2025 | K46: 10 | L46: =K46-($B$9-J46) -> 9 | M46: PROPIO | N46: BUENO | O46: IM ≥ 12 | P46: NO | Q46: 2025 | R46: SI | S46: 2025 | T46: Mantenimiento Externo | U46: Bbraun | X46: 2 | AD46: X | AJ46: X
A47: Hospital Antiguo | B47: Bodega EQM | C47: Apoyo Terapéutico | D47: Mediano Costo | E47: Bomba Infusión Volumétrica | F47: BBRAUN | G47: INFUSOMAT COMPACT | H47: 46195 | I47: 74061 | J47: 2015 | K47: 10 | L47: 0 | M47: PROPIO | N47: BUENO | O47: IM ≥ 12 | P47: NO | Q47: NO APLICA | R47: SI | S47: 2025 | T47: Mantenimiento Externo | U47: MEDICAL SYSTEM | W47: 246971.63 | X47: 2 | AD47: X | AJ47: X
A48: Hospital Antiguo | B48: Bodega EQM | C48: Apoyo Terapéutico | D48: Mediano Costo | E48: Bomba Infusión Volumétrica | F48: FRESENIUS KABI | G48: VOLUMAT MAC AGILIA | H48: 019181/22324963 | I48: 74062 | J48: 2015 | K48: 10 | L48: 0 | M48: PROPIO | N48: BUENO | O48: IM ≥ 12 | P48: NO | Q48: NO APLICA | R48: SI | S48: 2025 | T48: Mantenimiento Externo | U48: MEDICAL SYSTEM | W48: 246971.63 | X48: 2 | AD48: X | AJ48: X
A49: Hospital Antiguo | B49: Bodega EQM | C49: Apoyo Terapéutico | D49: Mediano Costo | E49: Bomba Infusión Volumétrica | F49: FRESENIUS KABI | G49: VOLUMAT MAC AGILIA | H49: 20885416 | I49: 74201 | J49: 2015 | K49: 10 | L49: 0 | M49: PROPIO | N49: BUENO | O49: IM ≥ 12 | P49: NO | Q49: NO APLICA | R49: SI | S49: 2025 | T49: Mantenimiento Externo | U49: MEDICAL SYSTEM | W49: 246971.63 | X49: 2 | AD49: X | AJ49: X
A50: Hospital Antiguo | B50: Bodega EQM | C50: Apoyo Terapéutico | D50: Mediano Costo | E50: Bomba Infusión Volumétrica | F50: BBRAUN | G50: SPACE PLUS INFUSOMAT | H50: 51822 | I50: 74197 | J50: 2024 | K50: 10 | L50: 9 | M50: PROPIO | N50: REGULAR | O50: IM ≥ 12 | P50: NO | Q50: NO APLICA | R50: SI | S50: 2025 | T50: Mantenimiento Externo | U50: MEDICAL SYSTEM | W50: 140953.45 | X50: 2 | AD50: X | AJ50: X
A51: Atención Cerrada Hospitalización | B51: Bodega de Equipos | C51: Apoyo Terapéutico | D51: Mediano Costo | E51: Bomba Infusión Volumétrica | F51: BRAUN | G51: INFUSOMAT | H51: 976105 | I51: 75263 | J51: 2025 | K51: 10 | L51: =K51-($B$9-J51) -> 9 | M51: PROPIO | N51: BUENO | O51: IM ≥ 12 | P51: NO | Q51: 2025 | R51: SI | S51: 2025 | T51: Mantenimiento Externo | U51: Bbraun | X51: 2 | AD51: X | AJ51: X
A52: Unidad Urgencia Pabellón Quirúrgico | B52: Pabellón Quirúrgico Multiproposito | C52: Apoyo Terapéutico | D52: Mediano Costo | E52: Bomba Infusión Volumétrica | F52: BRAUN | G52: INFUSOMAT | H52: 976085 | I52: 75264 | J52: 2025 | K52: 10 | L52: =K52-($B$9-J52) -> 9 | M52: PROPIO | N52: BUENO | O52: IM ≥ 12 | P52: NO | Q52: 2025 | R52: SI | S52: 2025 | T52: Mantenimiento Externo | U52: Bbraun | X52: 2 | AD52: X | AJ52: X
A53: Atención Cerrada Hospitalización | B53: Bodega de Equipos | C53: Apoyo Terapéutico | D53: Mediano Costo | E53: Bomba Infusión Volumétrica | F53: BRAUN | G53: INFUSOMAT | H53: 976184 | I53: 75265 | J53: 2025 | K53: 10 | L53: =K53-($B$9-J53) -> 9 | M53: PROPIO | N53: BUENO | O53: IM ≥ 12 | P53: NO | Q53: 2025 | R53: SI | S53: 2025 | T53: Mantenimiento Externo | U53: Bbraun | X53: 2 | AD53: X | AJ53: X
A54: Atención Cerrada Hospitalización | B54: Bodega de Equipos | C54: Apoyo Terapéutico | D54: Mediano Costo | E54: Bomba Infusión Volumétrica | F54: BRAUN | G54: INFUSOMAT | H54: 976084 | I54: 75266 | J54: 2025 | K54: 10 | L54: =K54-($B$9-J54) -> 9 | M54: PROPIO | N54: BUENO | O54: IM ≥ 12 | P54: NO | Q54: 2025 | R54: SI | S54: 2025 | T54: Mantenimiento Externo | U54: Bbraun | X54: 2 | AD54: X | AJ54: X
A55: Unidad Urgencias | B55: Box Observación | C55: Apoyo Terapéutico | D55: Mediano Costo | E55: Bomba Infusión Volumétrica | F55: BRAUN | G55: INFUSOMAT | H55: 976108 | I55: 75268 | J55: 2025 | K55: 10 | L55: =K55-($B$9-J55) -> 9 | M55: PROPIO | N55: BUENO | O55: IM ≥ 12 | P55: NO | Q55: 2025 | R55: SI | S55: 2025 | T55: Mantenimiento Externo | U55: Bbraun | X55: 2 | AD55: X | AJ55: X
A56: Unidad Urgencias | B56: Box Observación | C56: Apoyo Terapéutico | D56: Mediano Costo | E56: Bomba Infusión Volumétrica | F56: BRAUN | G56: INFUSOMAT | H56: 976100 | I56: 75269 | J56: 2025 | K56: 10 | L56: =K56-($B$9-J56) -> 9 | M56: PROPIO | N56: BUENO | O56: IM ≥ 12 | P56: NO | Q56: 2025 | R56: SI | S56: 2025 | T56: Mantenimiento Externo | U56: Bbraun | X56: 2 | AD56: X | AJ56: X
A57: Unidad Urgencias | B57: Box Observación | C57: Apoyo Terapéutico | D57: Mediano Costo | E57: Bomba Infusión Volumétrica | F57: BRAUN | G57: INFUSOMAT | H57: 976106 | I57: 75270 | J57: 2025 | K57: 10 | L57: =K57-($B$9-J57) -> 9 | M57: PROPIO | N57: BUENO | O57: IM ≥ 12 | P57: NO | Q57: 2025 | R57: SI | S57: 2025 | T57: Mantenimiento Externo | U57: Bbraun | X57: 2 | AD57: X | AJ57: X
A58: Unidad Urgencia Pabellón Quirúrgico | B58: Sala de Parto Integral | C58: Apoyo Terapéutico | D58: Mediano Costo | E58: Bomba Infusión Volumétrica | F58: BRAUN | G58: INFUSOMAT | H58: 947601 | I58: 75272 | J58: 2025 | K58: 10 | L58: =K58-($B$9-J58) -> 9 | M58: PROPIO | N58: BUENO | O58: IM ≥ 12 | P58: NO | Q58: 2025 | R58: SI | S58: 2025 | T58: Mantenimiento Externo | U58: Bbraun | X58: 2 | AD58: X | AJ58: X
A59: Unidad Urgencias | B59: Sala Reanimación | C59: Apoyo Terapéutico | D59: Mediano Costo | E59: Bomba Infusión Volumétrica | F59: BRAUN | G59: INFUSOMAT | H59: 976112 | I59: 75267 | J59: 2025 | K59: 10 | L59: =K59-($B$9-J59) -> 9 | M59: PROPIO | N59: BUENO | O59: IM ≥ 12 | P59: NO | Q59: 2025 | R59: SI | S59: 2025 | T59: Mantenimiento Externo | U59: Bbraun | X59: 2 | AD59: X | AJ59: X
A60: Unidad Urgencia Pabellón Quirúrgico | B60: Sala Recuperación | C60: Apoyo Terapéutico | D60: Mediano Costo | E60: Bomba Infusión Volumétrica | F60: BRAUN | G60: INFUSOMAT | H60: 976095 | I60: 75273 | J60: 2025 | K60: 10 | L60: =K60-($B$9-J60) -> 9 | M60: PROPIO | N60: BUENO | O60: IM ≥ 12 | P60: NO | Q60: 2025 | R60: SI | S60: 2025 | T60: Mantenimiento Externo | U60: Bbraun | X60: 2 | AD60: X | AJ60: X
A61: Hospital Antiguo | B61: Bodega EQM | C61: Med. Física y Rehabilitación | D61: Bajo Costo | E61: Calentador Compresas | F61: HYDROCOLLATOR | G61: E2 | H61: T2043 | I61: 74173 | J61: 2015 | K61: 10 | L61: 0 | M61: PROPIO | N61: BUENO | O61: IM ≥ 12 | P61: NO | Q61: NO APLICA | R61: SI | S61: 2026 | T61: Mantenimiento Externo | X61: 2 | AD61: X | AJ61: X
A62: Medicina Fisica y Rehabilitación | B62: Camilla 2 | C62: Med. Física y Rehabilitación | D62: Bajo Costo | E62: Calentador Compresas con compresas | F62: RELIEF | G62: 111994 | H62: RP8M0389 | I62: 75111 | J62: 2025 | K62: 10 | L62: =K62-($B$9-J62) -> 9 | M62: PROPIO | N62: BUENO | O62: IM ≥ 12 | P62: NO | Q62: 2025 | R62: SI | S62: 2027 | T62: Mantenimiento Interno | U62: Doctor Choice | X62: 1 | AJ62: X
A63: Atención Abierta | B63: Laboratorio Dental | C63: Odontología | D63: Bajo Costo | E63: Calentador de Cera | F63: GENERICO | G63: JT-15 | H63: S/S | I63: 76576 | J63: 2025 | K63: 10 | L63: =K63-($B$9-J63) -> 9 | M63: PROPIO | N63: BUENO | O63: NO APLICA | P63: NO | Q63: 2025 | R63: NO | S63: 2027 | U63: Dental Laval | X63: 0
A64: Unidad Urgencias | B64: Sala Reanimación | C64: Apoyo Terapéutico | D64: Bajo Costo | E64: Calentador de fluidos | F64: QUALMEDI | G64: 120B | I64: 76770 | J64: 2025 | K64: 10 | L64: =K64-($B$9-J64) -> 9 | M64: PROPIO | N64: BUENO | O64: NO APLICA | P64: SI | Q64: 2026 | R64: SI | S64: 2026 | T64: Mantenimiento Externo | U64: Ortopedia 3D | X64: 1 | AA64: √
A65: Unidad Urgencias | B65: Box Observación | C65: Apoyo Terapéutico | D65: Bajo Costo | E65: Calentador de Pacientes | F65: CALIMA | G65: CCALIMA22 | H65: 230302675 | I65: 75058 | J65: 2025 | K65: 10 | L65: =K65-($B$9-J65) -> 9 | M65: PROPIO | N65: BUENO | O65: NO APLICA | P65: SI | Q65: 2026 | R65: SI | S65: 2026 | T65: Mantenimiento Externo | U65: Medtronic | X65: 1 | AD65: X
A66: Atención Cerrada Hospitalización | B66: Estación Enfermería | C66: Apoyo Terapéutico | D66: Bajo Costo | E66: Calentador de Pacientes | F66: CALIMA | G66: CCALIMA22 | H66: 230302673 | I66: 75056 | J66: 2025 | K66: 10 | L66: =K66-($B$9-J66) -> 9 | M66: PROPIO | N66: BUENO | O66: NO APLICA | P66: SI | Q66: 2026 | R66: SI | S66: 2026 | T66: Mantenimiento Externo | U66: Medtronic | X66: 1 | AD66: X
A67: Atención Cerrada Hospitalización | B67: Estación Enfermería | C67: Apoyo Terapéutico | D67: Bajo Costo | E67: Calentador de Pacientes | F67: CALIMA | G67: CCALIMA22 | H67: 230302674 | I67: 75057 | J67: 2025 | K67: 10 | L67: =K67-($B$9-J67) -> 9 | M67: PROPIO | N67: BUENO | O67: NO APLICA | P67: SI | Q67: 2026 | R67: SI | S67: 2026 | T67: Mantenimiento Externo | U67: Medtronic | X67: 1 | AD67: X
A68: Unidad Urgencia Pabellón Quirúrgico | B68: Estación Enfermería (Área Limpia) | C68: Apoyo Terapéutico | D68: Bajo Costo | E68: Calentador de Sueros | F68: QUALMEDI | G68: 120B | H68: S/S | I68: 76550 | J68: 2025 | K68: 10 | L68: =K68-($B$9-J68) -> 9 | M68: PROPIO | N68: BUENO | O68: NO APLICA | P68: SI | Q68: 2026 | R68: SI | S68: 2026 | T68: Mantenimiento Externo | U68: Ortopedia 3D | X68: 1 | AA68: √
A69: Unidad Urgencia Pabellón Quirúrgico | B69: Sala Parto Integral | C69: Apoyo Terapéutico | D69: Alto Costo | E69: Cama de parto integral | F69: PARDO | G69: NEW BABYCHAIR | H69: 2269604 | I69: 76694 | J69: 2025 | K69: 10 | L69: =K69-($B$9-J69) -> 9 | M69: PROPIO | N69: BUENO | O69: IM ≥ 12 | P69: SI | Q69: 2026 | R69: SI | S69: 2026 | T69: Mantenimiento Externo | U69: Plusmedical | X69: 1 | AD69: X
A70: Depósito de Cadáveres | B70: Morgue | C70: Apoyo Quirúrgico | D70: Alto Costo | E70: Cámara Mortuoria (capacidad 2 cadaveres) | F70: MATACHANA | G70: dos cuerpos lateral | H70: CLF24173 | I70: 75116 | J70: 2025 | K70: 10 | L70: =K70-($B$9-J70) -> 9 | M70: PROPIO | N70: BUENO | O70: IM ≥ 12 | P70: NO | Q70: 2025 | R70: SI | S70: 2025 | T70: Mantenimiento Externo | U70: IClinics | X70: 1 | AI70: X
A71: Depósito de Cadáveres | B71: Sala de espera y entrega de Cadaveres | C71: Laboratorio/Farmacia | D71: Mediano Costo | E71: Camilla cadáver | J71: 2025 | K71: 10 | L71: =K71-($B$9-J71) -> 9 | M71: PROPIO | N71: BUENO | O71: NO APLICA | P71: NO | Q71: 2025 | R71: SI | S71: 2025 | T71: Mantenimiento Externo | U71: Consorcio | X71: 1 | AI71: X
A72: Medicina Fisica y Rehabilitación | B72: Camilla 1 | C72: Apoyo Terapéutico | D72: Bajo Costo | E72: Camilla de exámen | F72: SAIKANG | G72: X09-A | H72: X09240441021 | I72: 75244 | J72: 2025 | K72: 10 | L72: =K72-($B$9-J72) -> 9 | M72: PROPIO | N72: BUENO | O72: NO APLICA | P72: SI | Q72: 2026 | R72: SI | S72: 2026 | T72: Mantenimiento Externo | U72: Plusmedical | X72: 1 | AD72: X
A73: Medicina Fisica y Rehabilitación | B73: Camilla 2 | C73: Apoyo Terapéutico | D73: Bajo Costo | E73: Camilla de exámen | F73: SAIKANG | G73: X09-A | H73: X09240441043 | I73: 75245 | J73: 2025 | K73: 10 | L73: =K73-($B$9-J73) -> 9 | M73: PROPIO | N73: BUENO | O73: NO APLICA | P73: SI | Q73: 2026 | R73: SI | S73: 2026 | T73: Mantenimiento Externo | U73: Plusmedical | X73: 1 | AD73: X
A74: Medicina Fisica y Rehabilitación | B74: Sala de evaluación | C74: Apoyo Terapéutico | D74: Bajo Costo | E74: Camilla de exámen | F74: SAIKANG | G74: X09-A | H74: X09240441044 | I74: 75246 | J74: 2025 | K74: 10 | L74: =K74-($B$9-J74) -> 9 | M74: PROPIO | N74: BUENO | O74: NO APLICA | P74: SI | Q74: 2026 | R74: SI | S74: 2026 | T74: Mantenimiento Externo | U74: Plusmedical | X74: 1 | AD74: X
A75: Atención Abierta | B75: Box Procedimientos N°2 | C75: Apoyo Terapéutico | D75: Bajo Costo | E75: Camilla de Examen con barandas | F75: SAIKANG | G75: X09-02 | H75: X0924041013 | I75: 75231 | J75: 2025 | K75: 10 | L75: =K75-($B$9-J75) -> 9 | M75: PROPIO | N75: BUENO | O75: NO APLICA | P75: SI | Q75: 2026 | R75: SI | S75: 2026 | T75: Mantenimiento Externo | U75: Plusmedical | X75: 1 | AD75: X
A76: Atención Abierta | B76: Box Procedimientos N°2 | C76: Apoyo Terapéutico | D76: Bajo Costo | E76: Camilla de Examen con barandas | F76: SAIKANG | G76: X09-02 | H76: X0924041014 | I76: 75232 | J76: 2025 | K76: 10 | L76: =K76-($B$9-J76) -> 9 | M76: PROPIO | N76: BUENO | O76: NO APLICA | P76: SI | Q76: 2026 | R76: SI | S76: 2026 | T76: Mantenimiento Externo | U76: Plusmedical | X76: 1 | AD76: X
A77: Atención Abierta | B77: Box Multiproposito N°6 | C77: Apoyo Terapéutico | D77: Bajo Costo | E77: Camilla de Examen con barandas | F77: SAIKANG | G77: X09-02 | H77: X0924041012 | I77: 75230 | J77: 2025 | K77: 10 | L77: =K77-($B$9-J77) -> 9 | M77: PROPIO | N77: BUENO | O77: NO APLICA | P77: SI | Q77: 2026 | R77: SI | S77: 2026 | T77: Mantenimiento Externo | U77: Plusmedical | X77: 1 | AD77: X
A78: Atención Abierta | B78: Box Multipropósito Nº2 | C78: Apoyo Terapéutico | D78: Bajo Costo | E78: Camilla de Examen con barandas | F78: SAIKANG | G78: X09-02 | H78: X0924041003 | I78: 75221 | J78: 2025 | K78: 10 | L78: =K78-($B$9-J78) -> 9 | M78: PROPIO | N78: BUENO | O78: NO APLICA | P78: SI | Q78: 2026 | R78: SI | S78: 2026 | T78: Mantenimiento Externo | U78: Plusmedical | X78: 1 | AD78: X
A79: Atención Abierta | B79: Box Multipropósito Nº3 | C79: Apoyo Terapéutico | D79: Bajo Costo | E79: Camilla de Examen con barandas | F79: SAIKANG | G79: X09-02 | H79: X0924041004 | I79: 75222 | J79: 2025 | K79: 10 | L79: =K79-($B$9-J79) -> 9 | M79: PROPIO | N79: BUENO | O79: NO APLICA | P79: SI | Q79: 2026 | R79: SI | S79: 2026 | T79: Mantenimiento Externo | U79: Plusmedical | X79: 1 | AD79: X
A80: Atención Abierta | B80: Box Multipropósito Nº4 | C80: Apoyo Terapéutico | D80: Bajo Costo | E80: Camilla de Examen con barandas | F80: SAIKANG | G80: X09-02 | H80: X0924041005 | I80: 75223 | J80: 2025 | K80: 10 | L80: =K80-($B$9-J80) -> 9 | M80: PROPIO | N80: BUENO | O80: NO APLICA | P80: SI | Q80: 2026 | R80: SI | S80: 2026 | T80: Mantenimiento Externo | U80: Plusmedical | X80: 1 | AD80: X
A81: Atención Abierta | B81: Box Multipropósito Nº5 | C81: Apoyo Terapéutico | D81: Bajo Costo | E81: Camilla de Examen con barandas | F81: SAIKANG | G81: X09-02 | H81: X0924041006 | I81: 75224 | J81: 2025 | K81: 10 | L81: =K81-($B$9-J81) -> 9 | M81: PROPIO | N81: BUENO | O81: NO APLICA | P81: SI | Q81: 2026 | R81: SI | S81: 2026 | T81: Mantenimiento Externo | U81: Plusmedical | X81: 1 | AD81: X
A82: Atención Abierta | B82: Box Multipropósito N°8 | C82: Apoyo Terapéutico | D82: Bajo Costo | E82: Camilla de Examen con barandas | F82: SAIKANG | G82: X09-02 | H82: X0924041007 | I82: 75225 | J82: 2025 | K82: 10 | L82: =K82-($B$9-J82) -> 9 | M82: PROPIO | N82: BUENO | O82: NO APLICA | P82: SI | Q82: 2026 | R82: SI | S82: 2026 | T82: Mantenimiento Externo | U82: Plusmedical | X82: 1 | AD82: X
A83: Atención Abierta | B83: Box Rondas Médicas | C83: Apoyo Terapéutico | D83: Bajo Costo | E83: Camilla de Examen con barandas | F83: SAIKANG | G83: X09-02 | H83: X0924041008 | I83: 75226 | J83: 2025 | K83: 10 | L83: =K83-($B$9-J83) -> 9 | M83: PROPIO | N83: BUENO | O83: NO APLICA | P83: SI | Q83: 2026 | R83: SI | S83: 2026 | T83: Mantenimiento Externo | U83: Plusmedical | X83: 1 | AD83: X
... A106: Laboratorio | B106: Toma de Muestras | C106: Apoyo Terapéutico | D106: Bajo Costo | E106: Camilla Transporte Paciente | F106: SAIKANG | G106: Skb041 | H106: SKB041-324093016 | I106: 75243 | J106: 2025 | K106: 10 | L106: =K106-($B$9-J106) -> 9 | M106: PROPIO | N106: BUENO | O106: IM ≥ 12 | P106: SI | Q106: 2026 | R106: SI | S106: 2026 | T106: Mantenimiento Externo | U106: Plusmedical | X106: 1 | AD106: X
A107: Medicina Fisica y Rehabilitación | B107: Area de Gimnasio infantil y adulto (actividades terapeuticas) | C107: Med. Física y Rehabilitación | D107: Mediano Costo | E107: Caminadora | F107: DYACO | G107: 7.0T | H107: 24070045 | I107: 76166 | J107: 2025 | K107: 10 | L107: =K107-($B$9-J107) -> 9 | M107: PROPIO | N107: BUENO | O107: IM ≥ 12 | P107: SI | Q107: 2027 | R107: SI | S107: 2026 | T107: Mantenimiento Externo | U107: Sportmaster | X107: 1 | AC107: X
A108: Medicina Fisica y Rehabilitación | B108: Area de Gimnasio infantil y adulto (actividades terapeuticas) | C108: Med. Física y Rehabilitación | D108: Mediano Costo | E108: Caminadora | F108: DYACO | G108: 7.0T | H108: 24070046 | I108: 76167 | J108: 2025 | K108: 10 | L108: =K108-($B$9-J108) -> 9 | M108: PROPIO | N108: BUENO | O108: IM ≥ 12 | P108: SI | Q108: 2027 | R108: SI | S108: 2026 | T108: Mantenimiento Externo | U108: Sportmaster | X108: 1 | AC108: X
A109: Hospital Antiguo | B109: Bodega EQM | C109: Apoyo Terapéutico | D109: Mediano Costo | E109: Cánula Nasal de Alto Flujo (CNAF) | F109: FISHER & PAYKEL | G109: AIRVO 2 | H109: 210323251456 | I109: 74190 | J109: 2024 | K109: 10 | L109: 9 | M109: PROPIO | N109: BUENO | O109: CRÍTICO | P109: NO | Q109: NO APLICA | R109: NO | S109: 2025 | T109: Mantenimiento Externo | X109: 2 | AD109: X | AJ109: X
A110: Depósito de Cadáveres | B110: Depósito de Cadáveres | C110: Apoyo Quirúrgico | D110: Mediano Costo | E110: Carro de Transporte Cadáveres | F110: MATACHANA | G110: REINAX | H110: S/S | I110: 75118 | J110: 2025 | K110: 10 | L110: =K110-($B$9-J110) -> 9 | M110: PROPIO | N110: BUENO | O110: NO APLICA | P110: NO | Q110: 2025 | R110: SI | S110: 2026 | T110: Mantenimiento Externo | U110: IClinics | X110: 1 | AI110: X
A111: Unidad Urgencias | B111: Box Atención Yeso | C111: Apoyo Terapéutico | D111: Mediano Costo | E111: Carro de Yeso | F111: MAGNÉTICA SHOP | G111: 50 CM x 100 CM x 90 CM acero inoxidable AISI304 | H111: S/S | I111: 76222 | J111: 2025 | K111: 10 | L111: =K111-($B$9-J111) -> 9 | M111: PROPIO | N111: BUENO | O111: IM ≥ 12 | P111: SI | Q111: 2026 | R111: SI | S111: 2026 | T111: Mantenimiento Externo | U111: Magnetica Shop | X111: 1 | AE111: X
A112: Depósito de Cadáveres | B112: Depósito de Cadáveres | C112: Apoyo Quirúrgico | D112: Alto Costo | E112: Carro elevador cadaver | F112: MATACHANA | G112: para camas laterales | H112: ELE0224131 | I112: 75117 | J112: 2025 | K112: 10 | L112: =K112-($B$9-J112) -> 9 | M112: PROPIO | N112: BUENO | O112: IM ≥ 12 | P112: NO | Q112: 2025 | R112: SI | S112: 2026 | T112: Mantenimiento Externo | U112: IClinics | X112: 1 | AI112: X
A113: Atención Cerrada Hospitalización | B113: Sala 1- 2 camas + Baño | C113: Apoyo Terapéutico | D113: Alto Costo | E113: Catre Clínico Eléctrico | F113: PARDO | G113: Advantcare | H113: 1636913 | I113: 75235 | J113: 2025 | K113: 10 | L113: =K113-($B$9-J113) -> 9 | M113: PROPIO | N113: BUENO | O113: IM ≥ 12 | P113: SI | Q113: 2026 | R113: SI | S113: 2026 | T113: Mantenimiento Externo | U113: Plusmedical | X113: 1 | AD113: X
A114: Atención Cerrada Hospitalización | B114: Sala 2- 2 camas + Baño | C114: Apoyo Terapéutico | D114: Alto Costo | E114: Catre Clínico Eléctrico | F114: PARDO | G114: Advantcare | H114: 1636919 | I114: 75237 | J114: 2025 | K114: 10 | L114: =K114-($B$9-J114) -> 9 | M114: PROPIO | N114: BUENO | O114: IM ≥ 12 | P114: SI | Q114: 2026 | R114: SI | S114: 2026 | T114: Mantenimiento Externo | U114: Plusmedical | X114: 1 | AD114: X
A115: Atención Cerrada Hospitalización | B115: Sala 2- 2 camas + Baño | C115: Apoyo Terapéutico | D115: Alto Costo | E115: Catre Clínico Eléctrico | F115: PARDO | G115: Advantcare | H115: 1636924 | I115: 75238 | J115: 2025 | K115: 10 | L115: =K115-($B$9-J115) -> 9 | M115: PROPIO | N115: BUENO | O115: IM ≥ 12 | P115: SI | Q115: 2026 | R115: SI | S115: 2026 | T115: Mantenimiento Externo | U115: Plusmedical | X115: 1 | AD115: X
A116: Atención Cerrada Hospitalización | B116: Sala 3 -2 camas + Baño | C116: Apoyo Terapéutico | D116: Alto Costo | E116: Catre Clínico Eléctrico | F116: PARDO | G116: Advantcare | H116: 1636928 | I116: 75239 | J116: 2025 | K116: 10 | L116: =K116-($B$9-J116) -> 9 | M116: PROPIO | N116: BUENO | O116: IM ≥ 12 | P116: SI | Q116: 2026 | R116: SI | S116: 2026 | T116: Mantenimiento Externo | U116: Plusmedical | X116: 1 | AD116: X
A117: Atención Cerrada Hospitalización | B117: Sala 3 -2 camas + Baño | C117: Apoyo Terapéutico | D117: Alto Costo | E117: Catre Clínico Eléctrico | F117: PARDO | G117: Advantcare | H117: 1636915 | I117: 75240 | J117: 2025 | K117: 10 | L117: =K117-($B$9-J117) -> 9 | M117: PROPIO | N117: BUENO | O117: IM ≥ 12 | P117: SI | Q117: 2026 | R117: SI | S117: 2026 | T117: Mantenimiento Externo | U117: Plusmedical | X117: 1 | AD117: X
A118: Atención Cerrada Hospitalización | B118: Sala 4 - 1 camas + Baño | C118: Apoyo Terapéutico | D118: Alto Costo | E118: Catre Clínico Eléctrico | F118: PARDO | G118: Advantcare | H118: 1636914 | I118: 75236 | J118: 2025 | K118: 10 | L118: =K118-($B$9-J118) -> 9 | M118: PROPIO | N118: BUENO | O118: IM ≥ 12 | P118: SI | Q118: 2026 | R118: SI | S118: 2026 | T118: Mantenimiento Externo | U118: Plusmedical | X118: 1 | AD118: X
A119: Atención Cerrada Hospitalización | B119: Sala 4- 1 cama + Baño | C119: Apoyo Terapéutico | D119: Alto Costo | E119: Catre Clínico Eléctrico | F119: PARDO | G119: Advantcare | H119: 1636909 | I119: 75234 | J119: 2025 | K119: 10 | L119: =K119-($B$9-J119) -> 9 | M119: PROPIO | N119: BUENO | O119: IM ≥ 12 | P119: SI | Q119: 2026 | R119: SI | S119: 2026 | T119: Mantenimiento Externo | U119: Plusmedical | X119: 1 | AD119: X
A120: Laboratorio | B120: Entrega de Sangre (Unidad Medicina Transfusional) | C120: Laboratorio/Farmacia | D120: Mediano Costo | E120: Centrifuga de tarjeta de gel | F120: ALLSHENG | G120: TD2-12 | H120: AS-10030-00 | I120: 75065 | J120: 2025 | K120: 10 | L120: =K120-($B$9-J120) -> 9 | M120: PROPIO | N120: BUENO | O120: RELEVANTE | P120: SI | Q120: 2026 | R120: SI | S120: 2026 | T120: Mantenimiento Externo | U120: Winkler | X120: 1 | AB120: X
A121: Laboratorio | B121: Hematología Química Clínica | C121: Laboratorio/Farmacia | D121: Mediano Costo | E121: Centrifuga hematológica | F121: EPPENDORF | G121: 5702 | H121: 5702MQ461214 | I121: 75186 | J121: 2025 | K121: 10 | L121: =K121-($B$9-J121) -> 9 | M121: PROPIO | N121: BUENO | O121: RELEVANTE | P121: SI | Q121: 2027 | R121: SI | S121: 2026 | T121: Mantenimiento Externo | U121: Arquimed | X121: 1 | AD121: X
A122: Laboratorio | B122: Bacteriología y Orina | C122: Laboratorio/Farmacia | D122: Mediano Costo | E122: Centrífuga Universal (4000-5000 RPM, 6 tubos, 15ml) | F122: EPPENDORF | G122: 5702 | H122: 5702MQ461230 | I122: 75184 | J122: 2025 | K122: 10 | L122: =K122-($B$9-J122) -> 9 | M122: PROPIO | N122: BUENO | O122: RELEVANTE | P122: SI | Q122: 2027 | R122: SI | S122: 2026 | T122: Mantenimiento Externo | U122: Arquimed | X122: 1 | AD122: X
A123: Laboratorio | B123: Hematología Química Clínica | C123: Laboratorio/Farmacia | D123: Mediano Costo | E123: Centrífuga Universal (4000-5000 RPM, 6 tubos, 15ml) | F123: EPPENDORF | G123: 5702 | H123: 5702MQ461229 | I123: 75185 | J123: 2025 | K123: 10 | L123: =K123-($B$9-J123) -> 9 | M123: PROPIO | N123: BUENO | O123: RELEVANTE | P123: SI | Q123: 2027 | R123: SI | S123: 2026 | T123: Mantenimiento Externo | U123: Arquimed | X123: 1 | AD123: X
A124: Atención Abierta | B124: Laboratorio Dental | C124: Odontología | D124: Bajo Costo | E124: Cortador de yeso | F124: ESSENCE | G124: 2482 | H124: RG2617 | I124: 76090 | J124: 2025 | K124: 10 | L124: =K124-($B$9-J124) -> 9 | M124: PROPIO | N124: BUENO | O124: IM ≥ 12 | P124: SI | Q124: 2026 | R124: NO | S124: 2027 | U124: Dental Laval | X124: 0
A125: Hospital Antiguo | B125: Bodega EQM | C125: Apoyo Terapéutico | D125: Alto Costo | E125: Cuna Cuidados Intensivos | F125: AIR SHIELD | G125: PM78-1E | H125: QG16607 | I125: 74179 | J125: 2015 | K125: 10 | L125: 0 | M125: PROPIO | N125: BUENO | O125: IM ≥ 12 | P125: NO | Q125: NO APLICA | R125: SI | S125: 2025 | T125: Mantenimiento Externo | U125: MEDICAL SYSTEM | W125: 246971.63 | X125: 1 | AJ125: X
A126: Atención Cerrada Hospitalización | B126: Bodega de Equipos | C126: Apoyo Terapéutico | D126: Bajo Costo | E126: Cuna Lactante | F126: SAIKANG | G126: X01-5 | H126: X01-523097001 | I126: 75101 | J126: 2025 | K126: 10 | L126: =K126-($B$9-J126) -> 9 | M126: PROPIO | N126: BUENO | O126: NO APLICA | P126: SI | Q126: 2027 | R126: SI | S126: 2026 | T126: Mantenimiento Externo | U126: Plusmedical | X126: 1 | AD126: X
A127: Atención Cerrada Hospitalización | B127: Fototerapia | C127: Apoyo Terapéutico | D127: Bajo Costo | E127: Cuna Lactante | F127: SAIKANG | G127: X01-5 | H127: X01-523076028 | I127: 75093 | J127: 2025 | K127: 10 | L127: =K127-($B$9-J127) -> 9 | M127: PROPIO | N127: BUENO | O127: NO APLICA | P127: SI | Q127: 2027 | R127: SI | S127: 2026 | T127: Mantenimiento Externo | U127: Plusmedical | X127: 1 | AD127: X
...

Sheet Hoja3
A1: SERVICIO CLÍNICO | B1: RECINTO | C1: CLASE | D1: SUBCLASE | E1: NOMBRE EQUIPO | F1: MARCA | G1: MODELO | H1: SERIE | I1: N° INVENTARIO
A2: Laboratorio | B2: Hematología Química Clínica | C2: Laboratorio/Farmacia | D2: Bajo Costo | E2: Agitador de muestras (tipo vortex) | F2: DLAB | G2: MX-S | H2: VB232AS0008474 | I2: 75188
A3: Laboratorio | B3: Bacteriología y Orina | C3: Laboratorio/Farmacia | D3: Bajo Costo | E3: Agitador Magnetico (RPR) | F3: DIGISYSTEM | G3: DS-DSR2100D | H3: S/S | I3: 75067
A4: Laboratorio | B4: Hematología Química Clínica | C4: Laboratorio/Farmacia | D4: Alto Costo | E4: Analizador Hematologico Digital (Células Sanguíneas) | F4: DIGISYSTEM | G4: DBC-9D-M | H4: S/S | I4: 75066
A5: Atención Abierta | B5: Laboratorio Dental | C5: Odontología | D5: Bajo Costo | E5: Arenadora con cajón | F5: ESSENCE | G5: EVOLUT | H5: TJ0124 | I5: 76577
A6: Hospital Antiguo | B6: Bodega EQM | C6: Esterilización | D6: Alto Costo | E6: AUTOCLAVE | F6: MINGTAI | G6: SUN45-III | H6: SA2211296 | I6: 74052
A7: Esterilización | B7: Material Esteril (Autoclave) | C7: Esterilización | D7: Alto Costo | E7: Autoclave 100 Litros (2 STU) | F7: MATACHANA | G7: SC500E-1 | H7: E-35162 | I7: 75041
A8: Sedile | B8: Sedile | C8: Esterilización | D8: Alto Costo | E8: Autoclave 21 Litros | F8: MATACHANA | G8: M20-B | H8: 34122 | I8: 75039
A9: Laboratorio | B9: Descontaminacion y Lavado | C9: Esterilización | D9: Alto Costo | E9: Autoclave 50Lt vertical | F9: RAYPA | G9: AE-50-DRY | H9: 443333 | I9: 75038
A10: Unidad Urgencias | B10: Closet EQM | C10: Apoyo Diagnóstico | D10: Alto Costo | E10: Autorefractómetro | F10: NIDEK | G10: Ark-1 | H10: S/N | I10: 75071
A11: Laboratorio | B11: Entrega de Sangre (Unidad Medicina Transfusional) | C11: Laboratorio/Farmacia | D11: Mediano Costo | E11: Balanza de presición | F11: BIOLOGIX | G11: 01-BD304N4 | H11: YS05202410006 | I11: 75302
A12: Laboratorio | B12: Hematología Química Clínica | C12: Laboratorio/Farmacia | D12: Bajo Costo | E12: Baño Termoregulado | F12: LAUDA | G12: HYDRO H8 | H12: S230014557 | I12: 75187
A13: Hospital Antiguo | B13: Bodega EQM | C13: Med. Física y Rehabilitación | D13: Alto Costo | E13: BAÑO TURBIÓN EXTREMIDAD INFERIOR | F13: S/M | G13: S/M | H13: S/N | I13: 74177
A14: Medicina Fisica y Rehabilitación | B14: Area de Gimnasio infantil y adulto (actividades terapeuticas) | C14: Med. Física y Rehabilitación | D14: Mediano Costo | E14: Bicicleta Ergonométrica | F14: DYACO | G14: 7.0 | H14: 20-24080029 | I14: 75299
A15: Medicina Fisica y Rehabilitación | B15: Area de Gimnasio infantil y adulto (actividades terapeuticas) | C15: Med. Física y Rehabilitación | D15: Mediano Costo | E15: Bicicleta Ergonométrica | F15: DYACO | G15: 7.0 | H15: 30-24080019 | I15: 75300
A16: Atención Cerrada Hospitalización | B16: Bodega de Equipos | C16: Apoyo Terapéutico | D16: Bajo Costo | E16: Bomba Alimentación Enteral | F16: FEEGIND PUMP | G16: FP300 | H16: 8014223 | I16: 75134
A17: Unidad Urgencia Pabellón Quirúrgico | B17: Pabellón Quirúrgico Multiproposito | C17: Apoyo Quirúrgico | D17: Bajo Costo | E17: Bomba Aspiración Quirúrgica | F17: CAMI | G17: NEW HOSPIVAC 350 | H17: 41017 | I17: 75072
A18: Unidad Urgencia Pabellón Quirúrgico | B18: Sala de Parto Integral | C18: Apoyo Quirúrgico | D18: Bajo Costo | E18: Bomba Aspiración Quirúrgica | F18: CAMI | G18: NEW HOSPIVAC 350 | H18: 41013 | I18: 75073
A19: Hospital Antiguo | B19: Bodega EQM | C19: Apoyo Quirúrgico | D19: Bajo Costo | E19: Bomba de Aspiración | F19: CA-MI | G19: 230-12BR | H19: 2470 | I19: 74184
A20: Hospital Antiguo | B20: Bodega EQM | C20: Apoyo Quirúrgico | D20: Bajo Costo | E20: Bomba de Aspiración | F20: DEVILBISS | G20: 7314P-D | H20: 4PD061810 | I20: 74191
A21: Hospital Antiguo | B21: Bodega EQM | C21: Apoyo Quirúrgico | D21: Bajo Costo | E21: Bomba de Aspiración | F21: EACHMAN | G21: VP35 | H21: V3AB-90-1141 | I21: 74210
A22: Hospital Antiguo | B22: Bodega EQM | C22: Apoyo Quirúrgico | D22: Bajo Costo | E22: Bomba de Aspiración | F22: MEDI AIR | G22: SUBOI SERIES | H22: SU12K00846 | I22: 74194
A23: Hospital Antiguo | B23: Bodega EQM | C23: Apoyo Quirúrgico | D23: Bajo Costo | E23: Bomba de Aspiración | F23: NEW ASKIR | G23: 230-12BR | H23: 19979 | I23: 74187
A24: Hospital Antiguo | B24: Bodega EQM | C24: Apoyo Quirúrgico | D24: Bajo Costo | E24: Bomba de Aspiración | F24: THOMAS | G24: 1636 | H24: 16900002248
A25: Hospital Antiguo | B25: Bodega EQM | C25: Apoyo Quirúrgico | D25: Bajo Costo | E25: Bomba de Aspiración | F25: APEX MEDICAL | G25: VAC PLUS | H25: 077B-04591
A26: Atención Cerrada Hospitalización | B26: Bodega de Equipos | C26: Apoyo Quirúrgico | D26: Bajo Costo | E26: Bomba de Aspiración | F26: FLAEM | G26: ASPIRA PLUS | H26: 23AK260037 | I26: 76591
A27: Atención Abierta | B27: Box Tratamiento Respiratorio (IRA) | C27: Apoyo Quirúrgico | D27: Bajo Costo | E27: Bomba de Aspiración | F27: FLAEM | G27: ASPIRA PLUS | H27: 23AK260048 | I27: 75108
A28: Atención Cerrada Hospitalización | B28: Estación Enfermería | C28: Apoyo Quirúrgico | D28: Bajo Costo | E28: Bomba de Aspiración | F28: FLAEM | G28: ASPIRA PLUS | H28: 23AK260047 | I28: 75110
A29: Unidad Urgencias | B29: Estación Enfermería | C29: Apoyo Quirúrgico | D29: Bajo Costo | E29: Bomba de Aspiración | F29: FLAEM | G29: ASPIRA PLUS | H29: 23AK260031 | I29: 75113
A30: Unidad Urgencias | B30: Sala Reanimación | C30: Apoyo Quirúrgico | D30: Bajo Costo | E30: Bomba de Aspiración | F30: FLAEM | G30: ASPIRA PLUS | H30: 23AK260032 | I30: 75114
A31: Unidad Urgencias | B31: Box Atención 2 | C31: Apoyo Quirúrgico | D31: Bajo Costo | E31: Bomba de Aspiración | F31: FLAEM | G31: ASPIRA PLUS | H31: 23AK260038 | I31: 75115
A32: Unidad Urgencia Pabellón Quirúrgico | B32: Estación Enfermería (Área Limpia) | C32: Apoyo Terapéutico | D32: Mediano Costo | E32: Bomba Infusión Jeringa | F32: BRAUN | G32: B/BRAUN | H32: 644181 | I32: 75275
A33: Hospital Antiguo | B33: Bodega EQM | C33: Apoyo Terapéutico | D33: Mediano Costo | E33: Bomba Infusión Volumétrica | F33: BBRAUN | G33: INFUSOMAT COMPACT | H33: 46195 | I33: 74061
A34: Hospital Antiguo | B34: Bodega EQM | C34: Apoyo Terapéutico | D34: Mediano Costo | E34: Bomba Infusión Volumétrica | F34: FRESENIUS KABI | G34: VOLUMAT MAC AGILIA | H34: 019181/22324963 | I34: 74062
A35: Hospital Antiguo | B35: Bodega EQM | C35: Apoyo Terapéutico | D35: Mediano Costo | E35: Bomba Infusión Volumétrica | F35: FRESENIUS KABI | G35: VOLUMAT MAC AGILIA | H35: 20885416 | I35: 74201
A36: Hospital Antiguo | B36: Bodega EQM | C36: Apoyo Terapéutico | D36: Mediano Costo | E36: Bomba Infusión Volumétrica | F36: BBRAUN | G36: SPACE PLUS INFUSOMAT | H36: 51822 | I36: 74197
A37: Atención Cerrada Hospitalización | B37: Bodega de Equipos | C37: Apoyo Terapéutico | D37: Mediano Costo | E37: Bomba Infusión Volumétrica | F37: BRAUN | G37: INFUSOMAT | H37: 976105 | I37: 75263
A38: Unidad Urgencia Pabellón Quirúrgico | B38: Pabellón Quirúrgico Multiproposito | C38: Apoyo Terapéutico | D38: Mediano Costo | E38: Bomba Infusión Volumétrica | F38: BRAUN | G38: INFUSOMAT | H38: 976085 | I38: 75264
A39: Atención Cerrada Hospitalización | B39: Bodega de Equipos | C39: Apoyo Terapéutico | D39: Mediano Costo | E39: Bomba Infusión Volumétrica | F39: BRAUN | G39: INFUSOMAT | H39: 976184 | I39: 75265
A40: Atención Cerrada Hospitalización | B40: Bodega de Equipos | C40: Apoyo Terapéutico | D40: Mediano Costo | E40: Bomba Infusión Volumétrica | F40: BRAUN | G40: INFUSOMAT | H40: 976084 | I40: 75266
A41: Unidad Urgencias | B41: Box Observación | C41: Apoyo Terapéutico | D41: Mediano Costo | E41: Bomba Infusión Volumétrica | F41: BRAUN | G41: INFUSOMAT | H41: 976108 | I41: 75268
A42: Unidad Urgencias | B42: Box Observación | C42: Apoyo Terapéutico | D42: Mediano Costo | E42: Bomba Infusión Volumétrica | F42: BRAUN | G42: INFUSOMAT | H42: 976100 | I42: 75269
A43: Unidad Urgencias | B43: Box Observación | C43: Apoyo Terapéutico | D43: Mediano Costo | E43: Bomba Infusión Volumétrica | F43: BRAUN | G43: INFUSOMAT | H43: 976106 | I43: 75270
A44: Unidad Urgencia Pabellón Quirúrgico | B44: Sala de Parto Integral | C44: Apoyo Terapéutico | D44: Mediano Costo | E44: Bomba Infusión Volumétrica | F44: BRAUN | G44: INFUSOMAT | H44: 947601 | I44: 75272
A45: Unidad Urgencias | B45: Sala Reanimación | C45: Apoyo Terapéutico | D45: Mediano Costo | E45: Bomba Infusión Volumétrica | F45: BRAUN | G45: INFUSOMAT | H45: 976112 | I45: 75267
A46: Unidad Urgencia Pabellón Quirúrgico | B46: Sala Recuperación | C46: Apoyo Terapéutico | D46: Mediano Costo | E46: Bomba Infusión Volumétrica | F46: BRAUN | G46: INFUSOMAT | H46: 976095 | I46: 75273
A47: Hospital Antiguo | B47: Bodega EQM | C47: Med. Física y Rehabilitación | D47: Bajo Costo | E47: Calentador Compresas | F47: HYDROCOLLATOR | G47: E2 | H47: T2043 | I47: 74173
A48: Medicina Fisica y Rehabilitación | B48: Camilla 2 | C48: Med. Física y Rehabilitación | D48: Bajo Costo | E48: Calentador Compresas con compresas | F48: RELIEF | G48: 111994 | H48: RP8M0389 | I48: 75111
A49: Atención Abierta | B49: Laboratorio Dental | C49: Odontología | D49: Bajo Costo | E49: Calentador de Cera | F49: GENERICO | G49: JT-15 | H49: S/S | I49: 76576
A50: Unidad Urgencias | B50: Sala Reanimación | C50: Apoyo Terapéutico | D50: Bajo Costo | E50: Calentador de fluidos | F50: QUALMEDI | G50: 120B | I50: 76770
A51: Unidad Urgencias | B51: Box Observación | C51: Apoyo Terapéutico | D51: Bajo Costo | E51: Calentador de Pacientes | F51: CALIMA | G51: CCALIMA22 | H51: 230302675 | I51: 75058
A52: Atención Cerrada Hospitalización | B52: Estación Enfermería | C52: Apoyo Terapéutico | D52: Bajo Costo | E52: Calentador de Pacientes | F52: CALIMA | G52: CCALIMA22 | H52: 230302673 | I52: 75056
A53: Atención Cerrada Hospitalización | B53: Estación Enfermería | C53: Apoyo Terapéutico | D53: Bajo Costo | E53: Calentador de Pacientes | F53: CALIMA | G53: CCALIMA22 | H53: 230302674 | I53: 75057
A54: Unidad Urgencia Pabellón Quirúrgico | B54: Estación Enfermería (Área Limpia) | C54: Apoyo Terapéutico | D54: Bajo Costo | E54: Calentador de Sueros | F54: QUALMEDI | G54: 120B | H54: S/S | I54: 76550
A55: Unidad Urgencia Pabellón Quirúrgico | B55: Sala Parto Integral | C55: Apoyo Terapéutico | D55: Alto Costo | E55: Cama de parto integral | F55: PARDO | G55: NEW BABYCHAIR | H55: 2269604 | I55: 76694
A56: Depósito de Cadáveres | B56: Morgue | C56: Apoyo Quirúrgico | D56: Alto Costo | E56: Cámara Mortuoria (capacidad 2 cadaveres) | F56: MATACHANA | G56: dos cuerpos lateral | H56: CLF24173 | I56: 75116
A57: Depósito de Cadáveres | B57: Sala de espera y entrega de Cadaveres | C57: Laboratorio/Farmacia | D57: Mediano Costo | E57: Camilla cadáver
A58: Medicina Fisica y Rehabilitación | B58: Camilla 1 | C58: Apoyo Terapéutico | D58: Bajo Costo | E58: Camilla de exámen | F58: SAIKANG | G58: X09-A | H58: X09240441021 | I58: 75244
A59: Medicina Fisica y Rehabilitación | B59: Camilla 2 | C59: Apoyo Terapéutico | D59: Bajo Costo | E59: Camilla de exámen | F59: SAIKANG | G59: X09-A | H59: X09240441043 | I59: 75245
A60: Medicina Fisica y Rehabilitación | B60: Sala de evaluación | C60: Apoyo Terapéutico | D60: Bajo Costo | E60: Camilla de exámen | F60: SAIKANG | G60: X09-A | H60: X09240441044 | I60: 75246
A61: Atención Abierta | B61: Box Procedimientos N°2 | C61: Apoyo Terapéutico | D61: Bajo Costo | E61: Camilla de Examen con barandas | F61: SAIKANG | G61: X09-02 | H61: X0924041013 | I61: 75231
A62: Atención Abierta | B62: Box Procedimientos N°2 | C62: Apoyo Terapéutico | D62: Bajo Costo | E62: Camilla de Examen con barandas | F62: SAIKANG | G62: X09-02 | H62: X0924041014 | I62: 75232
A63: Atención Abierta | B63: Box Multiproposito N°6 | C63: Apoyo Terapéutico | D63: Bajo Costo | E63: Camilla de Examen con barandas | F63: SAIKANG | G63: X09-02 | H63: X0924041012 | I63: 75230
A64: Atención Abierta | B64: Box Multipropósito Nº2 | C64: Apoyo Terapéutico | D64: Bajo Costo | E64: Camilla de Examen con barandas | F64: SAIKANG | G64: X09-02 | H64: X0924041003 | I64: 75221
A65: Atención Abierta | B65: Box Multipropósito Nº3 | C65: Apoyo Terapéutico | D65: Bajo Costo | E65: Camilla de Examen con barandas | F65: SAIKANG | G65: X09-02 | H65: X0924041004 | I65: 75222
A66: Atención Abierta | B66: Box Multipropósito Nº4 | C66: Apoyo Terapéutico | D66: Bajo Costo | E66: Camilla de Examen con barandas | F66: SAIKANG | G66: X09-02 | H66: X0924041005 | I66: 75223
A67: Atención Abierta | B67: Box Multipropósito Nº5 | C67: Apoyo Terapéutico | D67: Bajo Costo | E67: Camilla de Examen con barandas | F67: SAIKANG | G67: X09-02 | H67: X0924041006 | I67: 75224
A68: Atención Abierta | B68: Box Multipropósito N°8 | C68: Apoyo Terapéutico | D68: Bajo Costo | E68: Camilla de Examen con barandas | F68: SAIKANG | G68: X09-02 | H68: X0924041007 | I68: 75225
A69: Atención Abierta | B69: Box Rondas Médicas | C69: Apoyo Terapéutico | D69: Bajo Costo | E69: Camilla de Examen con barandas | F69: SAIKANG | G69: X09-02 | H69: X0924041008 | I69: 75226
... A92: Laboratorio | B92: Toma de Muestras | C92: Apoyo Terapéutico | D92: Bajo Costo | E92: Camilla Transporte Paciente | F92: SAIKANG | G92: Skb041 | H92: SKB041-324093016 | I92: 75243
A93: Medicina Fisica y Rehabilitación | B93: Area de Gimnasio infantil y adulto (actividades terapeuticas) | C93: Med. Física y Rehabilitación | D93: Mediano Costo | E93: Caminadora | F93: DYACO | G93: 7.0T | H93: 24070045 | I93: 76166
A94: Medicina Fisica y Rehabilitación | B94: Area de Gimnasio infantil y adulto (actividades terapeuticas) | C94: Med. Física y Rehabilitación | D94: Mediano Costo | E94: Caminadora | F94: DYACO | G94: 7.0T | H94: 24070046 | I94: 76167
A95: Hospital Antiguo | B95: Bodega EQM | C95: Apoyo Terapéutico | D95: Mediano Costo | E95: Cánula Nasal de Alto Flujo (CNAF) | F95: FISHER & PAYKEL | G95: AIRVO 2 | H95: 210323251456 | I95: 74190
A96: Depósito de Cadáveres | B96: Depósito de Cadáveres | C96: Apoyo Quirúrgico | D96: Mediano Costo | E96: Carro de Transporte Cadáveres | F96: MATACHANA | G96: REINAX | H96: S/S | I96: 75118
A97: Unidad Urgencias | B97: Box Atención Yeso | C97: Apoyo Terapéutico | D97: Mediano Costo | E97: Carro de Yeso | F97: MAGNÉTICA SHOP | G97: 50 CM x 100 CM x 90 CM acero inoxidable AISI304 | H97: S/S | I97: 76222
A98: Depósito de Cadáveres | B98: Depósito de Cadáveres | C98: Apoyo Quirúrgico | D98: Alto Costo | E98: Carro elevador cadaver | F98: MATACHANA | G98: para camas laterales | H98: ELE0224131 | I98: 75117
A99: Atención Cerrada Hospitalización | B99: Sala 1- 2 camas + Baño | C99: Apoyo Terapéutico | D99: Alto Costo | E99: Catre Clínico Eléctrico | F99: PARDO | G99: Advantcare | H99: 1636913 | I99: 75235
A100: Atención Cerrada Hospitalización | B100: Sala 2- 2 camas + Baño | C100: Apoyo Terapéutico | D100: Alto Costo | E100: Catre Clínico Eléctrico | F100: PARDO | G100: Advantcare | H100: 1636919 | I100: 75237
A101: Atención Cerrada Hospitalización | B101: Sala 2- 2 camas + Baño | C101: Apoyo Terapéutico | D101: Alto Costo | E101: Catre Clínico Eléctrico | F101: PARDO | G101: Advantcare | H101: 1636924 | I101: 75238
A102: Atención Cerrada Hospitalización | B102: Sala 3 -2 camas + Baño | C102: Apoyo Terapéutico | D102: Alto Costo | E102: Catre Clínico Eléctrico | F102: PARDO | G102: Advantcare | H102: 1636928 | I102: 75239
A103: Atención Cerrada Hospitalización | B103: Sala 3 -2 camas + Baño | C103: Apoyo Terapéutico | D103: Alto Costo | E103: Catre Clínico Eléctrico | F103: PARDO | G103: Advantcare | H103: 1636915 | I103: 75240
A104: Atención Cerrada Hospitalización | B104: Sala 4 - 1 camas + Baño | C104: Apoyo Terapéutico | D104: Alto Costo | E104: Catre Clínico Eléctrico | F104: PARDO | G104: Advantcare | H104: 1636914 | I104: 75236
A105: Atención Cerrada Hospitalización | B105: Sala 4- 1 cama + Baño | C105: Apoyo Terapéutico | D105: Alto Costo | E105: Catre Clínico Eléctrico | F105: PARDO | G105: Advantcare | H105: 1636909 | I105: 75234
A106: Laboratorio | B106: Entrega de Sangre (Unidad Medicina Transfusional) | C106: Laboratorio/Farmacia | D106: Mediano Costo | E106: Centrifuga de tarjeta de gel | F106: ALLSHENG | G106: TD2-12 | H106: AS-10030-00 | I106: 75065
A107: Laboratorio | B107: Hematología Química Clínica | C107: Laboratorio/Farmacia | D107: Mediano Costo | E107: Centrifuga hematológica | F107: EPPENDORF | G107: 5702 | H107: 5702MQ461214 | I107: 75186
A108: Laboratorio | B108: Bacteriología y Orina | C108: Laboratorio/Farmacia | D108: Mediano Costo | E108: Centrífuga Universal (4000-5000 RPM, 6 tubos, 15ml) | F108: EPPENDORF | G108: 5702 | H108: 5702MQ461230 | I108: 75184
A109: Laboratorio | B109: Hematología Química Clínica | C109: Laboratorio/Farmacia | D109: Mediano Costo | E109: Centrífuga Universal (4000-5000 RPM, 6 tubos, 15ml) | F109: EPPENDORF | G109: 5702 | H109: 5702MQ461229 | I109: 75185
A110: Atención Abierta | B110: Laboratorio Dental | C110: Odontología | D110: Bajo Costo | E110: Cortador de yeso | F110: ESSENCE | G110: 2482 | H110: RG2617 | I110: 76090
A111: Hospital Antiguo | B111: Bodega EQM | C111: Apoyo Terapéutico | D111: Alto Costo | E111: Cuna Cuidados Intensivos | F111: AIR SHIELD | G111: PM78-1E | H111: QG16607 | I111: 74179
A112: Atención Cerrada Hospitalización | B112: Bodega de Equipos | C112: Apoyo Terapéutico | D112: Bajo Costo | E112: Cuna Lactante | F112: SAIKANG | G112: X01-5 | H112: X01-523097001 | I112: 75101
A113: Atención Cerrada Hospitalización | B113: Fototerapia | C113: Apoyo Terapéutico | D113: Bajo Costo | E113: Cuna Lactante | F113: SAIKANG | G113: X01-5 | H113: X01-523076028 | I113: 75093
A114: Atención Cerrada Hospitalización | B114: Bodega de Equipos | C114: Apoyo Terapéutico | D114: Alto Costo | E114: Cuna procedimientos | F114: GENERAL ELECTRIC | G114: LULLABY WARMER | H114: SF824241015PA | I114: 75107
A115: Unidad Urgencia Pabellón Quirúrgico | B115: Sala de parto integral | C115: Apoyo Terapéutico | D115: Alto Costo | E115: Cuna Radiante Lactante | F115: NATALLY | G115: RW-610 | H115: 42826 | I115: 75109
A116: Administración Atención Abierta | B116: Espera 1 | C116: Monitoreo | D116: Alto Costo | E116: DEA | F116: PHILIPS | G116: HEARTSTART FRX | H116: B23L-01968 | I116: 75154
A117: Atención Abierta | B117: Espera 7AA | C117: Monitoreo | D117: Alto Costo | E117: DEA | F117: PHILIPS | G117: HEARTSTART FRX | H117: B24L-02747 | I117: 75155
A118: Hospital Antiguo | B118: Bodega EQM | C118: Monitoreo | D118: Alto Costo | E118: DEA | F118: ZOLL | G118: AED + PLUS | H118: X12J571461
A119: Hospital Antiguo | B119: Bodega EQM | C119: Monitoreo | D119: Alto Costo | E119: DEA | F119: ZOLL | G119: AED + PLUS | H119: (21)191202948 | I119: 74134
A120: Hospital Antiguo | B120: Bodega EQM | C120: Monitoreo | D120: Alto Costo | E120: DEA | F120: ZOLL | G120: AED PLUS | H120: (21)X15D754532 | I120: 74135
A121: Hospital Antiguo | B121: Bodega EQM | C121: Apoyo Diagnóstico | D121: Bajo Costo | E121: Detector de latidos cardiofetal | F121: SONOTRAX | G121: ULTRASONIC POCKET | H121: STAB07717736A
A122: Hospital Antiguo | B122: Bodega EQM | C122: Apoyo Diagnóstico | D122: Bajo Costo | E122: Detector de latidos cardiofetal | F122: JUMPER | G122: JPD-100E | H122: 20221220 | I122: 74205
...

Sheet SEGUIMIENTO GASTO
B3: SEGUIMIENTO GASTO CONVENIOS DE MANTENIMIENTO
K5: CONTROL MENSUAL EJECUCIÓN
K6: ENERO | M6: FEBRERO | O6: MARZO | Q6: ABRIL | S6: MAYO | U6: JUNIO | W6: JULIO | Y6: AGOSTO | AA6: SEPTIEMBRE | AC6: OCTUBRE | AE6: NOVIEMBRE | AG6: DICIEMBRE
B7: Nº | C7: SERVICIO DE SALUD | D7: ESTABLECIMIENTO | E7: NOMBRE CONVENIO DE MANTENIMIENTO | F7: Nº RESOLUCIÓN / ID / ORDEN DE COMPRA DEL CONVENIO | G7: FECHA RESOLUCIÓN | H7: FECHA DE EXPIRACION CONVENIO | I7: MONTO ANUAL ($) | J7: SUBASIGNACIÓN SIGFE | K7: N° ORDEN DE COMPRA / N° FACTURA | L7: MONTO ($) | M7: N° ORDEN DE COMPRA / N° FACTURA | N7: MONTO ($) | O7: N° ORDEN DE COMPRA / N° FACTURA | P7: MONTO ($) | Q7: N° ORDEN DE COMPRA / N° FACTURA | R7: MONTO ($) | S7: N° ORDEN DE COMPRA / N° FACTURA | T7: MONTO ($) | U7: N° ORDEN DE COMPRA / N° FACTURA | V7: MONTO ($) | W7: N° ORDEN DE COMPRA / N° FACTURA | X7: MONTO ($) | Y7: N° ORDEN DE COMPRA / N° FACTURA | Z7: MONTO ($) | AA7: N° ORDEN DE COMPRA / N° FACTURA | AB7: MONTO ($) | AC7: N° ORDEN DE COMPRA / N° FACTURA | AD7: MONTO ($) | AE7: N° ORDEN DE COMPRA / N° FACTURA | AF7: MONTO ($) | AG7: N° ORDEN DE COMPRA / N° FACTURA | AH7: MONTO ($) | AI7: TOTAL
AI8: =L8+N8+P8+R8+T8+V8+X8+Z8+AB8+AD8+AF8+AH8 -> 0
AI9: =L9+N9+P9+R9+T9+V9+X9+Z9+AB9+AD9+AF9+AH9 -> 0
AI10: =L10+N10+P10+R10+T10+V10+X10+Z10+AB10+AD10+AF10+AH10 -> 0
AI11: =L11+N11+P11+R11+T11+V11+X11+Z11+AB11+AD11+AF11+AH11 -> 0
AI12: =L12+N12+P12+R12+T12+V12+X12+Z12+AB12+AD12+AF12+AH12 -> 0
AI13: =L13+N13+P13+R13+T13+V13+X13+Z13+AB13+AD13+AF13+AH13 -> 0
I14: =SUM(I8:I13) -> 0
B16: SEGUIMIENTO GASTO MANTENIMIENTO CORRECTIVO / ADQUISICIÓN DE REPUESTOS / ADQUISICIÓN DE INSUMOS / ADQUISICIÓN DE ACCESORIOS
I18: CONTROL MENSUAL EJECUCIÓN
I19: ENERO | K19: FEBRERO | M19: MARZO | O19: ABRIL | Q19: MAYO | S19: JUNIO | U19: JULIO | W19: AGOSTO | Y19: SEPTIEMBRE | AA19: OCTUBRE | AC19: NOVIEMBRE | AE19: DICIEMBRE
B20: Nº | C20: SERVICIO DE SALUD | D20: ESTABLECIMIENTO | E20: DESCRIPCIÓN DE LA COMPRA | F20: TIPO DE GASTO CORRECTIVO | G20: MONTO | H20: SUBASIGNACIÓN SIGFE | I20: N° ORDEN DE COMPRA | J20: MONTO ($) | K20: N° ORDEN DE COMPRA | L20: MONTO ($) | M20: N° ORDEN DE COMPRA | N20: MONTO ($) | O20: N° ORDEN DE COMPRA | P20: MONTO ($) | Q20: N° ORDEN DE COMPRA | R20: MONTO ($) | S20: N° ORDEN DE COMPRA | T20: MONTO ($) | U20: N° ORDEN DE COMPRA | V20: MONTO ($) | W20: N° ORDEN DE COMPRA | X20: MONTO ($) | Y20: N° ORDEN DE COMPRA | Z20: MONTO ($) | AA20: N° ORDEN DE COMPRA | AB20: MONTO ($) | AC20: N° ORDEN DE COMPRA | AD20: MONTO ($) | AE20: N° ORDEN DE COMPRA | AF20: MONTO ($) | AG20: TOTAL
AG21: =+J21+L21+N21+P21+R21+T21+V21+X21+Z21+AB21+AD21+AF21 -> 0
AG22: =+J22+L22+N22+P22+R22+T22+V22+X22+Z22+AB22+AD22+AF22 -> 0
AG23: =+J23+L23+N23+P23+R23+T23+V23+X23+Z23+AB23+AD23+AF23 -> 0
AG24: =+J24+L24+N24+P24+R24+T24+V24+X24+Z24+AB24+AD24+AF24 -> 0
AG25: =+J25+L25+N25+P25+R25+T25+V25+X25+Z25+AB25+AD25+AF25 -> 0
AG26: =+J26+L26+N26+P26+R26+T26+V26+X26+Z26+AB26+AD26+AF26 -> 0

Sheet Detalle2
A1: Detalles para Suma de FRECUENCIA ANUAL DE MANTENIMIENTO - CRÍTICO/ RELEVANTE / IM≥12 / NO APLICA: CRÍTICO
A3: SERVICIO CLÍNICO | B3: RECINTO | C3: CLASE | D3: SUBCLASE | E3: NOMBRE EQUIPO | F3: MARCA | G3: MODELO | H3: SERIE | I3: N° INVENTARIO | J3: AÑO DE ADQUISICIÓN | K3: VIDA ÚTIL | L3: VIDA ÚTIL RESIDUAL | M3: PROPIO / ARRIENDO / COMODATO | N3: ESTADO (BUENO / REGULAR / MALO / BAJA) | O3: CRÍTICO/ RELEVANTE / IM≥12 / NO APLICA | P3: EN GARANTÍA (SI / NO) | Q3: AÑO VENCIMIENTO GARANTÍA | R3: BAJO PLAN DE MANTENIMIENTO (SI / NO) | S3: AÑO INGRESO A PLAN DE MANTENIMIENTO (2023 / 2024 / 2025 / 2026) | T3: MANTENIMIENTO INTERNO O MANTENIMIENTO EXTERNO O CONTRATO | U3: NOMBRE DE PROVEEDOR O MANTENIMIENTO INTERNO | V3: ID CONVENIO DE MANTENIMIENTO / ID DE REFERENCIA / COTIZACIÓN DE REFERENCIA | W3: COSTO ANUAL DE MANTENIMIENTO SEGÚN CONVENIO / PRECIO DE REFERENCIA MANTENIMIENTO ANUAL | X3: FRECUENCIA ANUAL DE MANTENIMIENTO | Y3: ENERO | Z3: FEBRERO | AA3: MARZO | AB3: ABRIL | AC3: MAYO | AD3: JUNIO | AE3: JULIO | AF3: AGOSTO | AG3: SEPTIEMBRE | AH3: OCTUBRE | AI3: NOVIEMBRE | AJ3: DICIEMBRE
A4: Pabellón | B4: Hospital Penco Lirquen | C4: Monitoreo | D4: Mediano Costo | E4: Monitor ECG Baja Complejidad | F4: Philips | G4: Efficia CM100 | H4: CN12099172 | J4: 2023 | K4: 8 | L4: 7 | M4: Propio | N4: Bueno | O4: CRÍTICO | P4: SI | Q4: 45627 | R4: SI | S4: 2024 | T4: EXTERNO | U4: Andover | V4: COLDAS | X4: 1 | AJ4: X
A5: Especialidades cuidados paliativos | B5: Hospital Penco Lirquen | C5: Apoyo Terapéutico | E5: Monitor Signos Vitales | F5: Nothern Meditec Limited | G5: Aquarius | H5: JHC01B508004 | J5: 2024 | K5: 8 | L5: 8 | M5: Propio | N5: Bueno | O5: CRÍTICO | P5: SI | Q5: 46174 | R5: SI | S5: 2024 | T5: EXTERNO | U5: BALDER | V5: 1057931-4-LE24 | X5: 1 | AI5: X
A6: Ambulancia - 7B | B6: Hospital Penco Lirquen | C6: Monitoreo | D6: Mediano Costo | E6: Monitor ECG Baja Complejidad | F6: Nihon Kohden | G6: SVM-7260 | H6: 00292 | I6: HPL30123 | J6: 2020 | K6: 8 | L6: 4 | M6: Propio | N6: Bueno | O6: CRÍTICO | P6: NO | Q6: NO APLICA | R6: SI | S6: 2023 | T6: INTERNO | U6: TECNICO EQM HPL | V6: NO APLICA | X6: 2 | AC6: √ | AI6: X
A7: Ambulancia - 7B | B7: Hospital Penco Lirquen | C7: Monitoreo | D7: Mediano Costo | E7: Monitor ECG Baja Complejidad | F7: Mindray | G7: uMEC10 | H7: KN-03065493 | I7: HPL30261 | J7: 2020 | K7: 8 | L7: 4 | M7: Propio | N7: Bueno | O7: CRÍTICO | P7: NO | Q7: NO APLICA | R7: SI | S7: 2023 | T7: INTERNO | U7: TECNICO EQM HPL | V7: NO APLICA | X7: 2 | AC7: ꓣ | AD7: √ | AI7: X
A8: UTI - 9D | B8: Hospital Penco Lirquen | C8: Apoyo Terapéutico | D8: Alto Costo | E8: Ventilador mecánico no Invasivo | F8: Philips | G8: Trilogy 202 | H8: TV016091214 | I8: HPL24776 | J8: 2016 | K8: 8 | L8: 0 | M8: Propio | N8: Bueno | O8: CRÍTICO | P8: NO | R8: SI | S8: 2023 | T8: EXTERNO | U8: TDM | V8: 1057540-101-LE23 | W8: 2427846 | X8: 2 | AD8: √ | AJ8: X
A9: UTI - 9D | B9: Hospital Penco Lirquen | C9: Apoyo Terapéutico | D9: Alto Costo | E9: Ventilador mecánico no Invasivo | F9: Philips | G9: Trilogy 202 | H9: TV016091211 | I9: HPL24850 | J9: 2016 | K9: 8 | L9: 0 | M9: Propio | N9: Bueno | O9: CRÍTICO | P9: NO | R9: SI | S9: 2023 | T9: EXTERNO | U9: TDM | V9: 1057540-101-LE23 | W9: 2427846 | X9: 2 | AD9: √ | AJ9: X
A10: UTI - 1B | B10: Hospital Penco Lirquen | C10: Apoyo Terapéutico | D10: Alto Costo | E10: Ventilador mecánico Invasivo | F10: Philips | G10: Trilogy 100 | H10: TV11909271B | I10: HPL30385 | J10: 2020 | K10: 8 | L10: 4 | M10: Préstamo | N10: Bueno | O10: CRÍTICO | P10: NO | Q10: NO APLICA | R10: SI | S10: 2023 | T10: EXTERNO | U10: TDM | V10: 1057540-101-LE23 | W10: 2499246 | X10: 2 | AD10: √ | AJ10: X
A11: UTI - 1B | B11: Hospital Penco Lirquen | C11: Apoyo Terapéutico | D11: Alto Costo | E11: Ventilador mecánico Invasivo | F11: MECKics | G11: MV2000-EVO 5 | H11: MV2000UA1C0551 | I11: HPL30273 | J11: 2021 | K11: 8 | L11: 5 | M11: Préstamo | N11: Bueno | O11: CRÍTICO | P11: NO | Q11: NO APLICA | R11: SI | S11: 2023 | T11: EXTERNO | U11: TDM | V11: 1057540-101-LE23 | W11: 2499246 | X11: 2 | AD11: √ | AJ11: X
A12: UTI | B12: Hospital Penco Lirquen | C12: Monitoreo | D12: Alto Costo | E12: Monitor ECG transporte alta complejidad (pequeño adosado a 03740) | F12: Nihon Kohden | G12: BSM-1763K | H12: 8528 | J12: 2021 | K12: 8 | L12: 5 | M12: Préstamo | N12: Bueno | O12: CRÍTICO | P12: NO | Q12: NO APLICA | R12: SI | S12: 2023 | T12: INTERNO | U12: TECNICO EQM HPL | V12: NO APLICA | X12: 2 | AC12: √ | AI12: X
A13: UTI | B13: Hospital Penco Lirquen | C13: Monitoreo | D13: Alto Costo | E13: Monitor ECG transporte alta complejidad (pequeño adosado a 03740) | F13: Nihon Kohden | G13: BSM-1763K | H13: 08699 | I13: HPL30134 | J13: 2021 | K13: 8 | L13: 5 | M13: Préstamo | N13: Bueno | O13: CRÍTICO | P13: NO | Q13: NO APLICA | R13: SI | S13: 2023 | T13: INTERNO | U13: TECNICO EQM HPL | V13: NO APLICA | X13: 2 | AC13: √ | AI13: X
A14: UTI | B14: Hospital Penco Lirquen | C14: Monitoreo | D14: Alto Costo | E14: Monitor ECG transporte alta complejidad (pequeño adosado a 03740) | F14: Nihon Kohden | G14: BSM-1763K | H14: 08697 | I14: HPL30133 | J14: 2021 | K14: 8 | L14: 5 | M14: Préstamo | N14: Bueno | O14: CRÍTICO | P14: NO | Q14: NO APLICA | R14: SI | S14: 2023 | T14: INTERNO | U14: TECNICO EQM HPL | V14: NO APLICA | X14: 2 | AC14: √ | AI14: X
A15: UTI | B15: Hospital Penco Lirquen | C15: Monitoreo | D15: Alto Costo | E15: Monitor ECG transporte alta complejidad (pequeño adosado a 03740) | F15: Nihon Kohden | G15: BSM-1763K | H15: 08694 | I15: HPL30132 | J15: 2021 | K15: 8 | L15: 5 | M15: Préstamo | N15: Bueno | O15: CRÍTICO | P15: NO | Q15: NO APLICA | R15: SI | S15: 2023 | T15: INTERNO | U15: TECNICO EQM HPL | V15: NO APLICA | X15: 2 | AC15: √ | AI15: X
A16: UTI | B16: Hospital Penco Lirquen | C16: Monitoreo | D16: Alto Costo | E16: Monitor ECG alta complejidad | F16: Nihon Kohden | G16: CSM-1502 | H16: 03740 | I16: HPL30129 | J16: 2021 | K16: 8 | L16: 5 | M16: Préstamo | N16: Bueno | O16: CRÍTICO | P16: NO | Q16: NO APLICA | R16: SI | S16: 2023 | T16: INTERNO | U16: TECNICO EQM HPL | V16: NO APLICA | X16: 2 | AC16: √ | AI16: X
A17: UTI | B17: Hospital Penco Lirquen | C17: Monitoreo | D17: Alto Costo | E17: Monitor ECG alta complejidad | F17: Nihon Kohden | G17: CSM-1502 | H17: 03739 | I17: HPL30128 | J17: 2021 | K17: 8 | L17: 5 | M17: Propio | N17: Bueno | O17: CRÍTICO | P17: NO | Q17: NO APLICA | R17: SI | S17: 2023 | T17: INTERNO | U17: TECNICO EQM HPL | V17: NO APLICA | X17: 2 | AC17: √ | AI17: X
A18: UTI | B18: Hospital Penco Lirquen | C18: Monitoreo | D18: Alto Costo | E18: Monitor ECG alta complejidad | F18: Nihon Kohden | G18: CSM-1502 | H18: 03726 | I18: HPL30127 | J18: 2021 | K18: 8 | L18: 5 | M18: Préstamo | N18: Bueno | O18: CRÍTICO | P18: NO | Q18: NO APLICA | R18: SI | S18: 2023 | T18: INTERNO | U18: TECNICO EQM HPL | V18: NO APLICA | X18: 2 | AC18: √ | AI18: X
A19: UTI | B19: Hospital Penco Lirquen | C19: Monitoreo | D19: Alto Costo | E19: Monitor ECG alta complejidad | F19: Nihon Kohden | G19: CSM-1502 | H19: 03723 | I19: HPL30126 | J19: 2021 | K19: 8 | L19: 5 | M19: Propio | N19: Bueno | O19: CRÍTICO | P19: NO | Q19: NO APLICA | R19: SI | S19: 2023 | T19: INTERNO | U19: TECNICO EQM HPL | V19: NO APLICA | X19: 2 | AC19: √ | AI19: X
A20: UTI | B20: Hospital Penco Lirquen | C20: Monitoreo | D20: Alto Costo | E20: Monitor ECG alta complejidad | F20: Nihon Kohden | G20: CSM-1502 | H20: 03717 | I20: HPL30125 | J20: 2021 | K20: 8 | L20: 5 | M20: Préstamo | N20: Bueno | O20: CRÍTICO | P20: NO | Q20: NO APLICA | R20: SI | S20: 2023 | T20: INTERNO | U20: TECNICO EQM HPL | V20: NO APLICA | X20: 2 | AC20: √ | AI20: X
A21: UTI | B21: Hospital Penco Lirquen | C21: Monitoreo | D21: Alto Costo | E21: Monitor ECG alta complejidad | F21: Nihon Kohden | G21: CSM-1502 | H21: 03714 | I21: HPL30124 | J21: 2021 | K21: 8 | L21: 5 | M21: Préstamo | N21: Bueno | O21: CRÍTICO | P21: NO | Q21: NO APLICA | R21: SI | S21: 2023 | T21: INTERNO | U21: TECNICO EQM HPL | V21: NO APLICA | X21: 2 | AC21: √ | AI21: X
A22: UTI | B22: Hospital Penco Lirquen | C22: Monitoreo | D22: Alto Costo | E22: Monitor ECG transporte mediana complejidad (pequeño adosado a 03740) | F22: Nihon Kohden | G22: BSM-1763K | H22: 6678 | I22: HPL29879 | J22: 2020 | K22: 8 | L22: 4 | M22: Propio | N22: Bueno | O22: CRÍTICO | P22: NO | Q22: NO APLICA | R22: SI | S22: 2023 | T22: INTERNO | U22: TECNICO EQM HPL | V22: NO APLICA | X22: 2 | AC22: √ | AI22: X
A23: UTI | B23: Hospital Penco Lirquen | C23: Monitoreo | D23: Mediano Costo | E23: Monitor desfibrilador | F23: Zoll medical | G23: Serie R ALS | H23: AF20F118297 | I23: HPL30215 | J23: 2020 | K23: 8 | L23: 4 | M23: Propio | N23: Bueno | O23: CRÍTICO | P23: NO | Q23: NO APLICA | R23: SI | S23: 2023 | T23: INTERNO | U23: TECNICO EQM HPL | V23: NO APLICA | W23: - | X23: 2 | AC23: √ | AI23: X
A24: UTI | B24: Hospital Penco Lirquen | C24: Apoyo Terapéutico | D24: Alto Costo | E24: Ventilador mecánico Invasivo | F24: MECKics | G24: MV2000-EVO 5 | H24: MV2000UA1C0549 | I24: HPL30272 | J24: 2021 | K24: 8 | L24: 5 | M24: Préstamo | N24: Bueno | O24: CRÍTICO | P24: NO | Q24: NO APLICA | R24: SI | S24: 2023 | T24: CONTRATO | U24: TDM | V24: 1057540-101-LE23 | W24: 2499246 | X24: 2 | AD24: √ | AJ24: X
A25: Urgencia - 1B | B25: Hospital Penco Lirquen | C25: Apoyo Terapéutico | D25: Alto Costo | E25: Ventilador mecánico invasivo de transporte | F25: Drager | G25: Oxylog 3000 plus | H25: ASNH-0102 | I25: HPL30220 | J25: 2020 | K25: 8 | L25: 4 | M25: Propio | N25: Bueno | O25: CRÍTICO | P25: NO | Q25: NO APLICA | R25: SI | S25: 2023 | T25: CONTRATO | U25: TDM | V25: 1057540-101-LE23 | W25: 2499246 | X25: 2 | AD25: √ | AJ25: X
A26: Urgencia | B26: Hospital Penco Lirquen | C26: Monitoreo | D26: Mediano Costo | E26: Desfibrilador externo automático (DEA) | F26: NIHON KOHDEN | G26: AED-3100 | H26: 30594 | J26: 2023 | K26: 8 | L26: 7 | M26: Propio | N26: BUENO | O26: CRÍTICO | P26: SI | Q26: 45984 | R26: SI | S26: 2024 | T26: INTERNO | U26: TECNICO EQM HPL | V26: COLDAS 2023 (BLUMEDICAL) | W26: 0 | X26: 2 | AB26: √ | AH26: X
A27: Urgencia | B27: Hospital Penco Lirquen | C27: Monitoreo | D27: Mediano Costo | E27: Desfibrilador externo automático (DEA) | F27: NIHON KOHDEN | G27: AED-3100 | H27: 30574 | J27: 2023 | K27: 8 | L27: 7 | M27: Propio | N27: BUENO | O27: CRÍTICO | P27: SI | Q27: 45984 | R27: SI | S27: 2024 | T27: INTERNO | U27: TECNICO EQM HPL | V27: COLDAS 2023 (BLUMEDICAL) | W27: 0 | X27: 2 | AB27: √ | AH27: X
A28: Urgencia | B28: Hospital Penco Lirquen | C28: Monitoreo | D28: Mediano Costo | E28: Desfibrilador externo automático (DEA) | F28: NIHON KOHDEN | G28: AED-3100 | H28: 30584 | J28: 2023 | K28: 8 | L28: 7 | M28: Propio | N28: BUENO | O28: CRÍTICO | P28: SI | Q28: 45984 | R28: SI | S28: 2024 | T28: INTERNO | U28: TECNICO EQM HPL | V28: COLDAS 2023 (BLUMEDICAL) | W28: 0 | X28: 2 | AB28: √ | AH28: X
A29: Urgencia | B29: Hospital Penco Lirquen | C29: Monitoreo | D29: Mediano Costo | E29: Desfibrilador externo automático (DEA) | F29: NIHON KOHDEN | G29: AED-3100 | H29: 30559 | J29: 2023 | K29: 8 | L29: 7 | M29: Propio | N29: BUENO | O29: CRÍTICO | P29: SI | Q29: 45984 | R29: SI | S29: 2024 | T29: INTERNO | U29: TECNICO EQM HPL | V29: COLDAS 2023 (BLUMEDICAL) | W29: 0 | X29: 2 | AB29: √ | AH29: X
A30: Urgencia | B30: Hospital Penco Lirquen | C30: Monitoreo | D30: Mediano Costo | E30: Desfibrilador externo automático (DEA) | F30: NIHON KOHDEN | G30: AED-3100 | H30: 30583 | J30: 2023 | K30: 8 | L30: 7 | M30: Propio | N30: BUENO | O30: CRÍTICO | P30: SI | Q30: 45984 | R30: SI | S30: 2024 | T30: INTERNO | U30: TECNICO EQM HPL | V30: COLDAS 2023 (BLUMEDICAL) | W30: 0 | X30: 2 | AB30: √ | AH30: X
A31: Urgencia | B31: Hospital Penco Lirquen | C31: Monitoreo | D31: Mediano Costo | E31: Monitor ECG Baja Complejidad | F31: General Electric | G31: B20 | H31: SGF15151303WA | I31: HPL30370 | J31: 2016 | K31: 8 | L31: 0 | M31: Propio | N31: Bueno | O31: CRÍTICO | P31: NO | Q31: NO APLICA | R31: SI | S31: 2023 | T31: INTERNO | U31: TECNICO EQM HPL | V31: NO APLICA | X31: 2 | AC31: √ | AI31: X
A32: Urgencia | B32: Hospital Penco Lirquen | C32: Monitoreo | D32: Mediano Costo | E32: Monitor ECG Baja Complejidad | F32: General Electric | G32: B20 | H32: SGF15131190WA | I32: HPL30369 | J32: 2015 | K32: 8 | L32: -1 | M32: Propio | N32: Bueno | O32: CRÍTICO | P32: NO | Q32: NO APLICA | R32: SI | S32: 2023 | T32: INTERNO | U32: TECNICO EQM HPL | V32: NO APLICA | X32: 2 | AC32: √ | AI32: X
A33: Bodega de Equipos Médicos | B33: Hospital Penco Lirquen | C33: Monitoreo | D33: Mediano Costo | E33: Desfibrilador externo automático (DEA) | F33: Philips | G33: Heart Start | H33: A19K-06543 | I33: HPL30200 | J33: 2020 | K33: 8 | L33: 4 | M33: Propio | N33: Bueno | O33: CRÍTICO | P33: NO | Q33: NO APLICA | R33: SI | S33: 2023 | T33: INTERNO | U33: TECNICO EQM HPL | V33: NO APLICA | X33: 2 | AC33: √ | AI33: X
A34: Urgencia | B34: Hospital Penco Lirquen | C34: Monitoreo | D34: Mediano Costo | E34: Monitor ECG Baja Complejidad | F34: Fukuda Denshi | G34: Dinascope DSL-8001 | H34: 50200469 | I34: HPL30044 | J34: 2016 | K34: 8 | L34: 0 | M34: Propio | N34: Bueno | O34: CRÍTICO | P34: NO | Q34: NO APLICA | R34: SI | S34: 2023 | T34: INTERNO | U34: TECNICO EQM HPL | V34: NO APLICA | X34: 2 | AC34: √ | AI34: X
A35: Urgencia | B35: Hospital Penco Lirquen | C35: Monitoreo | D35: Mediano Costo | E35: Monitor ECG Baja Complejidad | F35: Fukuda Denshi | G35: Dinascope DSL-8001 | H35: 50200457 | I35: HPL30039 | J35: 2016 | K35: 8 | L35: 0 | M35: Propio | N35: Bueno | O35: CRÍTICO | P35: NO | Q35: NO APLICA | R35: SI | S35: 2023 | T35: INTERNO | U35: TECNICO EQM HPL | V35: NO APLICA | X35: 2 | AC35: √ | AI35: X
A36: Urgencia | B36: Hospital Penco Lirquen | C36: Monitoreo | D36: Mediano Costo | E36: Monitor ECG Baja Complejidad | F36: Fukuda Denshi | G36: Dinascope DSL-8001 | H36: 50200455 | I36: HPL30037 | J36: 2016 | K36: 8 | L36: 0 | M36: Propio | N36: Bueno | O36: CRÍTICO | P36: NO | Q36: NO APLICA | R36: SI | S36: 2023 | T36: INTERNO | U36: TECNICO EQM HPL | V36: NO APLICA | X36: 2 | AC36: √ | AI36: X
A37: Urgencia | B37: Hospital Penco Lirquen | C37: Monitoreo | D37: Mediano Costo | E37: Monitor ECG Baja Complejidad | F37: Fukuda Denshi | G37: Dinascope DSL-8001 | H37: 50200452 | I37: HPL30035 | J37: 2016 | K37: 8 | L37: 0 | M37: Propio | N37: Bueno | O37: CRÍTICO | P37: NO | Q37: NO APLICA | R37: SI | S37: 2023 | T37: INTERNO | U37: TECNICO EQM HPL | V37: NO APLICA | X37: 2 | AC37: √ | AI37: X
A38: Urgencia | B38: Hospital Penco Lirquen | C38: Monitoreo | D38: Mediano Costo | E38: Monitor ECG Baja Complejidad | F38: Fukuda Denshi | G38: Dinascope DSL-8001 | H38: 50200451 | I38: HPL30034 | J38: 2016 | K38: 8 | L38: 0 | M38: Propio | N38: Bueno | O38: CRÍTICO | P38: NO | Q38: NO APLICA | R38: SI | S38: 2023 | T38: INTERNO | U38: TECNICO EQM HPL | V38: NO APLICA | X38: 2 | AC38: √ | AI38: X
A39: Corta Estadia | B39: Hospital Penco Lirquen | C39: Monitoreo | D39: Mediano Costo | E39: Monitor ECG Baja Complejidad | F39: Fukuda Denshi | G39: Dinascope DSL-8001 | H39: 50200450 | I39: HPL25510 | J39: 2016 | K39: 8 | L39: 0 | M39: Propio | N39: Bueno | O39: CRÍTICO | P39: NO | Q39: NO APLICA | R39: SI | S39: 2023 | T39: INTERNO | U39: TECNICO EQM HPL | V39: NO APLICA | X39: 2 | AD39: √ | AJ39: X
A40: Corta Estadia | B40: Hospital Penco Lirquen | C40: Monitoreo | D40: Mediano Costo | E40: Monitor ECG Baja Complejidad | F40: Fukuda Denshi | G40: Dinascope DSL-8001 | H40: 50200468 | I40: HPL21701 | J40: 2016 | K40: 8 | L40: 0 | M40: Propio | N40: Bueno | O40: CRÍTICO | P40: NO | Q40: NO APLICA | R40: SI | S40: 2023 | T40: INTERNO | U40: TECNICO EQM HPL | V40: NO APLICA | X40: 2 | AD40: √ | AJ40: X
A41: Corta Estadia | B41: Hospital Penco Lirquen | C41: Monitoreo | D41: Mediano Costo | E41: Desfibrilador externo automático (DEA) | F41: Philips | G41: Heart Start | H41: A19K-06055 | I41: HPL30198 | J41: 2020 | K41: 8 | L41: 4 | M41: Propio | N41: Bueno | O41: CRÍTICO | P41: NO | Q41: NO APLICA | R41: SI | S41: 2023 | T41: INTERNO | U41: TECNICO EQM HPL | V41: NO APLICA | X41: 2 | AD41: √ | AJ41: X
A42: Urgencia | B42: Hospital Penco Lirquen | C42: Monitoreo | D42: Mediano Costo | E42: Monitor ECG Baja Complejidad | F42: Fukuda Denshi | G42: Dinascope DSL-8001 | H42: 50200448 | I42: HPL30033 | J42: 2016 | K42: 8 | L42: 0 | M42: Propio | N42: Bueno | O42: CRÍTICO | P42: NO | Q42: NO APLICA | R42: SI | S42: 2023 | T42: INTERNO | U42: TECNICO EQM HPL | V42: NO APLICA | X42: 2 | AC42: √ | AI42: X
A43: Urgencia | B43: Hospital Penco Lirquen | C43: Monitoreo | D43: Mediano Costo | E43: Monitor ECG Baja Complejidad | F43: Fukuda Denshi | G43: Dinascope DSL-8001 | H43: 50200444 | I43: HPL30030 | J43: 2016 | K43: 8 | L43: 0 | M43: Propio | N43: Bueno | O43: CRÍTICO | P43: NO | Q43: NO APLICA | R43: SI | S43: 2023 | T43: INTERNO | U43: TECNICO EQM HPL | V43: NO APLICA | X43: 2 | AC43: √ | AI43: X
A44: Urgencia | B44: Hospital Penco Lirquen | C44: Monitoreo | D44: Mediano Costo | E44: Monitor ECG Baja Complejidad | F44: Fukuda Denshi | G44: Dinascope DSL-8001 | H44: 50200436 | I44: HPL30029 | J44: 2016 | K44: 8 | L44: 0 | M44: Propio | N44: Bueno | O44: CRÍTICO | P44: NO | Q44: NO APLICA | R44: SI | S44: 2023 | T44: INTERNO | U44: TECNICO EQM HPL | V44: NO APLICA | X44: 2 | AC44: √ | AI44: X
A45: Urgencia | B45: Hospital Penco Lirquen | C45: Monitoreo | D45: Mediano Costo | E45: Monitor ECG Baja Complejidad | F45: Nihon Kohden | G45: PVM-2701 | H45: 115438 | I45: HPL29917 | J45: 2016 | K45: 8 | L45: 0 | M45: Propio | N45: Bueno | O45: CRÍTICO | P45: NO | Q45: NO APLICA | R45: SI | S45: 2023 | T45: INTERNO | U45: TECNICO EQM HPL | V45: NO APLICA | X45: 2 | AC45: √ | AI45: X
A46: Urgencia | B46: Hospital Penco Lirquen | C46: Monitoreo | D46: Mediano Costo | E46: Monitor ECG Baja Complejidad | F46: Nihon Kohden | G46: PVM-2701 | H46: 115409 | I46: HPL29913 | J46: 2016 | K46: 8 | L46: 0 | M46: Propio | N46: Bueno | O46: CRÍTICO | P46: NO | Q46: NO APLICA | R46: SI | S46: 2023 | T46: INTERNO | U46: TECNICO EQM HPL | V46: NO APLICA | X46: 2 | AC46: √ | AI46: X
A47: Urgencia | B47: Hospital Penco Lirquen | C47: Monitoreo | D47: Mediano Costo | E47: Monitor ECG Baja Complejidad | F47: Nihon Kohden | G47: PVM-2701 | H47: 115373 | I47: HPL29911 | J47: 2016 | K47: 8 | L47: 0 | M47: Propio | N47: Bueno | O47: CRÍTICO | P47: NO | Q47: NO APLICA | R47: SI | S47: 2023 | T47: INTERNO | U47: TECNICO EQM HPL | V47: NO APLICA | X47: 2 | AC47: √ | AI47: X
A48: Urgencia | B48: Hospital Penco Lirquen | C48: Monitoreo | D48: Mediano Costo | E48: Monitor desfibrilador | F48: Zoll medical | G48: Serie R ALS | H48: AF15D045654 | I48: HPL30211 | J48: 2016 | K48: 8 | L48: 0 | M48: Propio | N48: Bueno | O48: CRÍTICO | P48: NO | Q48: NO APLICA | R48: SI | S48: 2023 | T48: INTERNO | U48: TECNICO EQM HPL | V48: NO APLICA | W48: - | X48: 2 | AC48: √ | AI48: X
A49: Urgencia | B49: Hospital Penco Lirquen | C49: Monitoreo | D49: Mediano Costo | E49: Monitor desfibrilador | F49: Zoll medical | G49: Serie R ALS | H49: AF15D045649 | I49: HPL30210 | J49: 2016 | K49: 8 | L49: 0 | M49: Propio | N49: Bueno | O49: CRÍTICO | P49: NO | Q49: NO APLICA | R49: SI | S49: 2023 | T49: INTERNO | U49: TECNICO EQM HPL | V49: NO APLICA | W49: - | X49: 2 | AC49: √ | AI49: X
A50: Urgencia | B50: Hospital Penco Lirquen | C50: Monitoreo | D50: Mediano Costo | E50: Desfibrilador externo automático (DEA) | F50: Philips | G50: Heart Start | H50: A19K-06534 | I50: HPL30199 | J50: 2020 | K50: 8 | L50: 4 | M50: Propio | N50: Bueno | O50: CRÍTICO | P50: NO | Q50: NO APLICA | R50: SI | S50: 2023 | T50: INTERNO | U50: TECNICO EQM HPL | V50: NO APLICA | X50: 2 | AC50: √ | AI50: X
A51: Urgencia | B51: Hospital Penco Lirquen | C51: Monitoreo | D51: Mediano Costo | E51: Desfibrilador externo automático (DEA) | F51: Zoll | G51: AED plus | H51: (21) X16K874144 | I51: HPL30119 | J51: 2017 | K51: 8 | L51: 1 | M51: Propio | N51: Bueno | O51: CRÍTICO | P51: NO | Q51: NO APLICA | R51: SI | S51: 2023 | T51: INTERNO | U51: TECNICO EQM HPL | V51: NO APLICA | X51: 2 | AC51: √ | AI51: X
A52: Urgencia | B52: Hospital Penco Lirquen | C52: Monitoreo | D52: Mediano Costo | E52: Monitor de signos vitales | F52: General Electric | G52: V100 | H52: SH622300047SA | I52: HPL31307 | J52: 2022 | K52: 8 | L52: 6 | M52: Propio | N52: Bueno | O52: CRÍTICO | P52: SI | Q52: 45627 | R52: SI | S52: 2024 | T52: EXTERNO | U52: PV EQUIP | V52: COLDAS | X52: 2 | AD52: √ | AJ52: X
A53: Urgencia | B53: Hospital Penco Lirquen | C53: Monitoreo | D53: Mediano Costo | E53: Monitor de signos vitales | F53: General Electric | G53: V100 | H53: SH622330003SA | I53: HPL31306 | J53: 2022 | K53: 8 | L53: 6 | M53: Propio | N53: Bueno | O53: CRÍTICO | P53: SI | Q53: 45627 | R53: SI | S53: 2024 | T53: EXTERNO | U53: PV EQUIP | V53: COLDAS | X53: 2 | AD53: √ | AJ53: X
A54: Urgencia | B54: Hospital Penco Lirquen | C54: Monitoreo | D54: Mediano Costo | E54: Monitor de signos vitales | F54: General Electric | G54: V100 | H54: SH622300072SA | I54: HPL31305 | J54: 2022 | K54: 8 | L54: 6 | M54: Propio | N54: Bueno | O54: CRÍTICO | P54: SI | Q54: 45627 | R54: SI | S54: 2024 | T54: EXTERNO | U54: PV EQUIP | V54: COLDAS | X54: 2 | AD54: √ | AJ54: X
A55: Urgencia | B55: Hospital Penco Lirquen | C55: Monitoreo | D55: Mediano Costo | E55: Monitor de signos vitales | F55: General Electric | G55: V100 | H55: SH622300059SA | I55: HPL31304 | J55: 2022 | K55: 8 | L55: 6 | M55: Propio | N55: Bueno | O55: CRÍTICO | P55: SI | Q55: 45627 | R55: SI | S55: 2024 | T55: EXTERNO | U55: PV EQUIP | V55: COLDAS | X55: 2 | AD55: √ | AJ55: X
A56: Urgencia | B56: Hospital Penco Lirquen | C56: Monitoreo | D56: Mediano Costo | E56: Desfibrilador externo automático (DEA) | F56: Philips | G56: Heart Start | H56: A15G-08197 | I56: HPL30196 | J56: 2015 | K56: 8 | L56: -1 | M56: Propio | N56: Bueno | O56: CRÍTICO | P56: NO | Q56: NO APLICA | R56: SI | S56: 2023 | T56: INTERNO | U56: TECNICO EQM HPL | V56: NO APLICA | X56: 2 | AD56: √ | AJ56: X
A57: Urgencia | B57: Hospital Penco Lirquen | C57: Monitoreo | D57: Mediano Costo | E57: Monitor de signos vitales | F57: Mindray | G57: DPM3 | H57: DQ-18000401 | I57: HPL30239 | J57: 2015 | K57: 8 | L57: -1 | M57: Propio | N57: Bueno | O57: CRÍTICO | P57: NO | Q57: NO APLICA | R57: SI | S57: 2023 | T57: INTERNO | U57: TECNICO EQM HPL | V57: NO APLICA | X57: 2 | AC57: √ | AI57: X
A58: Urgencia | B58: Hospital Penco Lirquen | C58: Monitoreo | D58: Mediano Costo | E58: Desfibrilador externo automático (DEA) | F58: Mindray | G58: BeneHeart C2 | H58: AE7-01001130 | I58: HPL30209 | J58: 2020 | K58: 8 | L58: 4 | M58: Propio | N58: Bueno | O58: CRÍTICO | P58: NO | Q58: NO APLICA | R58: SI | S58: 2023 | T58: INTERNO | U58: TECNICO EQM HPL | V58: NO APLICA | X58: 2 | AC58: √ | AI58: X
A59: Salud del personal | B59: Hospital Penco Lirquen | C59: Monitoreo | D59: Mediano Costo | E59: Monitor de signos vitales | F59: Edan | G59: M3A | H59: 302019-M14505610013 | I59: HPL11939 | J59: 2017 | K59: 8 | L59: 1 | M59: Propio | N59: Bueno | O59: CRÍTICO | P59: NO | Q59: NO APLICA | R59: SI | S59: 2023 | T59: INTERNO | U59: TECNICO EQM HPL | V59: NO APLICA | X59: 2 | AD59: √ | AJ59: X
A60: Rehabilitacion Integral | B60: Hospital Penco Lirquen | C60: Monitoreo | D60: Mediano Costo | E60: Monitor ECG Baja Complejidad | F60: Fukuda Denshi | G60: Dinascope DSL-8001 | H60: 50200458 | I60: HPL30040 | J60: 2016 | K60: 8 | L60: 0 | M60: Propio | N60: Bueno | O60: CRÍTICO | P60: NO | Q60: NO APLICA | R60: SI | S60: 2023 | T60: INTERNO | U60: TECNICO EQM HPL | V60: NO APLICA | X60: 2 | AD60: √ | AJ60: X
A61: Parto Integral - 2 | B61: Hospital Penco Lirquen | C61: Apoyo Terapéutico | D61: Alto Costo | E61: Incubadora de transporte | F61: Drager | G61: TI 500 | H61: EF10863 | I61: HPL30240 | J61: 2016 | K61: 8 | L61: 0 | M61: Propio | N61: Bueno | O61: CRÍTICO | P61: NO | Q61: NO APLICA | R61: SI | S61: 2023 | T61: EXTERNO | U61: CODESUR | V61: 1057540-110-LE23 | W61: 300000 | X61: 2 | AB61: √ | AH61: X
A62: Parto Integral | B62: Hospital Penco Lirquen | C62: Monitoreo | D62: Mediano Costo | E62: Monitor de signos vitales | F62: Creative medical | G62: PC-900 | H62: J0100JL01720 | I62: HPL30259 | J62: 2014 | K62: 8 | L62: -2 | M62: Propio | N62: Bueno | O62: CRÍTICO | P62: NO | Q62: NO APLICA | R62: SI | S62: 2023 | T62: INTERNO | U62: TECNICO EQM HPL | V62: NO APLICA | X62: 2 | AD62: √ | AJ62: X
A63: Parto Integral | B63: Hospital Penco Lirquen | C63: Monitoreo | D63: Mediano Costo | E63: Monitor desfibrilador | F63: Zoll medical | G63: Serie R ALS | H63: AF15D045660 | I63: HPL30213 | J63: 2016 | K63: 8 | L63: 0 | M63: Propio | N63: Bueno | O63: CRÍTICO | P63: NO | Q63: NO APLICA | R63: SI | S63: 2023 | T63: INTERNO | U63: TECNICO EQM HPL | V63: NO APLICA | W63: - | X63: 2 | AD63: √ | AJ63: X
A64: Parto Integral | B64: Hospital Penco Lirquen | C64: Monitoreo | D64: Mediano Costo | E64: Monitor ECG Baja Complejidad | F64: Fukuda Denshi | G64: Dinascope DSL-8001 | H64: 50200461 | I64: HPL30042 | J64: 2016 | K64: 8 | L64: 0 | M64: Propio | N64: Bueno | O64: CRÍTICO | P64: NO | Q64: NO APLICA | R64: SI | S64: 2023 | T64: INTERNO | U64: TECNICO EQM HPL | V64: NO APLICA | X64: 2 | AD64: √ | AJ64: X
A65: Pabellón CMA - 3B | B65: Hospital Penco Lirquen | C65: Apoyo Quirúrgico | D65: Alto Costo | E65: Máquina de Anestesia | F65: Drager | G65: Fabius GS Premium 8607000 | H65: ASFN-0031 | I65: HPL30217 | J65: 2015 | K65: 8 | L65: -1 | M65: Propio | N65: Bueno | O65: CRÍTICO | P65: NO | Q65: NO APLICA | R65: SI | S65: 2023 | T65: EXTERNO | U65: Drager | V65: 1057540-40-LP22 | X65: 2 | AB65: √ | AH65: X
A66: Pabellón 2 - 3B | B66: Hospital Penco Lirquen | C66: Apoyo Quirúrgico | D66: Alto Costo | E66: Máquina de Anestesia | F66: Drager | G66: Fabius GS Premium 8607000 | H66: ASHJ-0206 | I66: HPL30219 | J66: 2016 | K66: 8 | L66: 0 | M66: Propio | N66: Bueno | O66: CRÍTICO | P66: NO | Q66: NO APLICA | R66: SI | S66: 2023 | T66: EXTERNO | U66: Drager | V66: 1057540-40-LP22 | X66: 2 | AB66: √ | AH66: X
A67: Pabellón 1 - 3B | B67: Hospital Penco Lirquen | C67: Apoyo Quirúrgico | D67: Alto Costo | E67: Máquina de Anestesia | F67: Drager | G67: Fabius GS Premium 8607000 | H67: ASHJ-0205 | I67: HPL30218 | J67: 2016 | K67: 8 | L67: 0 | M67: Propio | N67: Bueno | O67: CRÍTICO | P67: NO | Q67: NO APLICA | R67: SI | S67: 2023 | T67: EXTERNO | U67: Drager | V67: 1057540-40-LP22 | X67: 2 | AB67: √ | AH67: X
A68: Pabellón - 3A | B68: Hospital Penco Lirquen | C68: Apoyo Terapéutico | D68: Mediano Costo | E68: Incubadora | F68: Medix | G68: TR200 | H68: 1078 | I68: HPL29859 | J68: 2015 | K68: 8 | L68: -1 | M68: Propio | N68: Bueno | O68: CRÍTICO | P68: NO | Q68: NO APLICA | R68: SI | S68: 2023 | T68: EXTERNO | U68: CODESUR | V68: 1057540-110-LE23 | W68: 300000 | X68: 2 | AB68: √ | AH68: X
A69: Pabellón | B69: Hospital Penco Lirquen | C69: Monitoreo | D69: Mediano Costo | E69: Monitor ECG Baja Complejidad | F69: General Electric | G69: B20 | H69: SGF15131188WA | I69: HPL30368 | J69: 2015 | K69: 8 | L69: -1 | M69: Propio | N69: Bueno | O69: CRÍTICO | P69: NO | Q69: NO APLICA | R69: SI | S69: 2023 | T69: INTERNO | U69: TECNICO EQM HPL | V69: NO APLICA | X69: 2 | AB69: √ | AH69: X
A70: Pabellón | B70: Hospital Penco Lirquen | C70: Monitoreo | D70: Mediano Costo | E70: Monitor ECG Baja Complejidad | F70: Fukuda Denshi | G70: Dinascope DSL-8001 | H70: 50200447 | I70: HPL30032 | J70: 2016 | K70: 8 | L70: 0 | M70: Propio | N70: Bueno | O70: CRÍTICO | P70: NO | Q70: NO APLICA | R70: SI | S70: 2023 | T70: INTERNO | U70: TECNICO EQM HPL | V70: NO APLICA | X70: 2 | AB70: √ | AH70: X
A71: Equipos Médicos | B71: Hospital Penco Lirquen | C71: Monitoreo | D71: Mediano Costo | E71: Monitor de signos vitales | F71: Indura | G71: Lifecare 740 | H71: 1022045 | I71: HPL29945 | J71: 2015 | K71: 8 | L71: -1 | M71: Propio | N71: Bueno | O71: CRÍTICO | P71: NO | Q71: NO APLICA | R71: SI | S71: 2023 | T71: INTERNO | U71: TECNICO EQM HPL | V71: NO APLICA | X71: 2 | AB71: √ | AH71: X
A72: Pabellón | B72: Hospital Penco Lirquen | C72: Monitoreo | D72: Mediano Costo | E72: Monitor ECG Baja Complejidad | F72: Nihon Kohden | G72: PVM-2701 | H72: 115467 | I72: HPL29918 | J72: 2016 | K72: 8 | L72: 0 | M72: Propio | N72: Bueno | O72: CRÍTICO | P72: NO | Q72: NO APLICA | R72: SI | S72: 2023 | T72: INTERNO | U72: TECNICO EQM HPL | V72: NO APLICA | X72: 2 | AB72: √ | AH72: X
A73: Pabellón | B73: Hospital Penco Lirquen | C73: Monitoreo | D73: Mediano Costo | E73: Monitor ECG Baja Complejidad | F73: Nihon Kohden | G73: PVM-2701 | H73: 115432 | I73: HPL29916 | J73: 2016 | K73: 8 | L73: 0 | M73: Propio | N73: Bueno | O73: CRÍTICO | P73: NO | Q73: NO APLICA | R73: SI | S73: 2023 | T73: INTERNO | U73: TECNICO EQM HPL | V73: NO APLICA | X73: 2 | AB73: √ | AH73: X
A74: Pabellón | B74: Hospital Penco Lirquen | C74: Monitoreo | D74: Mediano Costo | E74: Monitor ECG Baja Complejidad | F74: Nihon Kohden | G74: PVM-2701 | H74: 115426 | I74: HPL29915 | J74: 2016 | K74: 8 | L74: 0 | M74: Propio | N74: Bueno | O74: CRÍTICO | P74: NO | Q74: NO APLICA | R74: SI | S74: 2023 | T74: INTERNO | U74: TECNICO EQM HPL | V74: NO APLICA | X74: 2 | AB74: √ | AH74: X
A75: Endoscopia y PCM | B75: Hospital Penco Lirquen | C75: Monitoreo | D75: Mediano Costo | E75: Monitor ECG Baja Complejidad | F75: Fukuda Denshi | G75: Dinascope DSL-8001 | H75: 50200459 | I75: HPL30041 | J75: 2016 | K75: 8 | L75: 0 | M75: Propio | N75: Bueno | O75: CRÍTICO | P75: NO | Q75: NO APLICA | R75: SI | S75: 2023 | T75: INTERNO | U75: TECNICO EQM HPL | V75: NO APLICA | X75: 2 | AC75: √ | AI75: X
A76: Endoscopia y PCM | B76: Hospital Penco Lirquen | C76: Monitoreo | D76: Mediano Costo | E76: Monitor desfibrilador | F76: Instramed | G76: Cardiomax | H76: 10608CM2833 | I76: HPL30137 | J76: 2014 | K76: 8 | L76: -2 | M76: Propio | N76: BUENO | O76: CRÍTICO | P76: NO | Q76: NO APLICA | R76: SI | S76: 2023 | T76: INTERNO | U76: TECNICO EQM HPL | V76: NO APLICA | W76: - | X76: 2 | AC76: √ | AI76: X
A77: Pabellón | B77: Hospital Penco Lirquen | C77: Monitoreo | D77: Mediano Costo | E77: Monitor ECG Baja Complejidad | F77: Nihon Kohden | G77: PVM-2701 | H77: 115425 | I77: HPL29914 | J77: 2016 | K77: 8 | L77: 0 | M77: Propio | N77: Bueno | O77: CRÍTICO | P77: NO | Q77: NO APLICA | R77: SI | S77: 2023 | T77: INTERNO | U77: TECNICO EQM HPL | V77: NO APLICA | X77: 2 | AB77: √ | AH77: X
A78: Endoscopia y PCM | B78: Hospital Penco Lirquen | C78: Monitoreo | D78: Alto Costo | E78: Monitor ECG mediana complejidad | F78: Progetti | G78: TGS50 | H78: Q068E034129 | I78: HPL30277 | J78: 2021 | K78: 8 | L78: 5 | M78: Préstamo | N78: Bueno | O78: CRÍTICO | P78: NO | Q78: NO APLICA | R78: SI | S78: 2023 | T78: INTERNO | U78: TECNICO EQM HPL | V78: NO APLICA | X78: 2 | AC78: √ | AI78: X
A79: Pabellón | B79: Hospital Penco Lirquen | C79: Monitoreo | D79: Mediano Costo | E79: Monitor ECG Baja Complejidad | F79: Nihon Kohden | G79: PVM-2701 | H79: 115405 | I79: HPL29912 | J79: 2016 | K79: 8 | L79: 0 | M79: Propio | N79: Bueno | O79: CRÍTICO | P79: NO | Q79: NO APLICA | R79: SI | S79: 2023 | T79: INTERNO | U79: TECNICO EQM HPL | V79: NO APLICA | X79: 2 | AB79: √ | AH79: X
A80: Pabellón | B80: Hospital Penco Lirquen | C80: Monitoreo | D80: Mediano Costo | E80: Monitor desfibrilador | F80: Zoll medical | G80: Serie R ALS | H80: AF15D045672 | I80: HPL30214 | J80: 2016 | K80: 8 | L80: 0 | M80: Propio | N80: Bueno | O80: CRÍTICO | P80: NO | Q80: NO APLICA | R80: SI | S80: 2023 | T80: INTERNO | U80: TECNICO EQM HPL | V80: NO APLICA | W80: - | X80: 2 | AB80: √ | AH80: X
A81: Pabellón | B81: Hospital Penco Lirquen | C81: Monitoreo | D81: Mediano Costo | E81: Monitor desfibrilador | F81: Zoll medical | G81: Serie R ALS | H81: AF15D045656 | I81: HPL30212 | J81: 2016 | K81: 8 | L81: 0 | M81: Propio | N81: Bueno | O81: CRÍTICO | P81: NO | Q81: NO APLICA | R81: SI | S81: 2023 | T81: INTERNO | U81: TECNICO EQM HPL | V81: NO APLICA | W81: - | X81: 2 | AB81: √ | AH81: X
A82: Laboratorio | B82: Hospital Penco Lirquen | C82: Monitoreo | D82: Mediano Costo | E82: Monitor de signos vitales | F82: Criticare | G82: 506DN | H82: 122010786 | I82: HPL30046 | J82: 2022 | K82: 8 | L82: 6 | M82: Propio | N82: Bueno | O82: CRÍTICO | P82: NO | Q82: NO APLICA | R82: SI | S82: 2023 | T82: INTERNO | U82: TECNICO EQM HPL | V82: NO APLICA | X82: 2 | AD82: √ | AJ82: X
A83: Imagenologia | B83: Hospital Penco Lirquen | C83: Monitoreo | D83: Mediano Costo | E83: Monitor desfibrilador | F83: Zoll medical | G83: Serie R ALS | H83: AF20G120257 | I83: HPL30216 | J83: 2021 | K83: 8 | L83: 5 | M83: Propio | N83: Bueno | O83: CRÍTICO | P83: NO | Q83: NO APLICA | R83: SI | S83: 2023 | T83: INTERNO | U83: TECNICO EQM HPL | V83: NO APLICA | W83: - | X83: 2 | AD83: √ | AJ83: X
A84: Imagenologia | B84: Hospital Penco Lirquen | C84: Monitoreo | D84: Mediano Costo | E84: Monitor ECG Baja Complejidad | F84: Fukuda Denshi | G84: Dinascope DSL-8001 | H84: 50200456 | I84: HPL30038 | J84: 2016 | K84: 8 | L84: 0 | M84: Propio | N84: Bueno | O84: CRÍTICO | P84: NO | Q84: NO APLICA | R84: SI | S84: 2023 | T84: INTERNO | U84: TECNICO EQM HPL | V84: NO APLICA | X84: 2 | AC84: √ | AI84: X
A85: Endoscopia y PCM (urgencia) | B85: Hospital Penco Lirquen | C85: Monitoreo | D85: Mediano Costo | E85: Monitor de signos vitales | F85: Mindray | G85: DPM3 | H85: DQ-18000395 | I85: HPL30238 | J85: 2015 | K85: 8 | L85: -1 | M85: Propio | N85: Bueno | O85: CRÍTICO | P85: NO | Q85: NO APLICA | R85: SI | S85: 2023 | T85: INTERNO | U85: TECNICO EQM HPL | V85: NO APLICA | X85: 2 | AC85: √ | AI85: X
A86: Hospitalizados - 9D | B86: Hospital Penco Lirquen | C86: Apoyo Terapéutico | D86: Alto Costo | E86: Ventilador Mecanico No Invasivo | F86: Philips | G86: Trilogy EV300 | H86: H29910884D650 | I86: HPL31308 | J86: 2022 | K86: 8 | L86: 6 | M86: Propio | N86: Bueno | O86: CRÍTICO | P86: SI | Q86: 45627 | R86: SI | S86: 2023 | T86: EXTERNO | U86: Andover | V86: COLDAS 2022 | W86: - | X86: 2 | AD86: √ | AJ86: X
A87: Hospitalizados | B87: Hospital Penco Lirquen | C87: Monitoreo | D87: Mediano Costo | E87: Monitor ECG Baja Complejidad | F87: Philips | G87: Efficia CM100 | H87: CN12099175 | J87: 2024 | K87: 8 | L87: 8 | M87: Propio | N87: Bueno | O87: CRÍTICO | P87: SI | Q87: 2026 | R87: SI | S87: 2024 | T87: EXTERNO | U87: Andover | V87: 1057540-125-LE23 | W87: 0 | X87: 2 | AD87: √ | AJ87: X
A88: Hospitalizados | B88: Hospital Penco Lirquen | C88: Monitoreo | D88: Mediano Costo | E88: Monitor ECG Baja Complejidad | F88: Philips | G88: Efficia CM100 | H88: CN12099176 | J88: 2024 | K88: 8 | L88: 8 | M88: Propio | N88: Bueno | O88: CRÍTICO | P88: SI | Q88: 2026 | R88: SI | S88: 2024 | T88: EXTERNO | U88: Andover | V88: 1057540-125-LE23 | W88: 0 | X88: 2 | AD88: √ | AJ88: X
A89: Hospitalizados | B89: Hospital Penco Lirquen | C89: Monitoreo | D89: Mediano Costo | E89: Monitor ECG Baja Complejidad | F89: Philips | G89: Efficia CM100 | H89: CN12099177 | J89: 2024 | K89: 8 | L89: 8 | M89: Propio | N89: Bueno | O89: CRÍTICO | P89: SI | Q89: 2026 | R89: SI | S89: 2024 | T89: EXTERNO | U89: Andover | V89: 1057540-125-LE23 | W89: 0 | X89: 2 | AD89: √ | AJ89: X
A90: Hospitalizados | B90: Hospital Penco Lirquen | C90: Monitoreo | D90: Alto Costo | E90: Monitor ECG mediana complejidad | F90: Mindray | G90: uMEC12 | H90: KQ-04039751 | I90: HPL30267 | J90: 2020 | K90: 8 | L90: 4 | M90: Propio | N90: Bueno | O90: CRÍTICO | P90: NO | Q90: NO APLICA | R90: SI | S90: 2023 | T90: INTERNO | U90: TECNICO EQM HPL | V90: NO APLICA | X90: 2 | AB90: √ | AH90: X
A91: Hospitalizados | B91: Hospital Penco Lirquen | C91: Monitoreo | D91: Alto Costo | E91: Monitor ECG mediana complejidad | F91: Mindray | G91: uMEC12 | H91: KQ-04039657 | I91: HPL30266 | J91: 2020 | K91: 8 | L91: 4 | M91: Propio | N91: Bueno | O91: CRÍTICO | P91: NO | Q91: NO APLICA | R91: SI | S91: 2023 | T91: INTERNO | U91: TECNICO EQM HPL | V91: NO APLICA | X91: 2 | AB91: √ | AH91: X
A92: Hospitalizados | B92: Hospital Penco Lirquen | C92: Monitoreo | D92: Alto Costo | E92: Monitor ECG mediana complejidad | F92: Mindray | G92: uMEC12 | H92: KQ-04039627 | I92: HPL30265 | J92: 2020 | K92: 8 | L92: 4 | M92: Propio | N92: Bueno | O92: CRÍTICO | P92: NO | Q92: NO APLICA | R92: SI | S92: 2023 | T92: INTERNO | U92: TECNICO EQM HPL | V92: NO APLICA | X92: 2 | AB92: √ | AH92: X
A93: Hospitalizados | B93: Hospital Penco Lirquen | C93: Monitoreo | D93: Alto Costo | E93: Monitor ECG mediana complejidad | F93: Mindray | G93: uMEC12 | H93: KQ-04039590 | I93: HPL30264 | J93: 2020 | K93: 8 | L93: 4 | M93: Propio | N93: Bueno | O93: CRÍTICO | P93: NO | Q93: NO APLICA | R93: SI | S93: 2023 | T93: INTERNO | U93: TECNICO EQM HPL | V93: NO APLICA | X93: 2 | AB93: √ | AH93: X
A94: Hospitalizados | B94: Hospital Penco Lirquen | C94: Monitoreo | D94: Alto Costo | E94: Monitor ECG mediana complejidad | F94: Mindray | G94: uMEC12 | H94: KQ-04039029 | I94: HPL30263 | J94: 2020 | K94: 8 | L94: 4 | M94: Propio | N94: Bueno | O94: CRÍTICO | P94: NO | Q94: NO APLICA | R94: SI | S94: 2023 | T94: INTERNO | U94: TECNICO EQM HPL | V94: NO APLICA | X94: 2 | AB94: √ | AH94: X
A95: Hospitalizados | B95: Hospital Penco Lirquen | C95: Monitoreo | D95: Alto Costo | E95: Monitor ECG mediana complejidad | F95: Mindray | G95: uMEC12 | H95: KQ-04039010 | I95: HPL30262 | J95: 2020 | K95: 8 | L95: 4 | M95: Propio | N95: Bueno | O95: CRÍTICO | P95: NO | Q95: NO APLICA | R95: SI | S95: 2023 | T95: INTERNO | U95: TECNICO EQM HPL | V95: NO APLICA | X95: 2 | AB95: √ | AH95: X
A96: Hospitalizados | B96: Hospital Penco Lirquen | C96: Monitoreo | D96: Mediano Costo | E96: Monitor de signos vitales | F96: Mindray | G96: DPM3 | H96: DQ-18000407 | I96: HPL25044 | J96: 2014 | K96: 8 | L96: -2 | M96: Propio | N96: Bueno | O96: CRÍTICO | P96: NO | Q96: NO APLICA | R96: SI | S96: 2023 | T96: INTERNO | U96: TECNICO EQM HPL | V96: NO APLICA | X96: 2 | AB96: √ | AH96: X
A97: Hospitalizados | B97: Hospital Penco Lirquen | C97: Monitoreo | D97: Mediano Costo | E97: Monitor de signos vitales | F97: Mindray | G97: DPM3 | H97: DQ-18000403 | I97: HPL25252 | J97: 2014 | K97: 8 | L97: -2 | M97: Propio | N97: Bueno | O97: CRÍTICO | P97: NO | Q97: NO APLICA | R97: SI | S97: 2023 | T97: INTERNO | U97: TECNICO EQM HPL | V97: NO APLICA | X97: 2 | AB97: √ | AH97: X
A98: Especialidades cuidados paliativos | B98: Hospital Penco Lirquen | C98: Monitoreo | D98: Mediano Costo | E98: Monitor de signos vitales | F98: General Electric | G98: V100 | H98: SH617070056SA | I98: HPL5044 | J98: 2017 | K98: 8 | L98: 1 | M98: Propio | N98: Bueno | O98: CRÍTICO | P98: NO | Q98: NO APLICA | R98: SI | S98: 2023 | T98: INTERNO | U98: TECNICO EQM HPL | V98: NO APLICA | X98: 2 | AD98: √ | AJ98: X
A99: Especialidades cuidados paliativos | B99: Hospital Penco Lirquen | C99: Monitoreo | D99: Mediano Costo | E99: Monitor de signos vitales | F99: General Electric | G99: V100 | H99: SH617070057SA | I99: HPL5046 | J99: 2017 | K99: 8 | L99: 1 | M99: Propio | N99: Bueno | O99: CRÍTICO | P99: NO | Q99: NO APLICA | R99: SI | S99: 2023 | T99: INTERNO | U99: TECNICO EQM HPL | V99: NO APLICA | X99: 2 | AD99: √ | AJ99: X
A100: Hospitalizados | B100: Hospital Penco Lirquen | C100: Monitoreo | D100: Mediano Costo | E100: Monitor de signos vitales | F100: Mindray | G100: DPM3 | H100: DQ-18000398 | I100: HPL25043 | J100: 2014 | K100: 8 | L100: -2 | M100: Propio | N100: Bueno | O100: CRÍTICO | P100: NO | Q100: NO APLICA | R100: SI | S100: 2023 | T100: INTERNO | U100: TECNICO EQM HPL | V100: NO APLICA | X100: 2 | AB100: √ | AH100: X
A101: Hospitalizados | B101: Hospital Penco Lirquen | C101: Monitoreo | D101: Mediano Costo | E101: Monitor de signos vitales | F101: General Electric | G101: V100 | H101: SH622300074SA | I101: HPL31303 | J101: 2022 | K101: 8 | L101: 6 | M101: Propio | N101: Bueno | O101: CRÍTICO | P101: SI | Q101: 45627 | R101: SI | S101: 2023 | T101: EXTERNO | U101: PV EQUIP | V101: COLDAS | X101: 2 | AB101: √ | AH101: X
...

Sheet Detalle3
A1: Detalles para Suma de COSTO ANUAL DE MANTENIMIENTO SEGÚN CONVENIO / PRECIO DE REFERENCIA MANTENIMIENTO ANUAL - AÑO INGRESO A PLAN DE MANTENIMIENTO (2023 / 2024 / 2025 / 2026): 2025
A3: SERVICIO CLÍNICO | B3: RECINTO | C3: CLASE | D3: SUBCLASE | E3: NOMBRE EQUIPO | F3: MARCA | G3: MODELO | H3: SERIE | I3: N° INVENTARIO | J3: AÑO DE ADQUISICIÓN | K3: VIDA ÚTIL | L3: VIDA ÚTIL RESIDUAL | M3: PROPIO / ARRIENDO / COMODATO | N3: ESTADO (BUENO / REGULAR / MALO / BAJA) | O3: CRÍTICO/ RELEVANTE / IM≥12 / NO APLICA | P3: EN GARANTÍA (SI / NO) | Q3: AÑO VENCIMIENTO GARANTÍA | R3: BAJO PLAN DE MANTENIMIENTO (SI / NO) | S3: AÑO INGRESO A PLAN DE MANTENIMIENTO (2023 / 2024 / 2025 / 2026) | T3: MANTENIMIENTO INTERNO O MANTENIMIENTO EXTERNO O CONTRATO | U3: NOMBRE DE PROVEEDOR O MANTENIMIENTO INTERNO | V3: ID CONVENIO DE MANTENIMIENTO / ID DE REFERENCIA / COTIZACIÓN DE REFERENCIA | W3: COSTO ANUAL DE MANTENIMIENTO SEGÚN CONVENIO / PRECIO DE REFERENCIA MANTENIMIENTO ANUAL | X3: FRECUENCIA ANUAL DE MANTENIMIENTO | Y3: ENERO | Z3: FEBRERO | AA3: MARZO | AB3: ABRIL | AC3: MAYO | AD3: JUNIO | AE3: JULIO | AF3: AGOSTO | AG3: SEPTIEMBRE | AH3: OCTUBRE | AI3: NOVIEMBRE | AJ3: DICIEMBRE
A4: Laboratorio | B4: Hospital Penco Lirquen | C4: Laboratorio/Farmac | D4: Alto Costo | E4: Analizador de orina | F4: Cobas | G4: U411 | H4: 20638 | J4: 2024 | K4: 8 | L4: 8 | M4: Comodato | N4: BUENO | O4: IM ≥ 12 | P4: NO | Q4: NO APLICA | R4: SI | S4: 2025 | T4: CONTRATO | U4: ROCHE | V4: 1057540-126-LP23 | W4: 0

Sheet TABLA CÁLCULO
A3: Etiquetas de fila | B3: Suma de FRECUENCIA ANUAL DE MANTENIMIENTO
A4: CRÍTICO | B4: 276
A5: IM ≥ 12 | B5: 378
A6: RELEVANTE | B6: 39
A7: NO APLICA | B7: 22
A8: Total general | B8: 715
B12: ENERO | C12: FEBRERO | D12: MARZO | E12: ABRIL | F12: MAYO | G12: JUNIO | H12: JULIO | I12: AGOSTO | J12: SEPTIEMBRE | K12: OCTUBRE | L12: NOVIEMBRE | M12: DICIEMBRE | O12: TOTAL MP PROGRAMADAS | P12: =+GETPIVOTDATA("FRECUENCIA ANUAL DE MANTENIMIENTO",$A$49,"AÑO INGRESO A PLAN DE MANTENIMIENTO (2023 / 2024 / 2025 / 2026)",2023)++GETPIVOTDATA("FRECUENCIA ANUAL DE MANTENIMIENTO",$A$49,"AÑO INGRESO A PLAN DE MANTENIMIENTO (2023 / 2024 / 2025 / 2026)",2024)+++GETPIVOTDATA("FRECUENCIA ANUAL DE MANTENIMIENTO",$A$49,"AÑO INGRESO A PLAN DE MANTENIMIENTO (2023 / 2024 / 2025 / 2026)",2025) -> 711
A13: N° MP EJECUTADAS | B13: =+COUNTIF('CATASTRO Y PLANIFICACIÓN MP'!Y16:Y151,"√") -> 4 | C13: =+COUNTIF('CATASTRO Y PLANIFICACIÓN MP'!Z16:Z151,"√") -> 0 | D13: =+COUNTIF('CATASTRO Y PLANIFICACIÓN MP'!AA16:AA151,"√") -> 3 | E13: =+COUNTIF('CATASTRO Y PLANIFICACIÓN MP'!AB16:AB151,"√") -> 0 | F13: =+COUNTIF('CATASTRO Y PLANIFICACIÓN MP'!AC16:AC151,"√") -> 0 | G13: =+COUNTIF('CATASTRO Y PLANIFICACIÓN MP'!AD16:AD151,"√") -> 0 | H13: =+COUNTIF('CATASTRO Y PLANIFICACIÓN MP'!AE16:AE151,"√") -> 0 | I13: =+COUNTIF('CATASTRO Y PLANIFICACIÓN MP'!AF16:AF151,"√") -> 0 | ... M13: =+COUNTIF('CATASTRO Y PLANIFICACIÓN MP'!AJ16:AJ151,"√") -> 0 | O13: TOTAL MP EJECUTADAS | P13: =+SUM(B13:M13) -> 7 | R13: X | S13: PROGRAMADO | U13: CRÍTICO | W13: SI | Y13: 2025 | AA13: INTERNO | AC13: 1 | AE13: PROPIO | AF13: BUENO
A14: N° MP REPROGRAMADAS | B14: =+COUNTIF('CATASTRO Y PLANIFICACIÓN MP'!#REF!,"ꓣ") -> #REF! | C14: =+COUNTIF('CATASTRO Y PLANIFICACIÓN MP'!#REF!,"ꓣ") -> #REF! | D14: =+COUNTIF('CATASTRO Y PLANIFICACIÓN MP'!#REF!,"ꓣ") -> #REF! | E14: =+COUNTIF('CATASTRO Y PLANIFICACIÓN MP'!#REF!,"ꓣ") -> #REF! | F14: =+COUNTIF('CATASTRO Y PLANIFICACIÓN MP'!#REF!,"ꓣ") -> #REF! | G14: =+COUNTIF('CATASTRO Y PLANIFICACIÓN MP'!#REF!,"ꓣ") -> #REF! | H14: =+COUNTIF('CATASTRO Y PLANIFICACIÓN MP'!#REF!,"ꓣ") -> #REF! | I14: =+COUNTIF('CATASTRO Y PLANIFICACIÓN MP'!#REF!,"ꓣ") -> #REF! | ... M14: =+COUNTIF('CATASTRO Y PLANIFICACIÓN MP'!#REF!,"ꓣ") -> #REF! | O14: TOTAL MP REPROGRAMADAS | P14: =+SUM(B14:M14) -> #REF! | R14: √ | S14: REALIZADO | U14: RELEVANTE | W14: NO | Y14: 2026 | AA14: EXTERNO | AC14: 2 | AE14: ARRIENDO | AF14: REGULAR
B15: ENERO | C15: FEBRERO | D15: MARZO | E15: ABRIL | F15: MAYO | G15: JUNIO | H15: JULIO | I15: AGOSTO | J15: SEPTIEMBRE | K15: OCTUBRE | L15: NOVIEMBRE | M15: DICIEMBRE | O15: TOTAL MP PROGRAMADAS EQC | P15: =+GETPIVOTDATA("FRECUENCIA ANUAL DE MANTENIMIENTO",$A$49,"CRÍTICO/ RELEVANTE / IM≥12 / NO APLICA","CRÍTICO","AÑO INGRESO A PLAN DE MANTENIMIENTO (2023 / 2024 / 2025 / 2026)",2023)+GETPIVOTDATA("FRECUENCIA ANUAL DE MANTENIMIENTO",$A$49,"CRÍTICO/ RELEVANTE / IM≥12 / NO APLICA","CRÍTICO","AÑO INGRESO A PLAN DE MANTENIMIENTO (2023 / 2024 / 2025 / 2026)",2024)++GETPIVOTDATA("FRECUENCIA ANUAL DE MANTENIMIENTO",$A$49,"CRÍTICO/ RELEVANTE / IM≥12 / NO APLICA","CRÍTICO","AÑO INGRESO A PLAN DE MANTENIMIENTO (2023 / 2024 / 2025 / 2026)",2025) -> 272 | R15: ꓣ | S15: REPROGRAMADO | U15: IM ≥ 12 | Y15: 2027 | AA15: CONTRATO | AC15: 3 | AE15: COMODATO | AF15: MALO
A16: N° MP EJECUTADAS EQ 2.1 | B16: =+COUNTIFS('CATASTRO Y PLANIFICACIÓN MP'!#REF!,"CRÍTICO",'CATASTRO Y PLANIFICACIÓN MP'!#REF!,"√") -> #REF! | C16: =+COUNTIFS('CATASTRO Y PLANIFICACIÓN MP'!#REF!,"CRÍTICO",'CATASTRO Y PLANIFICACIÓN MP'!#REF!,"√") -> #REF! | D16: =+COUNTIFS('CATASTRO Y PLANIFICACIÓN MP'!#REF!,"CRÍTICO",'CATASTRO Y PLANIFICACIÓN MP'!#REF!,"√") -> #REF! | E16: =+COUNTIFS('CATASTRO Y PLANIFICACIÓN MP'!#REF!,"CRÍTICO",'CATASTRO Y PLANIFICACIÓN MP'!#REF!,"√") -> #REF! | F16: =+COUNTIFS('CATASTRO Y PLANIFICACIÓN MP'!#REF!,"CRÍTICO",'CATASTRO Y PLANIFICACIÓN MP'!#REF!,"√") -> #REF! | G16: =+COUNTIFS('CATASTRO Y PLANIFICACIÓN MP'!#REF!,"CRÍTICO",'CATASTRO Y PLANIFICACIÓN MP'!#REF!,"√") -> #REF! | H16: =+COUNTIFS('CATASTRO Y PLANIFICACIÓN MP'!#REF!,"CRÍTICO",'CATASTRO Y PLANIFICACIÓN MP'!#REF!,"√") -> #REF! | I16: =+COUNTIFS('CATASTRO Y PLANIFICACIÓN MP'!#REF!,"CRÍTICO",'CATASTRO Y PLANIFICACIÓN MP'!#REF!,"√") -> #REF! | ... M16: =+COUNTIFS('CATASTRO Y PLANIFICACIÓN MP'!#REF!,"CRÍTICO",'CATASTRO Y PLANIFICACIÓN MP'!#REF!,"√") -> #REF! | O16: TOTAL MP PROGRAMADAS EQR | P16: =+GETPIVOTDATA("FRECUENCIA ANUAL DE MANTENIMIENTO",$A$49,"CRÍTICO/ RELEVANTE / IM≥12 / NO APLICA","RELEVANTE","AÑO INGRESO A PLAN DE MANTENIMIENTO (2023 / 2024 / 2025 / 2026)",2023)+GETPIVOTDATA("FRECUENCIA ANUAL DE MANTENIMIENTO",$A$49,"CRÍTICO/ RELEVANTE / IM≥12 / NO APLICA","RELEVANTE","AÑO INGRESO A PLAN DE MANTENIMIENTO (2023 / 2024 / 2025 / 2026)",2024) -> 39 | U16: NO APLICA | Y16: 2028 | AC16: 4 | AE16: PRÉSTAMO | AF16: BAJA, PARA REPOSICIÓN
A17: N° MP EJECUTADAS EQ 2.2 | B17: =+COUNTIFS('CATASTRO Y PLANIFICACIÓN MP'!#REF!,"RELEVANTE",'CATASTRO Y PLANIFICACIÓN MP'!#REF!,"√") -> #REF! | C17: =+COUNTIFS('CATASTRO Y PLANIFICACIÓN MP'!#REF!,"RELEVANTE",'CATASTRO Y PLANIFICACIÓN MP'!#REF!,"√") -> #REF! | D17: =+COUNTIFS('CATASTRO Y PLANIFICACIÓN MP'!#REF!,"RELEVANTE",'CATASTRO Y PLANIFICACIÓN MP'!#REF!,"√") -> #REF! | E17: =+COUNTIFS('CATASTRO Y PLANIFICACIÓN MP'!#REF!,"RELEVANTE",'CATASTRO Y PLANIFICACIÓN MP'!#REF!,"√") -> #REF! | F17: =+COUNTIFS('CATASTRO Y PLANIFICACIÓN MP'!#REF!,"RELEVANTE",'CATASTRO Y PLANIFICACIÓN MP'!#REF!,"√") -> #REF! | G17: =+COUNTIFS('CATASTRO Y PLANIFICACIÓN MP'!#REF!,"RELEVANTE",'CATASTRO Y PLANIFICACIÓN MP'!#REF!,"√") -> #REF! | H17: =+COUNTIFS('CATASTRO Y PLANIFICACIÓN MP'!#REF!,"RELEVANTE",'CATASTRO Y PLANIFICACIÓN MP'!#REF!,"√") -> #REF! | I17: =+COUNTIFS('CATASTRO Y PLANIFICACIÓN MP'!#REF!,"RELEVANTE",'CATASTRO Y PLANIFICACIÓN MP'!#REF!,"√") -> #REF! | ... M17: =+COUNTIFS('CATASTRO Y PLANIFICACIÓN MP'!#REF!,"RELEVANTE",'CATASTRO Y PLANIFICACIÓN MP'!#REF!,"√") -> #REF! | O17: TOTAL MP PROGRAMADAS IM≥12 | P17: =+GETPIVOTDATA("FRECUENCIA ANUAL DE MANTENIMIENTO",$A$49,"CRÍTICO/ RELEVANTE / IM≥12 / NO APLICA","IM ≥ 12","AÑO INGRESO A PLAN DE MANTENIMIENTO (2023 / 2024 / 2025 / 2026)",2023)+GETPIVOTDATA("FRECUENCIA ANUAL DE MANTENIMIENTO",$A$49,"CRÍTICO/ RELEVANTE / IM≥12 / NO APLICA","IM ≥ 12","AÑO INGRESO A PLAN DE MANTENIMIENTO (2023 / 2024 / 2025 / 2026)",2024)+GETPIVOTDATA("FRECUENCIA ANUAL DE MANTENIMIENTO",$A$49,"CRÍTICO/ RELEVANTE / IM≥12 / NO APLICA","IM ≥ 12","AÑO INGRESO A PLAN DE MANTENIMIENTO (2023 / 2024 / 2025 / 2026)",2025) -> 378 | AC17: 6
A18: N° MP EJECUTADAS IM≥12 | B18: =+COUNTIFS('CATASTRO Y PLANIFICACIÓN MP'!#REF!,"IM ≥ 12",'CATASTRO Y PLANIFICACIÓN MP'!#REF!,"√") -> #REF! | C18: =+COUNTIFS('CATASTRO Y PLANIFICACIÓN MP'!#REF!,"IM ≥ 12",'CATASTRO Y PLANIFICACIÓN MP'!#REF!,"√") -> #REF! | D18: =+COUNTIFS('CATASTRO Y PLANIFICACIÓN MP'!#REF!,"IM ≥ 12",'CATASTRO Y PLANIFICACIÓN MP'!#REF!,"√") -> #REF! | E18: =+COUNTIFS('CATASTRO Y PLANIFICACIÓN MP'!#REF!,"IM ≥ 12",'CATASTRO Y PLANIFICACIÓN MP'!#REF!,"√") -> #REF! | F18: =+COUNTIFS('CATASTRO Y PLANIFICACIÓN MP'!#REF!,"IM ≥ 12",'CATASTRO Y PLANIFICACIÓN MP'!#REF!,"√") -> #REF! | G18: =+COUNTIFS('CATASTRO Y PLANIFICACIÓN MP'!#REF!,"IM ≥ 12",'CATASTRO Y PLANIFICACIÓN MP'!#REF!,"√") -> #REF! | H18: =+COUNTIFS('CATASTRO Y PLANIFICACIÓN MP'!#REF!,"IM ≥ 12",'CATASTRO Y PLANIFICACIÓN MP'!#REF!,"√") -> #REF! | I18: =+COUNTIFS('CATASTRO Y PLANIFICACIÓN MP'!#REF!,"IM ≥ 12",'CATASTRO Y PLANIFICACIÓN MP'!#REF!,"√") -> #REF! | ... M18: =+COUNTIFS('CATASTRO Y PLANIFICACIÓN MP'!#REF!,"IM ≥ 12",'CATASTRO Y PLANIFICACIÓN MP'!#REF!,"√") -> #REF! | O18: TOTAL MP EJECUTADAS EQC | P18: =+SUM(B16:M16) -> #REF! | AC18: 12
A19: N° MP REPROGRAMADAS EQ 2.1 | B19: =+COUNTIFS('CATASTRO Y PLANIFICACIÓN MP'!#REF!,"CRÍTICO",'CATASTRO Y PLANIFICACIÓN MP'!#REF!,"ꓣ") -> #REF! | C19: =+COUNTIFS('CATASTRO Y PLANIFICACIÓN MP'!#REF!,"CRÍTICO",'CATASTRO Y PLANIFICACIÓN MP'!#REF!,"ꓣ") -> #REF! | D19: =+COUNTIFS('CATASTRO Y PLANIFICACIÓN MP'!#REF!,"CRÍTICO",'CATASTRO Y PLANIFICACIÓN MP'!#REF!,"ꓣ") -> #REF! | E19: =+COUNTIFS('CATASTRO Y PLANIFICACIÓN MP'!#REF!,"CRÍTICO",'CATASTRO Y PLANIFICACIÓN MP'!#REF!,"ꓣ") -> #REF! | F19: =+COUNTIFS('CATASTRO Y PLANIFICACIÓN MP'!#REF!,"CRÍTICO",'CATASTRO Y PLANIFICACIÓN MP'!#REF!,"ꓣ") -> #REF! | G19: =+COUNTIFS('CATASTRO Y PLANIFICACIÓN MP'!#REF!,"CRÍTICO",'CATASTRO Y PLANIFICACIÓN MP'!#REF!,"ꓣ") -> #REF! | H19: =+COUNTIFS('CATASTRO Y PLANIFICACIÓN MP'!#REF!,"CRÍTICO",'CATASTRO Y PLANIFICACIÓN MP'!#REF!,"ꓣ") -> #REF! | I19: =+COUNTIFS('CATASTRO Y PLANIFICACIÓN MP'!#REF!,"CRÍTICO",'CATASTRO Y PLANIFICACIÓN MP'!#REF!,"ꓣ") -> #REF! | ... M19: =+COUNTIFS('CATASTRO Y PLANIFICACIÓN MP'!#REF!,"CRÍTICO",'CATASTRO Y PLANIFICACIÓN MP'!#REF!,"ꓣ") -> #REF! | O19: TOTAL MP EJECUTADAS EQR | P19: =+SUM(B17:M17) -> #REF! | S19: MANTENIMIENTO CORRECTIVO
A20: N° MP REPROGRAMADAS EQ 2.2 | B20: =+COUNTIFS('CATASTRO Y PLANIFICACIÓN MP'!#REF!,"RELEVANTE",'CATASTRO Y PLANIFICACIÓN MP'!#REF!,"ꓣ") -> #REF! | C20: =+COUNTIFS('CATASTRO Y PLANIFICACIÓN MP'!#REF!,"RELEVANTE",'CATASTRO Y PLANIFICACIÓN MP'!#REF!,"ꓣ") -> #REF! | D20: =+COUNTIFS('CATASTRO Y PLANIFICACIÓN MP'!#REF!,"RELEVANTE",'CATASTRO Y PLANIFICACIÓN MP'!#REF!,"ꓣ") -> #REF! | E20: =+COUNTIFS('CATASTRO Y PLANIFICACIÓN MP'!#REF!,"RELEVANTE",'CATASTRO Y PLANIFICACIÓN MP'!#REF!,"ꓣ") -> #REF! | F20: =+COUNTIFS('CATASTRO Y PLANIFICACIÓN MP'!#REF!,"RELEVANTE",'CATASTRO Y PLANIFICACIÓN MP'!#REF!,"ꓣ") -> #REF! | G20: =+COUNTIFS('CATASTRO Y PLANIFICACIÓN MP'!#REF!,"RELEVANTE",'CATASTRO Y PLANIFICACIÓN MP'!#REF!,"ꓣ") -> #REF! | H20: =+COUNTIFS('CATASTRO Y PLANIFICACIÓN MP'!#REF!,"RELEVANTE",'CATASTRO Y PLANIFICACIÓN MP'!#REF!,"ꓣ") -> #REF! | I20: =+COUNTIFS('CATASTRO Y PLANIFICACIÓN MP'!#REF!,"RELEVANTE",'CATASTRO Y PLANIFICACIÓN MP'!#REF!,"ꓣ") -> #REF! | ... M20: =+COUNTIFS('CATASTRO Y PLANIFICACIÓN MP'!#REF!,"RELEVANTE",'CATASTRO Y PLANIFICACIÓN MP'!#REF!,"ꓣ") -> #REF! | O20: TOTAL MP EJECUTADAS IM≥12 | P20: =+SUM(B18:M18) -> #REF! | S20: ADQUISICIÓN DE REPUESTOS
A21: N° MP REPROGRAMADAS IM≥12 | B21: =+COUNTIFS('CATASTRO Y PLANIFICACIÓN MP'!#REF!,"IM ≥ 12",'CATASTRO Y PLANIFICACIÓN MP'!#REF!,"ꓣ") -> #REF! | C21: =+COUNTIFS('CATASTRO Y PLANIFICACIÓN MP'!#REF!,"IM ≥ 12",'CATASTRO Y PLANIFICACIÓN MP'!#REF!,"ꓣ") -> #REF! | D21: =+COUNTIFS('CATASTRO Y PLANIFICACIÓN MP'!#REF!,"IM ≥ 12",'CATASTRO Y PLANIFICACIÓN MP'!#REF!,"ꓣ") -> #REF! | E21: =+COUNTIFS('CATASTRO Y PLANIFICACIÓN MP'!#REF!,"IM ≥ 12",'CATASTRO Y PLANIFICACIÓN MP'!#REF!,"ꓣ") -> #REF! | F21: =+COUNTIFS('CATASTRO Y PLANIFICACIÓN MP'!#REF!,"IM ≥ 12",'CATASTRO Y PLANIFICACIÓN MP'!#REF!,"ꓣ") -> #REF! | G21: =+COUNTIFS('CATASTRO Y PLANIFICACIÓN MP'!#REF!,"IM ≥ 12",'CATASTRO Y PLANIFICACIÓN MP'!#REF!,"ꓣ") -> #REF! | H21: =+COUNTIFS('CATASTRO Y PLANIFICACIÓN MP'!#REF!,"IM ≥ 12",'CATASTRO Y PLANIFICACIÓN MP'!#REF!,"ꓣ") -> #REF! | I21: =+COUNTIFS('CATASTRO Y PLANIFICACIÓN MP'!#REF!,"IM ≥ 12",'CATASTRO Y PLANIFICACIÓN MP'!#REF!,"ꓣ") -> #REF! | ... M21: =+COUNTIFS('CATASTRO Y PLANIFICACIÓN MP'!#REF!,"IM ≥ 12",'CATASTRO Y PLANIFICACIÓN MP'!#REF!,"ꓣ") -> #REF! | S21: ADQUISICIÓN DE INSUMOS
O22: INDICADOR | P22: NIVEL ALCANZADO | S22: ADQUISICION DE ACCESORIOS
B23: ENERO | C23: FEBRERO | D23: MARZO | E23: ABRIL | F23: MAYO | G23: JUNIO | H23: JULIO | I23: AGOSTO | J23: SEPTIEMBRE | K23: OCTUBRE | L23: NOVIEMBRE | M23: DICIEMBRE | O23: % EJECUCION ANUAL MP | P23: =+P13/P12 -> 0.0098452883 | S23: OTRO
A24: % EJECUCIÓN MP TOTAL MENSUAL | B24: =+IFERROR(B13/(B13+B14),"") | C24: =+IFERROR(C13/(C13+C14),"") | D24: =+IFERROR(D13/(D13+D14),"") | E24: =+IFERROR(E13/(E13+E14),"") | F24: =+IFERROR(F13/(F13+F14),"") | G24: =+IFERROR(G13/(G13+G14),"") | H24: =+IFERROR(H13/(H13+H14),"") | I24: =+IFERROR(I13/(I13+I14),"") | ... M24: =+IFERROR(M13/(M13+M14),"") | O24: % EJECUCIÓN ANUAL EQC | P24: =+P18/P15 -> #REF!
A25: % EJECUCIÓN MP EQC MENSUAL | B25: =+IFERROR(B16/(B16+B19),"") | C25: =+IFERROR(C16/(C16+C19),"") | D25: =+IFERROR(D16/(D16+D19),"") | E25: =+IFERROR(E16/(E16+E19),"") | F25: =+IFERROR(F16/(F16+F19),"") | G25: =+IFERROR(G16/(G16+G19),"") | H25: =+IFERROR(H16/(H16+H19),"") | I25: =+IFERROR(I16/(I16+I19),"") | ... M25: =+IFERROR(M16/(M16+M19),"") | O25: % EJECUCIÓN ANUAL EQR | P25: =+P19/P16 -> #REF!
A26: % EJECUCIÓN MP EQR MENSUAL | B26: =+IFERROR(B17/(B17+B20),"") | C26: =+IFERROR(C17/(C17+C20),"") | D26: =+IFERROR(D17/(D17+D20),"") | E26: =+IFERROR(E17/(E17+E20),"") | F26: =+IFERROR(F17/(F17+F20),"") | G26: =+IFERROR(G17/(G17+G20),"") | H26: =+IFERROR(H17/(H17+H20),"") | I26: =+IFERROR(I17/(I17+I20),"") | ... M26: =+IFERROR(M17/(M17+M20),"") | O26: % EJECUCIÓN ANUAL IM≥12 | P26: =+P20/P17 -> #REF!
A27: % EJECUCIÓN MP IM≥12 MENSUAL | B27: =+IFERROR(B18/(B18+B21),"") | C27: =+IFERROR(C18/(C18+C21),"") | D27: =+IFERROR(D18/(D18+D21),"") | E27: =+IFERROR(E18/(E18+E21),"") | F27: =+IFERROR(F18/(F18+F21),"") | G27: =+IFERROR(G18/(G18+G21),"") | H27: =+IFERROR(H18/(H18+H21),"") | I27: =+IFERROR(I18/(I18+I21),"") | ... M27: =+IFERROR(M18/(M18+M21),"")
A29: GASTO PROGRAMADO MP | B29: =+SUM('SEGUIMIENTO GASTO'!I8:I13) -> 0
A31: GASTO PROGRAMADO MC | B31: =+'CATASTRO Y PLANIFICACIÓN MP'!B13 -> 0
A33: EJECUCIÓN GASTO MP | B33: =+SUM('SEGUIMIENTO GASTO'!AI8:AI13) -> 0
A35: EJECUCIÓN GASTO MC | B35: =+SUM('SEGUIMIENTO GASTO'!AG21:AG26) -> 0
A37: % EJECUCIÓN DEL GASTO MP | B37: =+IFERROR(B33/B29,"") | D37: =1-B37 -> #VALUE!
A39: % EJECUCIÓN DEL GASTO MC | B39: =+IFERROR(B35/B31,"") | D39: =1-B39 -> #VALUE!
A42: Etiquetas de fila | B42: Suma de COSTO ANUAL DE MANTENIMIENTO SEGÚN CONVENIO / PRECIO DE REFERENCIA MANTENIMIENTO ANUAL
A43: 2023 | B43: 205667484
A44: 2024 | B44: 8016150
A45: 2025 | B45: 0
A46: (en blanco) | B46: 10800000
A47: Total general | B47: 224483634
A49: Etiquetas de fila | B49: Suma de FRECUENCIA ANUAL DE MANTENIMIENTO
A50: 2023 | B50: 455
A51: CRÍTICO | B51: 234
A52: IM ≥ 12 | B52: 190
A53: RELEVANTE | B53: 31
A54: NO APLICA
A55: 2024 | B55: 193
A56: CRÍTICO | B56: 28
A57: IM ≥ 12 | B57: 153
A58: RELEVANTE | B58: 8
A59: NO APLICA | B59: 4
A60: 2025 | B60: 63
A61: CRÍTICO | B61: 10
A62: IM ≥ 12 | B62: 35
A63: NO APLICA | B63: 18
A64: NO APLICA
A65: NO APLICA
A66: Total general | B66: 711

Sheet PROYECCIÓN 2025
B3: SEGUIMIENTO GASTO CONVENIOS DE MANTENIMIENTO
K5: CONTROL MENSUAL EJECUCIÓN
K6: ENERO | M6: FEBRERO | O6: MARZO | Q6: ABRIL | S6: MAYO | U6: JUNIO | W6: JULIO | Y6: AGOSTO | AA6: SEPTIEMBRE | AC6: OCTUBRE | AE6: NOVIEMBRE | AG6: DICIEMBRE
B7: Nº | C7: SERVICIO DE SALUD | D7: ESTABLECIMIENTO | E7: NOMBRE CONVENIO DE MANTENIMIENTO | F7: Nº RESOLUCIÓN / ID / ORDEN DE COMPRA DEL CONVENIO | G7: FECHA RESOLUCIÓN | H7: FECHA DE EXPIRACION CONVENIO | I7: MONTO ANUAL ($) | J7: SUBASIGNACIÓN SIGFE | K7: N° ORDEN DE COMPRA / N° FACTURA | L7: MONTO ($) | M7: N° ORDEN DE COMPRA / N° FACTURA | N7: MONTO ($) | O7: N° ORDEN DE COMPRA / N° FACTURA | P7: MONTO ($) | Q7: N° ORDEN DE COMPRA / N° FACTURA | R7: MONTO ($) | S7: N° ORDEN DE COMPRA / N° FACTURA | T7: MONTO ($) | U7: N° ORDEN DE COMPRA / N° FACTURA | V7: MONTO ($) | W7: N° ORDEN DE COMPRA / N° FACTURA | X7: MONTO ($) | Y7: N° ORDEN DE COMPRA / N° FACTURA | Z7: MONTO ($) | AA7: N° ORDEN DE COMPRA / N° FACTURA | AB7: MONTO ($) | AC7: N° ORDEN DE COMPRA / N° FACTURA | AD7: MONTO ($) | AE7: N° ORDEN DE COMPRA / N° FACTURA | AF7: MONTO ($) | AG7: N° ORDEN DE COMPRA / N° FACTURA | AH7: MONTO ($) | AI7: TOTAL
B8: 1 | C8: SERVICIO DE SALUD TALCAHUANO | D8: HOSPITAL PENCO LIRQUEN | E8: CONVENIO MANTENIMIENTO PREVENTIVO Y CORRECTIVO DE MAQUINAS ANESTESIA PARA HOSPITAL PENCO LIRQUEN | F8: 1057540-77-LP24 | G8: 45587 | H8: 46263 | I8: =30391296+(2532608*3) -> 37989120 | J8: 22.06.006.003 | L8: =2532608+(2532608*3) -> 10130432 | N8: 2532608 | P8: 2532608 | R8: 2532608 | T8: 2532608 | V8: 2532608 | X8: 2532608 | Z8: 2532608 | AB8: 2532608 | AD8: 2532608 | AF8: 2532608 | AH8: 2532608 | AI8: =+L8+N8+P8+R8+T8+V8+X8+Z8+AB8+AD8+AF8+AH8 -> 37989120
B9: 2 | C9: SERVICIO DE SALUD TALCAHUANO | D9: HOSPITAL PENCO LIRQUEN | E9: SERVICIO DE MANTENCION PRE VENTIVA , CORRECTIVA PARA SIETE UNIDADES DENTALES | F9: 1057540-115-LE23 | G9: 45274 | H9: 46005 | I9: 1900000 | J9: 22.06.006.003 | N9: 600000 | V9: 700000 | AD9: 600000 | AI9: =+L9+N9+P9+R9+T9+V9+X9+Z9+AB9+AD9+AF9+AH9 -> 1900000
B10: 3 | C10: SERVICIO DE SALUD TALCAHUANO | D10: HOSPITAL PENCO LIRQUEN | E10: SERVICIO DE MANTENCION PREVENTIVA, CORRECTIVA PARA EQUIPOS DE ESTERILIZACIÓN PARA EL HOSPITAL - Reprocesadora de Endoscopios | F10: PENDIENTE | I10: 4072020 | J10: 22.06.006.003 | P10: 407202 | R10: 407202 | T10: 407202 | V10: 407202 | X10: 407202 | Z10: 407202 | AB10: 407202 | AD10: 407202 | AF10: 407202 | AH10: 407202 | AI10: =+L10+N10+P10+R10+T10+V10+X10+Z10+AB10+AD10+AF10+AH10 -> 4072020
B11: 4.1 | C11: SERVICIO DE SALUD TALCAHUANO | D11: HOSPITAL PENCO LIRQUEN | E11: SERVICIO DE MANTENCION PREVENTIVA, CORRECTIVA PARA EQUIPOS DE ESTERILIZACIÓN PARA EL HOSPITAL - Esterilizador de Plasma | F11: 1057540-91-LP23 | G11: 45219 | H11: 45950 | I11: 7021000 | J11: 22.06.006.003 | R11: 3510500 | AD11: 3510500 | AI11: =+L11+N11+P11+R11+T11+V11+X11+Z11+AB11+AD11+AF11+AH11 -> 7021000
B12: 4.2 | C12: SERVICIO DE SALUD TALCAHUANO | D12: HOSPITAL PENCO LIRQUEN | E12: SERVICIO DE MANTENCION PREVENTIVA, CORRECTIVA PARA EQUIPOS DE ESTERILIZACIÓN PARA EL HOSPITAL - Secadora de tubos | F12: 1057540-91-LP23 | G12: 45219 | H12: 45950 | I12: 5325974 | J12: 22.06.006.003 | N12: 2662987 | AB12: 2662987 | AI12: =+L12+N12+P12+R12+T12+V12+X12+Z12+AB12+AD12+AF12+AH12 -> 5325974
B13: 4.3 | C13: SERVICIO DE SALUD TALCAHUANO | D13: HOSPITAL PENCO LIRQUEN | E13: SERVICIO DE MANTENCION PREVENTIVA, CORRECTIVA PARA EQUIPOS DE ESTERILIZACIÓN PARA EL HOSPITAL - Lavadora descontaminadora | F13: 1057540-91-LP23 | G13: 45219 | H13: 45950 | I13: 6035504 | J13: 22.06.006.003 | N13: 3017752 | AB13: 3017752 | AI13: =+L13+N13+P13+R13+T13+V13+X13+Z13+AB13+AD13+AF13+AH13 -> 6035504
B14: 5 | C14: SERVICIO DE SALUD TALCAHUANO | D14: HOSPITAL PENCO LIRQUEN | E14: CONVENIO DE MANTENIMIENTO PREVENTIVO Y CORRECTIVO PARA 28 REFRIGERADORES CLINICOS DEL HOSPITAL PENCO LIRQUÉN | F14: 1057540-100-LE23 | G14: 45232 | H14: 45963 | I14: 1499400 | J14: 22.06.006.003 | AB14: 1499400 | AI14: =+L14+N14+P14+R14+T14+V14+X14+Z14+AB14+AD14+AF14+AH14 -> 1499400
B15: 6 | C15: SERVICIO DE SALUD TALCAHUANO | D15: HOSPITAL PENCO LIRQUEN | E15: CONVENIO DE MANTENCION PREVENTIVA Y CORRECTIVA PARA PISCINA TERAPEUTICA DE SERVICIO CLINICO DE REHABILITACION DEL HOSPITAL PENCO LIRQUÉN | F15: 1057540-134-LE23 | G15: 45307 | H15: 46038 | I15: 1190000 | J15: 22.06.006.003 | V15: 1190000 | AI15: =+L15+N15+P15+R15+T15+V15+X15+Z15+AB15+AD15+AF15+AH15 -> 1190000
B16: 7 | C16: SERVICIO DE SALUD TALCAHUANO | D16: HOSPITAL PENCO LIRQUEN | E16: CONVENIO DE MANTENCION PREVENTIVA Y CORRECTIVA PARA REENVASADORAS DE UNIDAD DE FARMACIA DEL HOSPITAL PENCO LIRQUÉN | F16: 1057540-122-LE23 | G16: 45303 | H16: 46034 | I16: 3665200 | J16: 22.06.006.003 | N16: 1832600 | Z16: 1832600 | AI16: =+L16+N16+P16+R16+T16+V16+X16+Z16+AB16+AD16+AF16+AH16 -> 3665200
B17: 8 | C17: SERVICIO DE SALUD TALCAHUANO | D17: HOSPITAL PENCO LIRQUEN | E17: MANTENCION PREVENTIVA, CORRECTIVA PARA EQUIPOS MICROSCOPIOS | F17: 1057540-130-LE23 | G17: 45306 | H17: 46037 | I17: 1761200 | J17: 22.06.006.003 | P17: 595000 | AD17: 1166200 | AI17: =+L17+N17+P17+R17+T17+V17+X17+Z17+AB17+AD17+AF17+AH17 -> 1761200
B18: 9 | C18: SERVICIO DE SALUD TALCAHUANO | D18: HOSPITAL PENCO LIRQUEN | E18: CONTRATACION DE SERVICIOS DE MANTENIMIENTO PREVENTIVO Y CORRECTIVO PARA EQUIPOS AUTOCLAVE, CÁMARA MORTUORIA Y ELEVADOR DE CADÁVERES DEL HOSPITAL DE PENCO-LIRQUÉN - Cámara Mortuoria y Carro Elevador | F18: 1057540-14-LE24 | G18: 45383 | H18: 46113 | I18: 1499400 | J18: 22.06.006.003 | N18: 1499400 | AI18: =+L18+N18+P18+R18+T18+V18+X18+Z18+AB18+AD18+AF18+AH18 -> 1499400
C19: SERVICIO DE SALUD TALCAHUANO | D19: HOSPITAL PENCO LIRQUEN | E19: CONTRATACION DE SERVICIOS DE MANTENIMIENTO PREVENTIVO Y CORRECTIVO PARA EQUIPOS AUTOCLAVE, CÁMARA MORTUORIA Y ELEVADOR DE CADÁVERES DEL HOSPITAL DE PENCO-LIRQUÉN - Autoclaves Raypa | AI19: =+L19+N19+P19+R19+T19+V19+X19+Z19+AB19+AD19+AF19+AH19 -> 0
B20: 10 | C20: SERVICIO DE SALUD TALCAHUANO | D20: HOSPITAL PENCO LIRQUEN | E20: CONTRATACION DE SERVICIOS DE MANTENIMIENTO PREVENTIVO Y CORRECTIVO PARA EQUIPOS AUTOCLAVE, CÁMARA MORTUORIA Y ELEVADOR DE CADÁVERES DEL HOSPITAL DE PENCO-LIRQUÉN - Autoclave 21ED | F20: 1057540-14-LE24 | G20: 44287 | H20: 46113 | I20: 749700 | J20: 22.06.006.003 | AB20: 749700 | AI20: =+L20+N20+P20+R20+T20+V20+X20+Z20+AB20+AD20+AF20+AH20 -> 749700
B21: 11 | C21: SERVICIO DE SALUD TALCAHUANO | D21: HOSPITAL PENCO LIRQUEN | E21: CONVENIO DE MANTENCION PARA EQUIPOS OFTALMOLÓGICOS | F21: 1057540-61-LE24 | G21: 45509 | H21: 46239 | I21: 3570000 | J21: 22.06.006.003 | N21: 773500 | AB21: 2796500 | AI21: =+L21+N21+P21+R21+T21+V21+X21+Z21+AB21+AD21+AF21+AH21 -> 3570000
B22: 12 | C22: SERVICIO DE SALUD TALCAHUANO | D22: HOSPITAL PENCO LIRQUEN | E22: CONVENIO DE MANTENIMIENTO NASOFIBROSCOPIO | F22: PENDIENTE | I22: 250000 | J22: 22.06.006.003 | T22: 200000 | AI22: =+L22+N22+P22+R22+T22+V22+X22+Z22+AB22+AD22+AF22+AH22 -> 200000
B23: 13 | C23: SERVICIO DE SALUD TALCAHUANO | D23: HOSPITAL PENCO LIRQUEN | E23: MANTENIMIENTO EQUIPOS DE LABORATORIO | F23: 1057540-16-LE24 | G23: 45377 | H23: 46107 | I23: 1719550 | J23: 22.06.006.003 | T23: 1719550 | AI23: =+L23+N23+P23+R23+T23+V23+X23+Z23+AB23+AD23+AF23+AH23 -> 1719550
B24: 14 | C24: SERVICIO DE SALUD TALCAHUANO | D24: HOSPITAL PENCO LIRQUEN | E24: CONVENIO DE MANTENIMIENTO CORRECTIVO PARA EQUIPOS DE LAPAROSCOPIA Y ARTROSCOPIA | F24: PENDIENTE | I24: 7380000 | J24: 22.06.006.003 | Z24: 7380000 | AI24: =+L24+N24+P24+R24+T24+V24+X24+Z24+AB24+AD24+AF24+AH24 -> 7380000
B25: 15 | C25: SERVICIO DE SALUD TALCAHUANO | D25: HOSPITAL PENCO LIRQUEN | E25: CONVENIO MANTENCION EQUIPOS OTORRINO- Video oculo instagmografo VNG | F25: PENDIENTE | I25: 600000 | J25: 22.06.006.003 | R25: 600000 | AI25: =+L25+N25+P25+R25+T25+V25+X25+Z25+AB25+AD25+AF25+AH25 -> 600000
B26: 16 | C26: SERVICIO DE SALUD TALCAHUANO | D26: HOSPITAL PENCO LIRQUEN | E26: SERVICIO DE MANTENIMIENTO PREVENTIVO Y CORRECTIVO PARA EQUIPOS DE UNIDAD DE MEDICINA FISICA Y REHABILITACION Y NEUROLOGIA DEL HOSPITAL DE PENCO-LIRQUEN | F26: 1057540-78-LE23 | G26: 45202 | H26: 45933 | I26: 4116500 | J26: 22.06.006.003 | P26: 4116500 | AI26: =+L26+N26+P26+R26+T26+V26+X26+Z26+AB26+AD26+AF26+AH26 -> 4116500
B27: 17 | C27: SERVICIO DE SALUD TALCAHUANO | D27: HOSPITAL PENCO LIRQUEN | E27: SERVICIO DE MANTENIMIENTO PREVENTIVO Y CORRECTIVO PARA MESAS QUIRURGICAS DEL HOSPITAL DE PENCO-LIRQUEN. Mesa Maquet SN 1848 y Mesa Schmitz SN 17453 | F27: 1057540-70-LE23 | G27: 45140 | H27: 45871 | I27: 535500 | J27: 22.06.006.003 | P27: 535500 | AI27: =+L27+N27+P27+R27+T27+V27+X27+Z27+AB27+AD27+AF27+AH27 -> 535500
B28: 17.1 | C28: SERVICIO DE SALUD TALCAHUANO | D28: HOSPITAL PENCO LIRQUEN | E28: SERVICIO DE MANTENIMIENTO PREVENTIVO Y CORRECTIVO PARA MESAS QUIRURGICAS DEL HOSPITAL DE PENCO-LIRQUEN. Mesa Maquet SN 1848 y Mesa Schmitz SN 17453 (SEGUNDO SEMESTRE) | F28: PENDIENTE | I28: 1071000 | J28: 22.06.006.003 | AB28: 1071000 | AI28: =+L28+N28+P28+R28+T28+V28+X28+Z28+AB28+AD28+AF28+AH28 -> 1071000
B29: 18 | C29: SERVICIO DE SALUD TALCAHUANO | D29: HOSPITAL PENCO LIRQUEN | E29: SERVICIO DE MANTENIMIENTO PREVENTIVO Y CORRECTIVO DE Ecografos GE | F29: 1057540-17-LE23 | G29: 45028 | H29: 45759 | I29: 4165000 | J29: 22.06.006.003 | N29: 4165000 | AI29: =+L29+N29+P29+R29+T29+V29+X29+Z29+AB29+AD29+AF29+AH29 -> 4165000
B30: 18.1 | C30: SERVICIO DE SALUD TALCAHUANO | D30: HOSPITAL PENCO LIRQUEN | E30: SERVICIO DE MANTENIMIENTO PREVENTIVO Y CORRECTIVO DE Ecografos GE (SEGUNDO SEMESTRE) | F30: PENDIENTE | I30: 4998000 | J30: 22.06.006.003 | AB30: 4998000 | AI30: =+L30+N30+P30+R30+T30+V30+X30+Z30+AB30+AD30+AF30+AH30 -> 4998000
B31: 19 | C31: SERVICIO DE SALUD TALCAHUANO | D31: HOSPITAL PENCO LIRQUEN | E31: SERVICIO DE MANTENIMIENTO PREVENTIVO Y CORRECTIVO DE CAMAS CLINICAS ELECTRICAS | F31: 1057540-128-LE23 | G31: 45306 | H31: 46037 | I31: 9520000 | J31: 22.06.006.003 | N31: 9520000 | AI31: =+L31+N31+P31+R31+T31+V31+X31+Z31+AB31+AD31+AF31+AH31 -> 9520000
B32: 20 | C32: SERVICIO DE SALUD TALCAHUANO | D32: HOSPITAL PENCO LIRQUEN | E32: SERVICIO MANTENIMIENTO PREVENTIVO, CORRECTIVO Y DE EMERGENCIA PARA EQUIPOS MEDICOS DE RX Y MAMOGRAFO- Mamógrafo (Siemens) ENE-MAR | F32: 1057540-3-LQ23 | G32: 45006 | H32: 45709 | I32: 6072390 | J32: 22.06.006.003 | L32: =1214478+(1214478*2) -> 3643434 | N32: 1214478 | P32: 1214478 | AI32: =+L32+N32+P32+R32+T32+V32+X32+Z32+AB32+AD32+AF32+AH32 -> 6072390
B33: 20.1 | C33: SERVICIO DE SALUD TALCAHUANO | D33: HOSPITAL PENCO LIRQUEN | E33: SERVICIO MANTENIMIENTO PREVENTIVO, CORRECTIVO Y DE EMERGENCIA PARA EQUIPOS MEDICOS DE RX Y MAMOGRAFO- Mamógrafo (Siemens) ABR-DIC | F33: PENDIENTE | I33: 34890156 | J33: 22.06.006.003 | R33: 3876684 | T33: 3876684 | V33: 3876684 | X33: 3876684 | Z33: 3876684 | AB33: 3876684 | AD33: 3876684 | AF33: 3876684 | AH33: 3876684 | AI33: =+L33+N33+P33+R33+T33+V33+X33+Z33+AB33+AD33+AF33+AH33 -> 34890156
B34: 21 | C34: SERVICIO DE SALUD TALCAHUANO | D34: HOSPITAL PENCO LIRQUEN | E34: SERVICIO MANTENIMIENTO PREVENTIVO, CORRECTIVO Y DE EMERGENCIA PARA EQUIPOS MEDICOS DE RX Y MAMOGRAFO Osteopulmonar ENE-MAR | F34: 1057540-3-LQ24 | G34: 45006 | H34: 45709 | I34: 16615375 | J34: 22.06.006.003 | L34: =3323075+(3323075*2) -> 9969225 | N34: 3323075 | P34: 3323075 | AI34: =+L34+N34+P34+R34+T34+V34+X34+Z34+AB34+AD34+AF34+AH34 -> 16615375
B35: 21.2 | C35: SERVICIO DE SALUD TALCAHUANO | D35: HOSPITAL PENCO LIRQUEN | E35: SERVICIO MANTENIMIENTO PREVENTIVO, CORRECTIVO Y DE EMERGENCIA PARA EQUIPOS MEDICOS DE RX Y MAMOGRAFO Osteopulmonar ABR-DIC | F35: PENDIENTE | I35: 33699370 | J35: 22.06.006.003 | R35: 3744374.5 | T35: 3744374.5 | V35: 3744374.5 | X35: 3744374.5 | Z35: 3744374.5 | AB35: 3744374.5 | AD35: 3744374.5 | AF35: 3744374.5 | AH35: 3744374.5 | AI35: =+L35+N35+P35+R35+T35+V35+X35+Z35+AB35+AD35+AF35+AH35 -> 33699370
B36: 21.3 | C36: SERVICIO DE SALUD TALCAHUANO | D36: HOSPITAL PENCO LIRQUEN | E36: SERVICIO MANTENIMIENTO PREVENTIVO, CORRECTIVO Y DE EMERGENCIA PARA EQUIPOS MEDICOS DE RX Y MAMOGRAFO RX portátil ENE-MAR | F36: 1057540-3-LQ24 | G36: 45006 | H36: 45709 | I36: 10040625 | J36: 22.06.006.003 | L36: =2008125+(2008125*2) -> 6024375 | N36: 2008125 | P36: 2008125 | AI36: =+L36+N36+P36+R36+T36+V36+X36+Z36+AB36+AD36+AF36+AH36 -> 10040625
B37: 21.4 | C37: SERVICIO DE SALUD TALCAHUANO | D37: HOSPITAL PENCO LIRQUEN | E37: SERVICIO MANTENIMIENTO PREVENTIVO, CORRECTIVO Y DE EMERGENCIA PARA EQUIPOS MEDICOS DE RX Y MAMOGRAFO RX portátil ABR-DIC | F37: PENDIENTE | I37: 25895553 | J37: 22.06.006.003 | R37: 2877279.7 | T37: 2877280.7 | V37: 2877281.7 | X37: 2877282.7 | Z37: 2877283.7 | AB37: 2877284.7 | AD37: 2877285.7 | AF37: 2877286.7 | AH37: 2877287.7 | AI37: =+L37+N37+P37+R37+T37+V37+X37+Z37+AB37+AD37+AF37+AH37 -> 25895553
B38: 21.5 | C38: SERVICIO DE SALUD TALCAHUANO | D38: HOSPITAL PENCO LIRQUEN | E38: SERVICIO MANTENIMIENTO PREVENTIVO, CORRECTIVO Y DE EMERGENCIA PARA EQUIPOS MEDICOS DE RX Y MAMOGRAFO Arco C (Philips) ENE-MAR | F38: 1057540-3-LQ24 | G38: 45006 | H38: 45709 | I38: 5330210 | J38: 22.06.006.003 | L38: =1066042+(1066042*2) -> 3198126 | N38: 1066042 | P38: 1066042 | AI38: =+L38+N38+P38+R38+T38+V38+X38+Z38+AB38+AD38+AF38+AH38 -> 5330210
B39: 21.6 | C39: SERVICIO DE SALUD TALCAHUANO | D39: HOSPITAL PENCO LIRQUEN | E39: SERVICIO MANTENIMIENTO PREVENTIVO, CORRECTIVO Y DE EMERGENCIA PARA EQUIPOS MEDICOS DE RX Y MAMOGRAFO Arco C (Philips) ABR-MAR | F39: PENDIENTE | I39: 13906971 | J39: 22.06.006.003 | R39: 1545215 | T39: 1545216 | V39: 1545217 | X39: 1545218 | Z39: 1545219 | AB39: 1545220 | AD39: 1545221 | AF39: 1545222 | AH39: 1545223 | AI39: =+L39+N39+P39+R39+T39+V39+X39+Z39+AB39+AD39+AF39+AH39 -> 13906971
B40: 22 | C40: SERVICIO DE SALUD TALCAHUANO | D40: HOSPITAL PENCO LIRQUEN | E40: CONVENIO DE MANTENIMIENTO EQUIPOS OTORRINO (Cámara silente, impedanciometro y audiometro) | F40: 1057540-20-LE24 | G40: 45400 | H40: 46130 | I40: 6650000 | J40: 22.06.006.003 | R40: 6650000 | AI40: =+L40+N40+P40+R40+T40+V40+X40+Z40+AB40+AD40+AF40+AH40 -> 6650000
B41: 23 | C41: SERVICIO DE SALUD TALCAHUANO | D41: HOSPITAL PENCO LIRQUEN | E41: CONVENIO SERVICIO DE MANTENIMIENTO PREVENTIVO Y CORRECTIVO RX DENTAL Y ECOGRAFO SAMSUNG | F41: 1057540-49-LE23 | G41: 45083 | H41: 45814 | I41: 452200 | J41: 22.06.006.003 | N41: 285600 | P41: 166600 | AI41: =+L41+N41+P41+R41+T41+V41+X41+Z41+AB41+AD41+AF41+AH41 -> 452200
B42: 23.1 | C42: SERVICIO DE SALUD TALCAHUANO | D42: HOSPITAL PENCO LIRQUEN | E42: CONVENIO SERVICIO DE MANTENIMIENTO PREVENTIVO Y CORRECTIVO RX DENTAL Y ECOGRAFO SAMSUNG (2DO SEMESTRE) | F42: PENDIENTE | I42: 747920 | J42: 22.06.006.003 | Z42: 548000 | AB42: 199920 | AI42: =+L42+N42+P42+R42+T42+V42+X42+Z42+AB42+AD42+AF42+AH42 -> 747920
B43: 24 | C43: SERVICIO DE SALUD TALCAHUANO | D43: HOSPITAL PENCO LIRQUEN | E43: MANTENIMIENTO EQUIPOS AUTOCLAVES ESTERILIZACION - AUTOCLAVES MATACHANA | F43: 1057540-38-LE23 | G43: 45077 | H43: 45808 | I43: 4275000 | J43: 22.06.006.003 | P43: 4275000 | AI43: =+L43+N43+P43+R43+T43+V43+X43+Z43+AB43+AD43+AF43+AH43 -> 4275000
B44: 24.1 | C44: SERVICIO DE SALUD TALCAHUANO | D44: HOSPITAL PENCO LIRQUEN | E44: MANTENIMIENTO EQUIPOS AUTOCLAVES ESTERILIZACION - AUTOCLAVES MATACHANA (2DO SEMESTRE) | F44: PENDIENTE | I44: 4400000 | J44: 22.06.006.003 | AD44: 4400000 | AI44: =+L44+N44+P44+R44+T44+V44+X44+Z44+AB44+AD44+AF44+AH44 -> 4400000
B45: 25 | C45: SERVICIO DE SALUD TALCAHUANO | D45: HOSPITAL PENCO LIRQUEN | E45: CONVENIO DE MANTENIMIENTO PREVENTIVO Y CORRECTIVO PARA CUNAS RADIANTES | F45: 1057540-83-LE23 | G45: 45166 | H45: 45897 | I45: 1286662 | J45: 22.06.006.003 | Z45: 1286662 | AI45: =+L45+N45+P45+R45+T45+V45+X45+Z45+AB45+AD45+AF45+AH45 -> 1286662
B46: 26 | C46: SERVICIO DE SALUD TALCAHUANO | D46: HOSPITAL PENCO LIRQUEN | E46: CONVENIO DE MANTENIMIENTO PREVENTIVO Y CORRECTIVO PARA COLUMNAS, LÁMPARAS Y PANTALLAS DE PABELLÓN CENTRAL | F46: PENDIENTE | I46: 1428000 | J46: 22.06.006.003 | AB46: 1428000 | AI46: =+L46+N46+P46+R46+T46+V46+X46+Z46+AB46+AD46+AF46+AH46 -> 1428000
B47: 27 | C47: SERVICIO DE SALUD TALCAHUANO | D47: HOSPITAL PENCO LIRQUEN | E47: CONVENIO MANTENIM IENTO EQUIPOS DE PABELLÓN Y GINECOLOGIA - ELECTROBISTURÍ INCUBADORAS | F47: 1057540-110-LE23 | G47: 45247 | H47: 45978 | I47: 640000 | J47: 22.06.006.003 | P47: 640000 | AI47: =+L47+N47+P47+R47+T47+V47+X47+Z47+AB47+AD47+AF47+AH47 -> 640000
B48: 27.1 | C48: SERVICIO DE SALUD TALCAHUANO | D48: HOSPITAL PENCO LIRQUEN | E48: CONVENIO MANTENIM IENTO EQUIPOS DE PABELLÓN Y GINECOLOGIA - ELECTROBISTURÍ INCUBADORAS (2DO SEMESTRE) | F48: PENDIENTE | I48: 650000 | J48: 22.06.006.003 | AB48: 650000 | AI48: =+L48+N48+P48+R48+T48+V48+X48+Z48+AB48+AD48+AF48+AH48 -> 650000
B49: 27.2 | C49: SERVICIO DE SALUD TALCAHUANO | D49: HOSPITAL PENCO LIRQUEN | E49: CONVENIO MANTENIM IENTO EQUIPOS DE PABELLÓN Y GINECOLOGIA - MONITOFES Y DETECTORES CARDIOFETALES Y EQUIPO DE ISQUEMIA | F49: PENDIENTE | I49: 280000 | J49: 22.06.006.003 | AB49: 280000 | AI49: =+L49+N49+P49+R49+T49+V49+X49+Z49+AB49+AD49+AF49+AH49 -> 280000
B50: 28 | C50: SERVICIO DE SALUD TALCAHUANO | D50: HOSPITAL PENCO LIRQUEN | E50: CONVENIO MANTENIM IENTO EQUIPOS DE PABELLÓN Y GINECOLOGIA - VENTILADORES MECÁNICOS | F50: 1057540-101-LE23 | G50: 45232 | H50: 45963 | I50: 7426338 | J50: 22.06.006.003 | P50: 7426338 | AI50: =+L50+N50+P50+R50+T50+V50+X50+Z50+AB50+AD50+AF50+AH50 -> 7426338
B51: 28.1 | C51: SERVICIO DE SALUD TALCAHUANO | D51: HOSPITAL PENCO LIRQUEN | E51: CONVENIO MANTENIM IENTO EQUIPOS DE PABELLÓN Y GINECOLOGIA - VENTILADORES MECÁNICOS (SEGUNDO SEMESTRE) | F51: PENDIENTE | I51: 2918416 | J51: 22.06.006.003 | AB51: 2918416 | AI51: =+L51+N51+P51+R51+T51+V51+X51+Z51+AB51+AD51+AF51+AH51 -> 2918416
B52: 29 | C52: SERVICIO DE SALUD TALCAHUANO | D52: HOSPITAL PENCO LIRQUEN | E52: CONVENIO MANTENIMIENTO EQUIPOS LAVADORA ULTRASONICA | F52: 1057540-129-LE23 | G52: 45303 | H52: 46034 | I52: 1600000 | J52: 22.06.006.003 | P52: 1600000 | AI52: =+L52+N52+P52+R52+T52+V52+X52+Z52+AB52+AD52+AF52+AH52 -> 1600000
B53: 30 | C53: SERVICIO DE SALUD TALCAHUANO | D53: HOSPITAL PENCO LIRQUEN | E53: CONVENIO MANTENIMIENTO EQUIPOS PATRONES | F53: PENDIENTE | I53: 4000000 | J53: 22.06.006.003 | P53: 4000000 | AI53: =+L53+N53+P53+R53+T53+V53+X53+Z53+AB53+AD53+AF53+AH53 -> 4000000
B54: 31 | C54: SERVICIO DE SALUD TALCAHUANO | D54: HOSPITAL PENCO LIRQUEN | E54: CONVENIO MANTENIMIENTO CENTRAL DE MONITOREO | F54: PENDIENTE | I54: 1500000 | J54: 22.06.006.003 | P54: 750000 | AB54: 750000 | AI54: =+L54+N54+P54+R54+T54+V54+X54+Z54+AB54+AD54+AF54+AH54 -> 1500000
B55: 32 | D55: HOSPITAL PENCO LIRQUEN | E55: CONVENIO MANTENIMIENTO EQUIPOS MOTORES IMPLANTES | F55: PENDIENTE | I55: 185640 | J55: 22.06.006.003 | X55: 185640 | AI55: =+L55+N55+P55+R55+T55+V55+X55+Z55+AB55+AD55+AF55+AH55 -> 185640
B56: 33 | C56: SERVICIO DE SALUD TALCAHUANO | D56: HOSPITAL PENCO LIRQUEN | E56: CONVENIO MANTENIMIENTO EQUIPOS HOLTER PRESIÓN Y CALENTADOR PACIENTES | F56: PENDIENTE | I56: 2000000 | J56: 22.06.006.003 | AI56: =+L56+N56+P56+R56+T56+V56+X56+Z56+AB56+AD56+AF56+AH56 -> 0
B57: 34 | C57: SERVICIO DE SALUD TALCAHUANO | D57: HOSPITAL PENCO LIRQUEN | E57: CONVENIO MANTENIMIENTO CAD CAM | I57: 2142000 | J57: 22.06.006.004 | AD57: 2142000 | AI57: =+L57+N57+P57+R57+T57+V57+X57+Z57+AB57+AD57+AF57+AH57 -> 2142000
B58: 35 | C58: SERVICIO DE SALUD TALCAHUANO | D58: HOSPITAL PENCO LIRQUEN | E58: CONVENIO MANTENIMIENTO TAC (OCT-NOV-DIC 2025) | I58: 17272441 | J58: 22.06.006.005 | AD58: 5757480.4 | AF58: 5757480.4 | AH58: 5757480.4 | AI58: =+L58+N58+P58+R58+T58+V58+X58+Z58+AB58+AD58+AF58+AH58 -> 17272441
B59: 36 | C59: SERVICIO DE SALUD TALCAHUANO | D59: HOSPITAL PENCO LIRQUEN | E59: CONVENIO MANTENIMIENTO CNAF | I59: 4336752 | J59: 22.06.006.006 | R59: 4336752 | AI59: =+L59+N59+P59+R59+T59+V59+X59+Z59+AB59+AD59+AF59+AH59 -> 4336752
C60: MONTO PREVENTIVO POYECTADO | I60: =SUM(I8:I59) -> 3.2127609e+08
B62: SEGUIMIENTO GASTO MANTENIMIENTO CORRECTIVO / ADQUISICIÓN DE REPUESTOS / ADQUISICIÓN DE INSUMOS / ADQUISICIÓN DE ACCESORIOS
I64: CONTROL MENSUAL EJECUCIÓN
I65: ENERO | K65: FEBRERO | M65: MARZO | O65: ABRIL | Q65: MAYO | S65: JUNIO | U65: JULIO | W65: AGOSTO | Y65: SEPTIEMBRE | AA65: OCTUBRE | AC65: NOVIEMBRE | AE65: DICIEMBRE
B66: Nº | C66: SERVICIO DE SALUD | D66: ESTABLECIMIENTO | E66: DESCRIPCIÓN DE LA COMPRA | F66: TIPO DE GASTO CORRECTIVO | G66: MONTO | H66: SUBASIGNACIÓN SIGFE | I66: N° ORDEN DE COMPRA | J66: MONTO ($) | K66: N° ORDEN DE COMPRA | L66: MONTO ($) | M66: N° ORDEN DE COMPRA | N66: MONTO ($) | O66: N° ORDEN DE COMPRA | P66: MONTO ($) | Q66: N° ORDEN DE COMPRA | R66: MONTO ($) | S66: N° ORDEN DE COMPRA | T66: MONTO ($) | U66: N° ORDEN DE COMPRA | V66: MONTO ($) | W66: N° ORDEN DE COMPRA | X66: MONTO ($) | Y66: N° ORDEN DE COMPRA | Z66: MONTO ($) | AA66: N° ORDEN DE COMPRA | AB66: MONTO ($) | AC66: N° ORDEN DE COMPRA | AD66: MONTO ($) | AE66: N° ORDEN DE COMPRA | AF66: MONTO ($) | AG66: TOTAL
B67: 1 | C67: Servicio de Salud Talcahuano | D67: Hospital Penco Lirquén | F67: MANTENIMIENTO CORRECTIVO | G67: 80000000 | H67: 22.06.006.004 | J67: 6666666.7 | L67: 6666666.7 | N67: 6666666.7 | P67: 6666666.7 | R67: 6666666.7 | T67: 6666666.7 | V67: 6666666.7 | X67: 6666666.7 | Z67: 6666666.7 | AB67: 6666666.7 | AD67: 6666666.7 | AF67: 6666666.7 | AG67: =SUM(AF67,AD67,AB67,Z67,X67,V67,T67,R67,P67,N67,L67,J67) -> 80000000
B68: 3 | E68: MC - Cambio tarjeta ECG Monitor Fukuda Denshi Hospitalizados | F68: MANTENIMIENTO CORRECTIVO | G68: 990000 | H68: 22.06.006.004 | J68: 990000 | AG68: =SUM(AF68,AD68,AB68,Z68,X68,V68,T68,R68,P68,N68,L68,J68) -> 990000
B69: 4 | E69: Repuestos Autoclave Matachana E-31058 segun MP oct 2024 | F69: MANTENIMIENTO CORRECTIVO | G69: 1637440 | H69: 22.06.006.004 | J69: 1637440 | AG69: =SUM(AF69,AD69,AB69,Z69,X69,V69,T69,R69,P69,N69,L69,J69) -> 1637440
B70: 5 | E70: Repuestos Autoclave Matachana E-31059 segun MP oct 2024 | F70: MANTENIMIENTO CORRECTIVO | G70: 1904000 | H70: 22.06.006.004 | J70: 1904000 | AG70: =SUM(AF70,AD70,AB70,Z70,X70,V70,T70,R70,P70,N70,L70,J70) -> 1904000
B71: 6 | H71: 22.06.006.004
B72: 7 | H72: 22.06.006.004
B73: 8 | H73: 22.06.006.004
C74: MONTO CORRECTIVO PROYECTADO | G74: =SUM(G67:G70) -> 84531440

Sheet Hoja1
A3: Bodega de Equipos Médicos | B3: Hospital Penco Lirquen | C3: Otros | D3: Alto Costo | E3: Analizador de monitores | F3: Fluke | G3: Prosim 8 | H3: 4645056 | I3: HPL29951 | J3: 2019 | K3: 10 | L3: =+IF(J3=0," ",K3-('CATASTRO Y PLANIFICACIÓN MP'!$B$9-J3)) -> 3 | M3: Propio | N3: Bueno | O3: IM ≥ 12 | P3: NO | Q3: NO APLICA | R3: SI | S3: 2024 | T3: EXTERNO | U3: NO APLICA | V3: POR LICITAR | X3: 1 | AF3: ꓣ | AK3: NO | AL3: NO | AM3: NO | AP3: 18
A4: Bodega de Equipos Médicos | B4: Hospital Penco Lirquen | C4: Otros | D4: Alto Costo | E4: Analizador de pruebas eléctricas | F4: Fluke | G4: ESA612 | H4: 4648049 | I4: HPL29953 | J4: 2019 | K4: 10 | L4: =+IF(J4=0," ",K4-('CATASTRO Y PLANIFICACIÓN MP'!$B$9-J4)) -> 3 | M4: Propio | N4: Bueno | O4: IM ≥ 12 | P4: NO | Q4: NO APLICA | R4: SI | S4: 2024 | T4: EXTERNO | U4: NO APLICA | V4: POR LICITAR | X4: 1 | AF4: ꓣ | AK4: NO | AL4: NO | AM4: NO | AP4: 20
A5: Bodega de Equipos Médicos | B5: Hospital Penco Lirquen | C5: Otros | D5: Alto Costo | E5: Analizador desfibrilador y ecg | F5: Fluke | G5: Impulse 700DP | H5: 4648020 | I5: HPL29952 | J5: 2019 | K5: 10 | L5: =+IF(J5=0," ",K5-('CATASTRO Y PLANIFICACIÓN MP'!$B$9-J5)) -> 3 | M5: Propio | N5: Bueno | O5: IM ≥ 12 | P5: NO | Q5: NO APLICA | R5: SI | S5: 2024 | T5: EXTERNO | U5: NO APLICA | V5: POR LICITAR | X5: 1 | AF5: ꓣ | AK5: NO | AL5: NO | AM5: NO | AP5: 19

Sheet Hoja2
A1: Bodega de Equipos Médicos | B1: Hospital Penco Lirquen | C1: Apoyo Quirúrgico | D1: Alto Costo | E1: Mesa quirúrgica | F1: KTK | G1: 2080 | H1: 3173 | I1: HPL29873 | J1: 2016 | K1: 10 | L1: =+IF(J1=0," ",K1-('CATASTRO Y PLANIFICACIÓN MP'!$B$9-J1)) -> 0 | M1: Propio | N1: Bueno | O1: NO APLICA | P1: NO | Q1: NO APLICA | R1: NO | T1: INTERNO | U1: TECNICO EQM HPL | V1: NO APLICA | AK1: si | AL1: si | AM1: no | AN1: si | AO1: Equipo de baja operacional | AP1: 17
A2: reprocesadora medivators: porque tiene monto de mp
A3: Especialidades Dental - 12 | B3: Hospital Penco Lirquen | C3: Odontología | D3: Mediano Costo | E3: Unidad dental | F3: Dabi Atlante | G3: Croma SF | H3: K000915 | I3: HPL18752 | J3: 2016 | K3: 8 | L3: =+IF(J3=0," ",K3-('CATASTRO Y PLANIFICACIÓN MP'!$B$9-J3)) -> -2 | M3: Propio | N3: Bueno | O3: IM ≥ 12 | P3: NO | Q3: NO APLICA | R3: SI | S3: 2023 | T3: CONTRATO | U3: RIGOBERTO FUICA | V3: 1057540-115-LE23 | W3: 300000 | X3: 3 | Z3: X | AD3: X | AH3: X | AK3: NO | AL3: NO | AM3: NO | AN3: SI | AO3: Corresponde 1 según orientación técnica, se programan 3 por equipos viejos. | AP3: 137
A4: Especialidades Dental - 12 | B4: Hospital Penco Lirquen | C4: Odontología | D4: Mediano Costo | E4: Unidad dental | F4: Dabi Atlante | G4: Croma plus | H4: k026826 | I4: HPL18708 | J4: 2015 | K4: 8 | L4: =+IF(J4=0," ",K4-('CATASTRO Y PLANIFICACIÓN MP'!$B$9-J4)) -> -3 | M4: Propio | N4: Bueno | O4: IM ≥ 12 | P4: NO | Q4: NO APLICA | R4: SI | S4: 2023 | T4: CONTRATO | U4: RIGOBERTO FUICA | V4: 1057540-115-LE23 | W4: 300000 | X4: 3 | Z4: X | AD4: X | AH4: X | AK4: NO | AL4: NO | AM4: NO | AN4: SI | AO4: Corresponde 1 según orientación técnica, se programan 3 por equipos viejos. | AP4: 138
E5: Espirómetro portátil | F5: MGC diagnostics | G5: CPF-S7D | H5: 220004754 | I5: eliminado de programacion
A6: Ginecologia Hospitalizados - 2 | B6: Hospital Penco Lirquen | C6: Mobiliario | D6: Clínico | E6: Cama clínica eléctrica | F6: Malvestio | G6: 345500 | H6: 20009247 | I6: HPL29987 | J6: 2015 | K6: 8 | L6: =+IF(J6=0," ",K6-('CATASTRO Y PLANIFICACIÓN MP'!$B$9-J6)) -> -3 | M6: Propio | N6: Bueno | O6: IM ≥ 12 | P6: NO | Q6: NO APLICA | R6: SI | S6: 2023 | T6: CONTRATO | U6: SERVITEC | V6: 1057540-128-LE23 | X6: 1 | AO6: No corresponde según orientanción técnica, debería hacerse al menos cada 2 años | AP6: 295
A8: Rehabilitacion Integral | B8: Hospital Penco Lirquen | C8: Med. Física Rehabilitación | D8: Bajo costo | E8: Cicloergómetro de mano | F8: S/M | G8: S/M | H8: S/N | I8: HPL30288 | J8: 2016 | K8: 8 | L8: =+IF(J8=0," ",K8-('CATASTRO Y PLANIFICACIÓN MP'!$B$9-J8)) -> -2 | M8: Propio | N8: Bueno | O8: IM ≥ 12 | P8: NO | Q8: NO APLICA | R8: SI | S8: 2024 | T8: INTERNO | U8: TECNICO EQM HPL | V8: NO APLICA | X8: 1 | AH8: X | AO8: Comprar materiales para realizar interno | AP8: 716
A9: UTI - 1C | B9: Hospital Penco Lirquen | C9: Apoyo Terapéutico | D9: Mediano Costo | E9: Sistema de alto flujo humidificado | F9: Fisher & Paykel Healthcare | G9: Airvo 2 | H9: 200611138798 | I9: HPL30169 | J9: 2021 | K9: 8 | L9: =+IF(J9=0," ",K9-('CATASTRO Y PLANIFICACIÓN MP'!$B$9-J9)) -> 3 | M9: Propio | N9: Bueno | O9: NO APLICA | P9: NO | Q9: NO APLICA | R9: NO | S9: 2025 | T9: EXTERNO | U9: PENDIENTE | V9: PENDIENTE | W9: 394250 | X9: 1 | AB9: X | AP9: 916
A10: Laboratorio | B10: Hospital Penco Lirquen | C10: Laboratorio/Farmac | D10: Bajo costo | E10: Mecheros portátiles | F10: Aleman | G10: Bunsen | H10: S/N | I10: HPL30331 | J10: 2016 | K10: 8 | L10: =+IF(J10=0," ",K10-('CATASTRO Y PLANIFICACIÓN MP'!$B$9-J10)) -> -2 | N10: Bueno | O10: NO APLICA | P10: NO | Q10: NO APLICA | R10: NO | T10: INTERNO | AP10: 506

Sheet proyeccion correctivos
K3: valor sin tubo RX
N4: ENERO | O4: FEBRERO | P4: MARZO | Q4: ABRIL | R4: MAYO | S4: JUNIO | T4: JULIO | U4: AGOSTO | V4: SEPTIEMBRE | W4: OCTUBRE | X4: NOVIEMBRE | Y4: DICIEMBRE
G5: monto correctivo ejecutado 2022 | J5: 129749412 | K5: 94225664 | N5: 4459177 | O5: 1311202 | P5: 13789874 | Q5: 3426160 | R5: 14399436 | S5: 5868931 | T5: 2552550 | U5: 4225484 | V5: 299499 | W5: 5035543 | X5: 2929780 | Y5: 35928028
G6: monto correctivo ejecutado 2023 | J6: 68625151 | K6: 68625151 | N6: $- | O6: 14329317 | P6: $- | Q6: $- | R6: 813246 | S6: 1251787 | T6: 9930855 | U6: 16471977 | V6: 2647750 | W6: 12606091 | X6: 7355374 | Y6: 3218754
G7: monto correctivo ejecutado 2024 | J7: 117827422 | K7: 63843665 | N7: 33320 | O7: 2975000 | P7: 6260827 | Q7: 5229842 | R7: 15315413 | S7: 6872007 | T7: 1677900 | U7: 6807078 | V7: 1892100 | W7: 3847165 | X7: 0 | Y7: 0
G8: monto proyectado 2025 | J8: 80000000 | N8: =$J$8/12 -> 6666666.7 | O8: =$J$8/12 -> 6666666.7 | P8: =$J$8/12 -> 6666666.7 | Q8: =$J$8/12 -> 6666666.7 | R8: =$J$8/12 -> 6666666.7 | S8: =$J$8/12 -> 6666666.7 | T8: =$J$8/12 -> 6666666.7 | U8: =$J$8/12 -> 6666666.7 | ... Y8: =$J$8/12 -> 6666666.7
